Workbook

Sheet Chek
B3: ДВД
A4: Договорн. стоймость обьектов: | B4: 2.1352396e+08 | C4: 2.1352396e+08 | D4: =B4-C4 -> 0
A5: Сданы по фактуре: | B5: 2.2553272e+08 | C5: 2.2553272e+08 | D5: =B5-C5 -> 0
A6: Всего оплачено: | B6: 2.1192651e+08 | C6: 2.1192651e+08 | D6: =B6-C6 -> 0
A7: Осталось по договор.: | B7: 1721212.6 | C7: 1721212.6 | D7: =B7-C7 -> 0
A8: Осталось по сданным: | B8: 13606218 | C8: 13606218 | D8: =B8-C8 -> 0
B11: კორპუსები
A12: Договорн. стоймость обьектов: | D12: =B12-C12 -> 0
A13: Сданы по фактуре: | D13: =B13-C13 -> 0
A14: Всего оплачено: | D14: =B14-C14 -> 0
A15: Осталось по договор.: | D15: =B15-C15 -> 0
A16: Осталось по сданным: | D16: =B16-C16 -> 0
A19: Договорн. стоймость обьектов: | D19: =B19-C19 -> 0
A20: Сданы по фактуре: | D20: =B20-C20 -> 0
A21: Всего оплачено: | D21: =B21-C21 -> 0
A22: Осталось по договор.: | D22: =B22-C22 -> 0
A23: Осталось по сданным: | D23: =B23-C23 -> 0

Sheet PIVOT_ALL
A3: Row Labels | B3: Sum of სულ შესრ 2025 | C3: Sum of ფაქტორ. ხარჯი 2025
A4: 5 | B4: 19 | C4: 69
A5: (Пр)-Архитект-Проджект Компани | B5: 0
A6: (Пр)-Газ Констракт | B6: 40275.55
A7: (Пр)-Газсервис | B7: 0
A8: (Пр)-Джи Пи | B8: 0
A9: (Пр)-Джорджия Газ Проджект | B9: 0
A10: (Пр)-Интер Газ | B10: 0
A11: (Пр)-Интерсервис 2011 | B11: 0
A12: (Пр)-Унимшени | B12: 11102
A13: (Пр)-Циспери Али | B13: 0
A14: Аркмшенсервис | B14: 2971405.6 | C14: 147436.03
A15: Бриджи | B15: 2058818.8
A16: Газ Констракт | B16: 9754642.7 | C16: 40232.14
A17: Газсервис | B17: 6922112 | C17: 262367.49
A18: Джорджия Газ Проджект | B18: 3142978.1 | C18: 31453.45
A19: Интер Газ | B19: 12717647 | C19: 466204.67
A20: Интерсервис 2011 | B20: 3187738 | C20: 28773.66
A21: Унимшени | B21: 3908525 | C21: 68062.52
A22: Энерджи сервис | B22: 2603053.6 | C22: 90214.92
A23: ჰაიდროკორპი | B23: 0
A24: (blank) | B24: 0
A25: Grand Total | B25: 47318317 | C25: 1134813.9

Sheet ДВД
A1: СОКАР ДЖОРДЖИЯ ГАЗ строительство-реабилитация | F1: 283649.11 | H1: =F1-H728 -> -0.00021742599 | Q1: კვანძი T-11 (ახალ. აბონ. მიერთება) | AM1: 5197 | AO1: 70809.72 | BK1: კვანძი (ახალ. აბონ. მიერთება) | BL1: 45639 | BM1: Принят | BN1: SGG | BO1: 45635 | BP1: SGG-C-24-70 | BS1: Yes
B2: Договорн. стоймость обьектов: | D2: =F7 -> 2.1352396e+08 | J2: 27000 | AO2: =AO7-AO1 -> 181174.7
B3: Сданы по фактуре: | D3: =H7 -> 2.2611158e+08 | J3: 1420.98 | BQ3: Yes
B4: Всего оплачено: | D4: =J7 -> 2.1295651e+08 | J4: =J3*1.18 -> 1676.7564
B5: Осталось по договор.: | D5: =K7 -> 691206.24 | J5: =J2+J4 -> 28676.756 | BQ5: No
B6: Осталось по сданным: | D6: =L7 -> 13155069 | H6: =(H1106-3000)/1.18 -> 50847.458 | AU6: 1048112.8 | AX6: 2198778.9 | BA6: 2361095.4 | BE6: 1840117.9
B7: =SUBTOTAL(3,B11:B3497) -> 1243 | C7: =SUBTOTAL(3,C11:C3497) -> 1237 | D7: =SUBTOTAL(3,D11:D3497) -> 1244 | E7: =SUBTOTAL(3,E11:E3497) -> 1244 | F7: =SUBTOTAL(9,F11:F3497) -> 2.1352396e+08 | H7: =SUBTOTAL(9,H11:H3497) -> 2.2611158e+08 | I7: =SUBTOTAL(9,I11:I3497) -> 90222850 | J7: =SUBTOTAL(9,J11:J3497) -> 2.1295651e+08 | K7: =SUBTOTAL(9,K11:K3497) -> 691206.24 | L7: =SUBTOTAL(9,L11:L3497) -> 13155069 | M7: =SUBTOTAL(9,M11:M3497) -> 1247112.5 | N7: =SUBTOTAL(9,N11:N3497) -> 39145851 | P7: =SUBTOTAL(9,P11:P3497) -> 261 | Q7: =SUBTOTAL(3,Q11:Q3497) -> 1212 | R7: =SUBTOTAL(9,R11:R3497) -> 58983622 | S7: =SUBTOTAL(9,S11:S3497) -> 16786679 | T7: =SUBTOTAL(9,T11:T3497) -> 16289115 | U7: =SUBTOTAL(9,U11:U3497) -> 57356.245 | V7: =SUBTOTAL(9,V11:V3497) -> 12456955 | W7: =SUBTOTAL(9,W11:W3497) -> 2484780.2 | X7: =SUBTOTAL(9,X11:X3497) -> 8376742.9 | Y7: =SUBTOTAL(9,Y11:Y3497) -> 1589027 | ... AQ7: =SUBTOTAL(9,AQ11:AQ3497) -> 0 | AR7: =SUBTOTAL(3,AR11:AR3497) -> 17 | AS7: =SUBTOTAL(9,AS11:AS3497) -> 27481391 | AT7: =SUBTOTAL(9,AT11:AT3497) -> 1994631.4 | AU7: =SUBTOTAL(9,AU11:AU3497) -> 1048112.8 | AV7: =SUBTOTAL(9,AV11:AV3497) -> 33780261 | AW7: =SUBTOTAL(9,AW11:AW3497) -> 2845141.9 | AX7: =SUBTOTAL(9,AX11:AX3497) -> 2198778.9 | AY7: =SUBTOTAL(9,AY11:AY3497) -> 32062781 | AZ7: =SUBTOTAL(9,AZ11:AZ3497) -> 1935256.3 | ... BE7: =SUBTOTAL(9,BE11:BE3497) -> 1840117.9 | BG7: =SUBTOTAL(9,BG11:BG3497) -> 30448206 | BJ7: =SUBTOTAL(3,BJ11:BJ3497) -> 856 | BK7: =SUBTOTAL(3,BK11:BK3497) -> 1240 | BL7: =SUBTOTAL(3,BL11:BL3497) -> 1244 | BM7: =SUBTOTAL(3,BM11:BM3497) -> 1244 | BN7: =SUBTOTAL(3,BN11:BN3497) -> 1244 | BO7: =SUBTOTAL(3,BO11:BO3497) -> 28 | BP7: =SUBTOTAL(3,BP11:BP3497) -> 115 | BQ7: =SUBTOTAL(3,BQ11:BQ3497) -> 1045
A9: № пп | B9: Регион | C9: Район/ Город | D9: Обьект | E9: Подрядная организация | F9: Договорная стоймость обьекта | G9: X | H9: Работы сданы по фактуре (A) | I9: ღირებულება პროექტის გარეშე | J9: Оплачено | K9: Осталось от договорн. стоймости | L9: Осталось от сданных работ | M9: Дл. (м) строящ. газопр. | N9: Возможный долг (Д) | O9: 1 | P9: Кол. нов. абон. | Q9: № по бюджету | R9: სულ შესრ 2025 | S9: სულ გად 2025 | T9: I შესრ | U9: I გად | V9: II შესრ | W9: II გად | X9: III შესრ | Y9: III გად | Z9: IV შესრ | AA9: IV გად | AB9: V შესრ | AC9: V გად | AD9: VI შესრ | AE9: VI გად | AF9: VII შესრ | AG9: VII გად | AH9: VIII შესრ | AI9: VIII გად | AJ9: IX შესრ | AK9: IX გად | AL9: X შესრ | AM9: X გად | AN9: XI შესრ | AO9: XI გად | AP9: XII შესრ | AQ9: XII გად | AR9: ჰარე | AS9: ფაქტორ. თანხა 2022 | AT9: ფაქტორ. ხარჯი 2022 | AU9: სხვაობა 2022 | AV9: ფაქტორ. თანხა 2023 | AW9: ფაქტორ. ხარჯი 2023 | AX9: სხვაობა 2023 | AY9: ფაქტორ. თანხა 2024 | AZ9: ფაქტორ. ხარჯი 2024 | BA9: სხვაობა 2024 (1) | BB9: სხვაობა 2024 (2) | BC9: ფაქტორ. თანხა 2025 | BD9: ფაქტორ. ხარჯი 2025 | BE9: სხვაობა 2025 (1) | BF9: სხვაობა 2025 (2) | BG9: ნაწილი მიღებულია ექსპლ. | BH9: ნაწილის ექსპლ. მიღ. თარიღი | BI9: Тип пр. | BJ9: Дата приема | BK9: Статус/прием в эксплуатацию | BL9: Примеч. Или Компания | BM9: Дата закл. договора | BN9: № Догов. | BO9: № Эксп. Сметы | BP9: Регистрация/ კომენტარი | BQ9: Примечание
A10: 1 | B10: 2 | C10: 3 | D10: 4 | E10: 5 | F10: 6 | G10: 7 | H10: 8 | I10: 9 | J10: 10 | K10: 11 | L10: 12 | M10: 13 | N10: 14 | O10: 15 | P10: 16 | Q10: 17 | R10: 19 | S10: 20 | T10: 22 | U10: 23 | V10: 25 | W10: 26 | X10: 28 | Y10: 29 | Z10: 31 | AA10: 32 | AB10: 34 | AC10: 35 | AD10: 37 | AE10: 38 | AF10: 40 | AG10: 41 | AH10: 43 | AI10: 44 | AJ10: 46 | AK10: 47 | AL10: 49 | AM10: 50 | AN10: 52 | AO10: 53 | AP10: 55 | AQ10: 56 | AR10: 57 | AS10: 58 | AT10: 59 | AU10: 60 | AV10: 61 | AW10: 62 | AX10: 63 | AY10: 64 | AZ10: 65 | BA10: 66 | BB10: 67 | BC10: 68 | BD10: 69 | BG10: 70 | BH10: 71 | BI10: 72 | BJ10: 73 | BK10: 74 | BL10: 75 | BM10: 76 | BN10: 77 | BO10: 78 | BP10: 79 | BQ10: 80 | BR10: 81
A11: 700 | B11: Квемо Картли | C11: Болниси | D11: ს. მუშევანის გაზიფიცირების პროექტის შედგენა. | E11: (Пр)-Архитект-Проджект Компани | F11: 26113.5 | G11: 2 | H11: =14922*1.75 -> 26113.5 | J11: =3983.415+22130.085 -> 26113.5 | K11: =F11-J11 -> 0 | L11: =H11-J11 -> 0 | N11: =IF(OR(BK11="принят",BK11="Завершено"),H11-J11,F11-J11) -> 0 | O11: 0 | R11: =T11+V11+X11+Z11+AB11+AD11+AF11+AH11+AJ11+AL11+AN11+AP11 -> 0 | S11: =U11+W11+Y11+AA11+AC11+AE11+AG11+AI11+AK11+AM11+AO11+AQ11 -> 0 | AS11: 0 | AT11: 0 | AU11: 0 | BI11: Проектирование | BJ11: 45625 | BK11: ПриПро | BL11: Сакорггаз | BM11: 45538 | BN11: СС-240903-1/0
A12: 905 | B12: Аджара | C12: Кобулети | D12: ს. მუხაესტატედან ს. ქაქუთამდე მიწისქვეშა გაზსადენის მშენებლობის საპროექტო სამუშაოები. | E12: (Пр)-Унимшени | F12: 0 | G12: 2 | H12: =R12 -> 11102 | J12: =S12 -> 11102 | K12: =F12-J12 -> -11102 | L12: =H12-J12 -> 0 | N12: =IF(OR(BK12="принят",BK12="Завершено"),H12-J12,F12-J12) -> -11102 | O12: 2 | P12: 0 | R12: =T12+V12+X12+Z12+AB12+AD12+AF12+AH12+AJ12+AL12+AN12+AP12 -> 11102 | S12: =U12+W12+Y12+AA12+AC12+AE12+AG12+AI12+AK12+AM12+AO12+AQ12 -> 11102 | AB12: =6344*1.75 -> 11102 | AE12: =1693.53+9408.47 -> 11102 | AS12: 0 | AT12: 0 | AU12: 0 | BI12: Проектирование | BJ12: 45805 | BK12: ПриПро | BL12: SGG | BM12: 45509 | BN12: BSG-240805-2/0 (1) | BP12: GGTC-ს აშენებულმა ქსელმა წნევა ვერ დაიჭირა. | BQ12: No
A13: 980 | B13: Аджара | C13: Кобулети | D13: ს. მუხაესტატედან ს. ქაქუთამდე მიწისქვეშა გაზსადენის სამშენებლო სამუშაოები. | E13: Унимшени | F13: 1200000 | G13: 2 | H13: =R13 -> 738389 | J13: =S13+AV13+AY13+BC13 -> 690000 | K13: =F13-J13 -> 510000 | L13: =H13-J13 -> 48389 | N13: =IF(OR(BK13="принят",BK13="Завершено"),H13-J13,F13-J13) -> 48389 | O13: 1 | R13: =T13+V13+X13+Z13+AB13+AD13+AF13+AH13+AJ13+AL13+AN13+AP13 -> 738389 | S13: =U13+W13+Y13+AA13+AC13+AE13+AG13+AI13+AK13+AM13+AO13+AQ13 -> 105254.22 | V13: 90000 | X13: 200000 | Y13: 13728.81 | Z13: 200000 | AA13: 30508.47 | AB13: 200000 | AC13: 30508.47 | AE13: 30508.47 | AJ13: 48389 | AS13: 0 | AT13: 0 | AU13: 0 | BC13: =76271.19+169491.53+169491.53+169491.53 -> 584745.78 | BD13: =1467.44+24615.74+21592.76+21736.71 -> 69412.65 | BI13: Реаб. | BJ13: 45910 | BK13: Принят | BL13: SGG | BM13: 45509 | BN13: BSG-240805-2/0 (2) | BP13: GGTC-ს აშენებულმა ქსელმა წნევა ვერ დაიჭირა. | BQ13: Yes
A14: 1374 | B14: Имерети | C14: Багдати | D14: Ремонт офиса с/центра Багдади | E14: Газсервис | F14: 69496 | H14: 87450.58 | J14: =87450.58 -> 87450.58 | K14: =F14-J14 -> -17954.58 | L14: =H14-J14 -> 0 | M14: 0 | N14: =IF(OR(BK14="принят",BK14="Завершено"),H14-J14,F14-J14) -> 0 | O14: 0 | R14: =T14+V14+X14+Z14+AB14+AD14+AF14+AH14+AJ14+AL14+AN14+AP14 -> 0 | S14: =U14+W14+Y14+AA14+AC14+AE14+AG14+AI14+AK14+AM14+AO14+AQ14 -> 0 | AS14: 0 | AT14: 0 | AU14: 0 | BI14: Ремонт офиса | BJ14: 44925 | BK14: Принят | BL14: SGG | BM14: 44811 | BN14: SGG-C-22-64 | BQ14: No
A15: 1487 | B15: Шида Картли | C15: Гори | D15: На ул. Размадзе, реаб. Газопр. | E15: Газ Констракт | F15: 65177 | H15: 45857 | J15: 45857 | K15: =F15-J15 -> 19320 | L15: =H15-J15 -> 0 | M15: =865+147 -> 1012 | N15: =IF(OR(BK15="принят",BK15="Завершено",BK15="ПриПро"),H15-J15,F15-J15) -> 0 | O15: 0 | Q15: P.3.115 | R15: =T15+V15+X15+Z15+AB15+AD15+AF15+AH15+AJ15+AL15+AN15+AP15 -> 0 | S15: =U15+W15+Y15+AA15+AC15+AE15+AG15+AI15+AK15+AM15+AO15+AQ15 -> 0 | AS15: 0 | AT15: 0 | AU15: =IF(H15<50000,0,IF(AT15>0,(H15/1.18-AT15-H15/100*0.8)*0.1,(H15/1.18-H15/1.18/100*5.4-H15/100*0.8)*0.1)) -> 0 | BI15: Реаб. | BJ15: 44592 | BK15: Принят | BL15: Сакорггаз | BM15: 44477 | BN15: BC-211008-1/0 | BO15: 120 | BQ15: Yes
A16: 1494 | B16: Самцхе Джавахети | C16: Адигени | D16: В с. Вархани реабилитация подз. Газопровода. | E16: Газ Констракт | F16: 6286 | H16: 2939 | J16: 2939 | K16: =F16-J16 -> 3347 | L16: =H16-J16 -> 0 | M16: 226 | N16: =IF(OR(BK16="принят",BK16="Завершено",BK16="ПриПро"),H16-J16,F16-J16) -> 0 | O16: 0 | Q16: Поручение | R16: =T16+V16+X16+Z16+AB16+AD16+AF16+AH16+AJ16+AL16+AN16+AP16 -> 0 | S16: =U16+W16+Y16+AA16+AC16+AE16+AG16+AI16+AK16+AM16+AO16+AQ16 -> 0 | AS16: 0 | AT16: 0 | AU16: =IF(H16<50000,0,IF(AT16>0,(H16/1.18-AT16-H16/100*0.8)*0.1,(H16/1.18-H16/1.18/100*5.4-H16/100*0.8)*0.1)) -> 0 | BI16: Реаб. | BJ16: 44627 | BK16: принят | BL16: SGG | BM16: 44488 | BN16: BS-211019-1/0 | BO16: 144 | BQ16: Yes
A17: 1496 | B17: Кахети | C17: Лагодехи | D17: Питающий газопровод Цнори-Лагодехи, по направлению Лагодехи | E17: Бриджи | F17: =1197386+53648 -> 1251034 | H17: =405600+228800+416000+200634 -> 1251034 | J17: =150000+150000+61871.19+43000+160000+69528.81+200000+200000+31000+185634+S17 -> 1251034 | K17: =F17-J17 -> 0 | L17: =H17-J17 -> 0 | M17: 11377 | N17: =IF(OR(BK17="принят",BK17="Завершено",BK17="ПриПро"),H17-J17,F17-J17) -> 0 | O17: 0 | P17: 0 | Q17: P.2.6 | R17: =T17+V17+X17+Z17+AB17+AD17+AF17+AH17+AJ17+AL17+AN17+AP17 -> 0 | S17: =U17+W17+Y17+AA17+AC17+AE17+AG17+AI17+AK17+AM17+AO17+AQ17 -> 0 | AS17: 0 | AT17: 0 | AU17: 0 | BI17: Н. Стр. | BJ17: 44620 | BK17: Принят | BL17: SGG | BM17: 44620 | BN17: BS-211018-1/1 | BO17: 1511 | BQ17: Yes
A18: 1619 | B18: Имерети | C18: Самтредия | D18: 1.1.10. Строительство питающего газопровода Самтредиа - Хони. (P.6.115) | E18: Газсервис | F18: 3286000 | H18: =975000+950000+875000+460000+263977.93 -> 3523977.9 | J18: =148728.81+144915.25+133474.58+70169.49+40267.819+AS18+223710.121 -> 3523977.9 | K18: =F18-J18 -> -237977.93 | L18: =H18-J18 -> 0 | M18: 14407 | N18: =IF(OR(BK18="принят",BK18="Завершено",BK18="ПриПро"),H18-J18,F18-J18) -> 4.6566129e-10 | O18: 0 | Q18: P.6.115 | R18: =T18+V18+X18+Z18+AB18+AD18+AF18+AH18+AJ18+AL18+AN18+AP18 -> 0 | S18: =U18+W18+Y18+AA18+AC18+AE18+AG18+AI18+AK18+AM18+AO18+AQ18 -> 0 | AS18: 2762711.9 | AT18: 247979.81 | AU18: =IF(H18<50000,0,IF(AT18>0,(H18/1.18-AT18-147869.7-H18/100*0.8)*0.1,(H18/1.18-H18/1.18/100*5.4-147869.7-H18/100*0.8)*0.1)) -> 256238.06 | BI18: Реаб. | BJ18: 44925 | BK18: Принят | BL18: Сакорггаз | BM18: 44641 | BN18: BCP-220321-1/2(1.1.10) | BP18: GGG
A19: 1610 | B19: Имерети | C19: Вани | D19: 1.1.1. В г. Вани, строительство газопровода от улицы Соломона II до центра с . Сулори. (P.6.121) | E19: Газсервис | F19: 1203300 | H19: =910000+540000+426237.45 -> 1876237.4 | J19: =138813.56+82372.88+65019.27+AS19+361218.18 -> 1876237.4 | K19: =F19-J19 -> -672937.45 | L19: =H19-J19 -> 0 | M19: 10540 | N19: =IF(OR(BK19="принят",BK19="Завершено",BK19="ПриПро"),H19-J19,F19-J19) -> 0 | O19: 0 | Q19: P.6.121 | R19: =T19+V19+X19+Z19+AB19+AD19+AF19+AH19+AJ19+AL19+AN19+AP19 -> 0 | S19: =U19+W19+Y19+AA19+AC19+AE19+AG19+AI19+AK19+AM19+AO19+AQ19 -> 0 | AS19: 1228813.6 | AT19: 110836.44 | AU19: =IF(H19<50000,0,IF(AT19>0,(H19/1.18-AT19-H19/100*0.8)*0.1,(H19/1.18-H19/1.18/100*5.4-H19/100*0.8)*0.1)) -> 146418.54 | BI19: Реаб. | BJ19: 44925 | BK19: Принят | BL19: Сакорггаз | BM19: 44641 | BN19: BCP-220321-1/2(1.1.1)
A20: 1620 | B20: Имерети | C20: Самтредия | D20: 1.1.11. В с. Патара Джихайши, строительство питающего газопровода. (P.6.101) | E20: Газсервис | F20: 1185000 | H20: =642000+691360.32 -> 1333360.3 | J20: =97932.2+105461.74+AS20+585898.58 -> 1333360.3 | K20: =F20-J20 -> -148360.32 | L20: =H20-J20 -> 0 | M20: 5393 | N20: =IF(OR(BK20="принят",BK20="Завершено",BK20="ПриПро"),H20-J20,F20-J20) -> 0 | O20: 0 | Q20: P.6.101 | R20: =T20+V20+X20+Z20+AB20+AD20+AF20+AH20+AJ20+AL20+AN20+AP20 -> 0 | S20: =U20+W20+Y20+AA20+AC20+AE20+AG20+AI20+AK20+AM20+AO20+AQ20 -> 0 | AS20: 544067.8 | AT20: 32964.55 | AU20: =IF(H20<50000,0,IF(AT20>0,(H20/1.18-AT20-58834.37-H20/100*0.8)*0.1,(H20/1.18-H20/1.18/100*5.4-58834.37-H20/100*0.8)*0.1)) -> 102750.06 | BI20: Реаб. | BJ20: 44925 | BK20: Принят | BL20: Сакорггаз | BM20: 44641 | BN20: BCP-220321-1/2(1.1.11)
A21: 1505 | B21: Кахети | C21: Ахмета | D21: Часть (30м) ул. Руставели (I этап) | E21: Интерсервис 2011 | F21: 5313 | H21: 3751 | J21: =572.186+3178.814 -> 3751 | K21: =F21-J21 -> 1562 | L21: =H21-J21 -> 0 | M21: =30-17 -> 13 | N21: =IF(OR(BK21="принят",BK21="Завершено",BK21="ПриПро"),H21-J21,F21-J21) -> 0 | O21: 0 | Q21: P.2.94 | R21: =T21+V21+X21+Z21+AB21+AD21+AF21+AH21+AJ21+AL21+AN21+AP21 -> 0 | S21: =U21+W21+Y21+AA21+AC21+AE21+AG21+AI21+AK21+AM21+AO21+AQ21 -> 0 | AS21: 0 | AT21: 0 | AU21: =IF(H21<50000,0,IF(AT21>0,(H21/1.18-AT21-H21/100*0.8)*0.1,(H21/1.18-H21/1.18/100*5.4-H21/100*0.8)*0.1)) -> 0 | BE21: 0 | BI21: Реаб. | BJ21: 44651 | BK21: Принят | BL21: SGG | BM21: 44511 | BN21: BS-211111-1/0 | BO21: 1516 | BQ21: Yes
A22: 1497 | B22: Квемо Картли | C22: Гардабани | D22: Реаб. в селе Вахтангиси, Гардабанского муниципалитета включая замену и вынос счетчиков; | E22: Интерсервис 2011 | F22: 658219 | H22: =488220+65204+64429+38553 -> 656406 | J22: =74474.24+183744.76+200000+9946.37+9828.15+50412.48+88000+20000+20000 -> 656406 | K22: =F22-J22 -> 1813 | L22: =H22-J22 -> 0 | M22: 13346 | N22: =IF(OR(BK22="принят",BK22="Завершено",BK22="ПриПро"),H22-J22,F22-J22) -> 0 | O22: 0 | Q22: обязательство перед государством | R22: =T22+V22+X22+Z22+AB22+AD22+AF22+AH22+AJ22+AL22+AN22+AP22 -> 0 | S22: =U22+W22+Y22+AA22+AC22+AE22+AG22+AI22+AK22+AM22+AO22+AQ22 -> 0 | AS22: 0 | AT22: 0 | AU22: =IF(H22<50000,0,IF(AT22>0,(H22/1.18-AT22-H22/100*0.8)*0.1,(H22/1.18-H22/1.18/100*5.4-H22/100*0.8)*0.1)) -> 52098.61 | BE22: 0 | BI22: Реаб. | BJ22: 44712 | BK22: Принят | BL22: SGG | BM22: 44423 | BN22: BS-210815-1/0 | BO22: 1505 | BQ22: Yes
A23: 1616 | B23: Имерети | C23: Терджола | D23: 1.1.7. В г. Тержола, поселке Метлахис Кархана, реабилитация питающего газопровода. (проектирование и строительство). (P.6.135) | E23: Газсервис | F23: 610000 | H23: =420000+130000+47280.69+7904.75+N("Project") -> 605185.44 | J23: =64067.8+19830.51+7212.308+1205.809+AS23+46767.323 -> 605185.44 | K23: =F23-J23 -> 4814.56 | L23: =H23-J23 -> 0 | M23: 4354 | N23: =IF(OR(BK23="принят",BK23="Завершено",BK23="ПриПро"),H23-J23,F23-J23) -> 0 | O23: 0 | Q23: P.6.135 | R23: =T23+V23+X23+Z23+AB23+AD23+AF23+AH23+AJ23+AL23+AN23+AP23 -> 0 | S23: =U23+W23+Y23+AA23+AC23+AE23+AG23+AI23+AK23+AM23+AO23+AQ23 -> 0 | AS23: 466101.69 | AT23: 43787.44 | AU23: =IF(H23<50000,0,IF(AT23>0,(H23/1.18-AT23-H23/100*0.8)*0.1,(H23/1.18-H23/1.18/100*5.4-H23/100*0.8)*0.1)) -> 46424.009 | BI23: Реаб. | BJ23: 44925 | BK23: принят | BL23: Сакорггаз | BM23: 44641 | BN23: BCP-220321-1/2(1.1.7)
A24: 1509 | B24: Квемо Картли | C24: Рустави | D24: Вынос счетчиков на ул. Тбилиси №22, №3 I-го прохода Мегоброба, ул. Руставели №16 и ул. Батуми №17 | E24: Интерсервис 2011 | F24: 22886 | H24: 22751 | J24: =3470.49+19280.51 -> 22751 | K24: =F24-J24 -> 135 | L24: =H24-J24 -> 0 | M24: 448.5 | N24: =IF(OR(BK24="принят",BK24="Завершено",BK24="ПриПро"),H24-J24,F24-J24) -> 0 | O24: 0 | Q24: P.2.72 (1 и 2) Поручение | R24: =T24+V24+X24+Z24+AB24+AD24+AF24+AH24+AJ24+AL24+AN24+AP24 -> 0 | S24: =U24+W24+Y24+AA24+AC24+AE24+AG24+AI24+AK24+AM24+AO24+AQ24 -> 0 | AS24: 0 | AT24: 0 | AU24: =IF(H24<50000,0,IF(AT24>0,(H24/1.18-AT24-H24/100*0.8)*0.1,(H24/1.18-H24/1.18/100*5.4-H24/100*0.8)*0.1)) -> 0 | BE24: 0 | BI24: Реаб. | BJ24: 44651 | BK24: Принят | BL24: Сакорггаз | BM24: 44533 | BN24: BC-211203-1/0 | BO24: 155 | BQ24: Yes
A25: 1513 | B25: Самцхе Джавахети | C25: Адигени | D25: в Абастумани, строит. сети вместе с Фондом Муниц. Развития (I этап 1.6 км.) | E25: Интер Газ | F25: =63700.88+2991.16 -> 66692.04 | H25: =63700.88+2991.16 -> 66692.04 | J25: =56518.68+10173.36+S25 -> 66692.04 | K25: =F25-J25 -> 0 | L25: =H25-J25 -> 0 | M25: 1604 | N25: =IF(OR(BK25="принят",BK25="Завершено",BK25="ПриПро"),H25-J25,F25-J25) -> -1.4551915e-11 | O25: 0 | Q25: P.3.231 | R25: =T25+V25+X25+Z25+AB25+AD25+AF25+AH25+AJ25+AL25+AN25+AP25 -> 0 | S25: =U25+W25+Y25+AA25+AC25+AE25+AG25+AI25+AK25+AM25+AO25+AQ25 -> 0 | AS25: 0 | AT25: 0 | AU25: 0 | BI25: Н. Стр. | BJ25: 44655 | BK25: Принят | BL25: SGG | BM25: 44508 | BN25: BSP-211108-1/0 | BO25: Бюро Экспертизы Самхараули | BQ25: No
A26: 1514 | B26: Гурия | C26: Чохатаури | D26: Реаб. Газопр. На ул. Думбадзе | E26: (Пр)-Унимшени | F26: 1426.25 | H26: 1426.25 | J26: 1426.25 | K26: =F26-J26 -> 0 | L26: =H26-J26 -> 0 | N26: =IF(OR(BK26="принят",BK26="Завершено",BK26="ПриПро"),H26-J26,F26-J26) -> 0 | O26: 0 | Q26: Поручение | R26: =T26+V26+X26+Z26+AB26+AD26+AF26+AH26+AJ26+AL26+AN26+AP26 -> 0 | S26: =U26+W26+Y26+AA26+AC26+AE26+AG26+AI26+AK26+AM26+AO26+AQ26 -> 0 | AS26: 0 | AT26: 0 | AU26: 0 | BI26: Проектирование | BJ26: 44621 | BK26: ПриПро | BL26: SGG | BM26: 44607 | BN26: CS-220215-1/0
A27: 1515 | B27: Гурия | C27: Чохатаури | D27: Реаб. Газопр. На ул. Думбадзе | E27: Унимшени | F27: 47083 | H27: 42187 | J27: =6435.30508474576+35751.6949152542 -> 42187 | K27: =F27-J27 -> 4896 | L27: =H27-J27 -> 0 | M27: 813.8 | N27: =IF(OR(BK27="принят",BK27="Завершено",BK27="ПриПро"),H27-J27,F27-J27) -> 4.3655746e-11 | O27: 0 | Q27: Поручение | R27: =T27+V27+X27+Z27+AB27+AD27+AF27+AH27+AJ27+AL27+AN27+AP27 -> 0 | S27: =U27+W27+Y27+AA27+AC27+AE27+AG27+AI27+AK27+AM27+AO27+AQ27 -> 0 | AS27: 0 | AT27: 0 | AU27: 0 | BI27: Реаб. | BJ27: 44681 | BK27: принят | BL27: SGG | BM27: 44621 | BN27: BS-220301-1/0 | BO27: 001-22 | BQ27: Yes
A28: 1516 | B28: Имерети | C28: Чиатура | D28: Реаб. Газопр. в с. Дарквети. d-40 mm (из за оползни) | E28: (Пр)-Газсервис | F28: 549.5 | H28: 549.5 | J28: 549.5 | K28: =F28-J28 -> 0 | L28: =H28-J28 -> 0 | N28: =IF(OR(BK28="принят",BK28="Завершено",BK28="ПриПро"),H28-J28,F28-J28) -> 0 | O28: 0 | Q28: Поручение | R28: =T28+V28+X28+Z28+AB28+AD28+AF28+AH28+AJ28+AL28+AN28+AP28 -> 0 | S28: =U28+W28+Y28+AA28+AC28+AE28+AG28+AI28+AK28+AM28+AO28+AQ28 -> 0 | AS28: 0 | AT28: 0 | AU28: 0 | BI28: Проектирование | BJ28: 44620 | BK28: ПриПро | BL28: SGG | BM28: 44602 | BN28: CS-220210-1/0
A29: 1517 | B29: Имерети | C29: Чиатура | D29: Реаб. Газопр. в с. Дарквети. d-40 mm (из за оползни) | E29: Газсервис | F29: 12812 | H29: 12801 | J29: =1952.69+10848.31 -> 12801 | K29: =F29-J29 -> 11 | L29: =H29-J29 -> 0 | M29: =314+5 -> 319 | N29: =IF(OR(BK29="принят",BK29="Завершено",BK29="ПриПро"),H29-J29,F29-J29) -> 0 | O29: 0 | Q29: Поручение | R29: =T29+V29+X29+Z29+AB29+AD29+AF29+AH29+AJ29+AL29+AN29+AP29 -> 0 | S29: =U29+W29+Y29+AA29+AC29+AE29+AG29+AI29+AK29+AM29+AO29+AQ29 -> 0 | AS29: 0 | AT29: 0 | AU29: =IF(H29<50000,0,IF(AT29>0,(H29/1.18-AT29-H29/100*0.8)*0.1,(H29/1.18-H29/1.18/100*5.4-H29/100*0.8)*0.1)) -> 0 | BI29: Реаб. | BJ29: 44651 | BK29: Принят | BL29: SGG | BM29: 44624 | BN29: BS-220304-1/0 | BO29: 002-22 | BQ29: Yes
A30: 1518 | B30: Имерети | C30: Кутаиси | D30: Участ. ул. Давида Агмашенебели (от ул. Гамсахурдиа до ул. Ниношвили) | E30: (Пр)-Газсервис | F30: 3024 | H30: 3024 | J30: =461.288+2562.712 -> 3024 | K30: =F30-J30 -> 0 | L30: =H30-J30 -> 0 | N30: =IF(OR(BK30="принят",BK30="Завершено",BK30="ПриПро"),H30-J30,F30-J30) -> 0 | O30: 0 | Q30: Поручение | R30: =T30+V30+X30+Z30+AB30+AD30+AF30+AH30+AJ30+AL30+AN30+AP30 -> 0 | S30: =U30+W30+Y30+AA30+AC30+AE30+AG30+AI30+AK30+AM30+AO30+AQ30 -> 0 | AS30: 0 | AT30: 0 | AU30: 0 | BI30: Проектирование | BJ30: 44627 | BK30: ПриПро | BL30: Сакорггаз | BM30: 44620 | BN30: CC-220228-1/0
A31: 1519 | B31: Имерети | C31: Кутаиси | D31: Участ. ул. Давида Агмашенебели (от ул. Гамсахурдиа до ул. Ниношвили) | E31: Газсервис | F31: 306010 | G31: ამოსაღებია მცირე ეტაპები (გადასვლები) გაკეთდა ექსპლუატაციით. | K31: =F31-J31 -> 306010 | L31: =H31-J31 -> 0 | M31: 1728 | N31: =IF(OR(BK31="принят",BK31="Завершено",BK31="ПриПро"),H31-J31,F31-J31) -> 306010 | O31: XO | Q31: Поручение | R31: =T31+V31+X31+Z31+AB31+AD31+AF31+AH31+AJ31+AL31+AN31+AP31 -> 0 | S31: =U31+W31+Y31+AA31+AC31+AE31+AG31+AI31+AK31+AM31+AO31+AQ31 -> 0 | AS31: 0 | AT31: 0 | AU31: 0 | BI31: Реаб. | BK31: 0 | BL31: Сакорггаз | BM31: 44631 | BN31: BC-220311-1/0 | BO31: 001-22 | BP31: გასაუქმებელია, მცირე ეტაპები (გადასვლები) გაკეთდა ექსპლუატაციით. | BQ31: Yes
A32: 1520 | B32: Квемо Картли | C32: Рустави | D32: Вынос счетч. С корпусов ул. Костава №25, ул. Мегоброба №26. | E32: (Пр)-Интерсервис 2011 | F32: =213.5+2380 -> 2593.5 | H32: =213.5+2380 -> 2593.5 | J32: =395.618+2197.882 -> 2593.5 | K32: =F32-J32 -> 0 | L32: =H32-J32 -> 0 | N32: =IF(OR(BK32="принят",BK32="Завершено",BK32="ПриПро"),H32-J32,F32-J32) -> 0 | O32: 0 | Q32: P | R32: =T32+V32+X32+Z32+AB32+AD32+AF32+AH32+AJ32+AL32+AN32+AP32 -> 0 | S32: =U32+W32+Y32+AA32+AC32+AE32+AG32+AI32+AK32+AM32+AO32+AQ32 -> 0 | AS32: 0 | AT32: 0 | AU32: 0 | BI32: Проектирование | BJ32: 44641 | BK32: ПриПро | BL32: Сакорггаз | BM32: 44620 | BN32: CC-220228-2/0
A33: 1584 | B33: Квемо Картли | C33: Рустави | D33: 1.1.7. В г. Рустави замена полиэтиленовых труб на фасадах корпусов (I и II этап). (P.2.72 (1 и 2)) (проектирование и строительство) | E33: Интерсервис 2011 | F33: 3380000 | G33: ?? | H33: =70450+44500+42000+33500+27172.25+37500+42500+41000+0+38800+16800+15300+43000+41500+49500+5908+64662.5+54000+47700+49300+31400+75000+58000+82600+18000+35900+43300+29800+50400+43200+8600+16200+4300+6400+5800+90000+18000+40000+25000+18000+15000+32000+15000+60000+18000+12000+35000+8000+20000+35000+10000+20000+10000+35000+35000+30000+35000+25000+30000+30000+17389.75+30000+20000+10000+50000+30000+35000+45000+60000+15000+10000+50000+11520.25+8000+15000+10996+6105.83+17891.88+16542.76+29844.78+28190.84+28551+29642+9509+6980+7596+1543+5442+737+2462+2906+559+259+23666+2859+7222+819+1386+3040+1106+201+4403+3641+9026+30000+28000+30000+50000+5000+3000+60000+50000+7540.75+35155+39940+3403+42395+56899+50569+64033+3242+28732+20983+673+12056+1008+4868+4817+40000+20000+15000+3000+3430+2568+17203+16484+28646+60450+60362+180725+125958+48697+60980+62487+46690+88896+112289+86109+43055+54798+47438+3679+73988+21012.25 -> 4601287.8 | J33: =10746.61+70000+5720.34+6483.05+6254.28+5918.64+2562.71+2333.9+6559.32+6330.51+7550.85+901.22+110526.48 +N("ოქტ დღგ 19 შუალედურის")+109584.88+N("ნოემბ 26 მიღების ჯამური დღგ")+3050.847+1525.42+7627.118+4576.27+5338.98+6864.406+9152.54+2288.14+1525.42+7627.118+1757.326+1220.338+2288.1355+1677.3559+931.397+2729.269+2523.47+4552.59+4300.297+4521.66+4355.237+53597.59+N("იანვრის 29 მიღების დღგ")+69302.1+N("Feb 20 მიღების დღგ")+AS33+AV33+687352.34+179635.92+N("მარტის 17 ჩაბარების დღგ")+272000+2501.91+3123.31+655.51+1181.99+1107.83 -> 4601287.8 | K33: =F33-J33 -> -1221287.8 | L33: =H33-J33 -> 0.0055999998 | N33: =IF(OR(BK33="принят",BK33="Завершено",BK33="ПриПро"),H33-J33,F33-J33) -> -1221287.8 | O33: 1 | Q33: P.2.72 (1 и 2) | R33: =T33+V33+X33+Z33+AB33+AD33+AF33+AH33+AJ33+AL33+AN33+AP33 -> 0 | S33: =U33+W33+Y33+AA33+AC33+AE33+AG33+AI33+AK33+AM33+AO33+AQ33 -> 0 | AS33: =2113185.44+N("68 ფაქტორინგი") -> 2113185.4 | AT33: =13852+N("მხოლოდ 2022-ში დასრულებული 8 ობიექტის (ჯამური თანხით 540 365 ლარი) ფაქტორინგი") -> 13852 | AU33: =(540365/1.18-AT33-(540365/100*0.8))*0.1 -> 43976.152 | AV33: =785737.77+N("შესაძლოა იყო ფაქტორინგი ათვისებული 2023-შიც") -> 785737.77 | BI33: Корп | BK33: =82996+68805.83+67191.88+64142.76+72344.78+61690.84+63551+59642 -> 540365.09 | BL33: Сакорггаз | BM33: 44677 | BN33: BCP-220426-1/2(1.1.7) | BP33: გასაყოფია სწორად, 2022-სა და 2023-ს შორის!
A34: 1626 | B34: Имерети | C34: Кутаиси | D34: 1.1.17. Реабилитация газопроводов по улицам Хандзтели, Сараджишвили, Каухчишвили и Табидзе в г. Кутаиси. (P.6.303) | E34: Газсервис | F34: 700000 | H34: =430000+94696.55 -> 524696.55 | J34: =65593.22+14445.236+80251.314+AS34 -> 524696.55 | K34: =F34-J34 -> 175303.45 | L34: =H34-J34 -> 0 | M34: 1307 | N34: =IF(OR(BK34="принят",BK34="Завершено",BK34="ПриПро"),H34-J34,F34-J34) -> 0 | O34: 0 | Q34: P.6.303 | R34: =T34+V34+X34+Z34+AB34+AD34+AF34+AH34+AJ34+AL34+AN34+AP34 -> 0 | S34: =U34+W34+Y34+AA34+AC34+AE34+AG34+AI34+AK34+AM34+AO34+AQ34 -> 0 | AS34: 364406.78 | AT34: 26571.75 | AU34: =IF(H34<50000,0,IF(AT34>0,(H34/1.18-AT34-H34/100*0.8)*0.1,(H34/1.18-H34/1.18/100*5.4-H34/100*0.8)*0.1)) -> 41388.877 | BI34: Реаб. | BJ34: 44925 | BK34: Принят | BL34: Сакорггаз | BM34: 44641 | BN34: BCP-220321-1/2(1.1.17)
A35: 1625 | B35: Имерети | C35: Кутаиси | D35: 1.1.16. В г. Кутаиси, реабилитация газопровода на ул. Гелати. (P.6.68) | E35: Газсервис | F35: 253000 | H35: =200000+200000+119999.52 -> 519999.52 | J35: =30508.47+30508.47+18305.01+101694.52+AS35 -> 519999.52 | K35: =F35-J35 -> -266999.52 | L35: =H35-J35 -> 0 | M35: 2126 | N35: =IF(OR(BK35="принят",BK35="Завершено",BK35="ПриПро"),H35-J35,F35-J35) -> 0 | O35: 0 | Q35: P.6.68 | R35: =T35+V35+X35+Z35+AB35+AD35+AF35+AH35+AJ35+AL35+AN35+AP35 -> 0 | S35: =U35+W35+Y35+AA35+AC35+AE35+AG35+AI35+AK35+AM35+AO35+AQ35 -> 0 | AS35: 338983.05 | AT35: 29384.72 | AU35: =IF(H35<50000,0,IF(AT35>0,(H35/1.18-AT35-H35/100*0.8)*0.1,(H35/1.18-H35/1.18/100*5.4-H35/100*0.8)*0.1)) -> 40713.284 | BI35: Реаб. | BJ35: 44925 | BK35: Принят | BL35: Сакорггаз | BM35: 44641 | BN35: BCP-220321-1/2(1.1.16)
A36: 1524 | B36: Шида Картли | C36: Каспи | D36: ул. Костава, А. Церетели и Ширикашвили (пересечения Важа Пшавела и Цулукидзе) (I этап) | E36: Газ Констракт | F36: =45318+2304 -> 47622 | H36: 47622 | J36: =7264.37+34879.66+5477.96999999999 -> 47622 | K36: =F36-J36 -> 0 | L36: =H36-J36 -> 0 | M36: 1143 | N36: =IF(OR(BK36="принят",BK36="Завершено",BK36="ПриПро"),H36-J36,F36-J36) -> 0 | O36: 0 | Q36: часть от P 3.49; и часть от P 3.105 | R36: =T36+V36+X36+Z36+AB36+AD36+AF36+AH36+AJ36+AL36+AN36+AP36 -> 0 | S36: =U36+W36+Y36+AA36+AC36+AE36+AG36+AI36+AK36+AM36+AO36+AQ36 -> 0 | AS36: 0 | AT36: 0 | AU36: =IF(H36<50000,0,IF(AT36>0,(H36/1.18-AT36-H36/100*0.8)*0.1,(H36/1.18-H36/1.18/100*5.4-H36/100*0.8)*0.1)) -> 0 | BI36: Реаб. | BJ36: 44651 | BK36: Принят | BL36: Сакорггаз | BM36: 44571 | BN36: BC-220110-1/1 | BO36: 133 | BQ36: Yes
A37: 1525 | B37: Имерети | C37: Кутаиси | D37: ул. Джибладзе реаб. Газопр. | E37: (Пр)-Газсервис | F37: 633.5 | H37: 633.5 | J37: 633.5 | K37: =F37-J37 -> 0 | L37: =H37-J37 -> 0 | N37: =IF(OR(BK37="принят",BK37="Завершено",BK37="ПриПро"),H37-J37,F37-J37) -> 0 | O37: 0 | Q37: Поручение | R37: =T37+V37+X37+Z37+AB37+AD37+AF37+AH37+AJ37+AL37+AN37+AP37 -> 0 | S37: =U37+W37+Y37+AA37+AC37+AE37+AG37+AI37+AK37+AM37+AO37+AQ37 -> 0 | AS37: 0 | AT37: 0 | AU37: 0 | BI37: Проектирование | BJ37: 44649 | BK37: ПриПро | BL37: Сакорггаз | BM37: 44645 | BN37: CC-220325-1/0
A38: 1526 | B38: Имерети | C38: Кутаиси | D38: ул. Джибладзе реаб. Газопр. | E38: Газсервис | F38: 29668 | H38: 29579 | J38: 29579 | K38: =F38-J38 -> 89 | L38: =H38-J38 -> 0 | M38: 362 | N38: =IF(OR(BK38="принят",BK38="Завершено",BK38="ПриПро"),H38-J38,F38-J38) -> 0 | O38: 0 | Q38: Поручение | R38: =T38+V38+X38+Z38+AB38+AD38+AF38+AH38+AJ38+AL38+AN38+AP38 -> 0 | S38: =U38+W38+Y38+AA38+AC38+AE38+AG38+AI38+AK38+AM38+AO38+AQ38 -> 0 | AS38: 0 | AT38: 0 | AU38: =IF(H38<50000,0,IF(AT38>0,(H38/1.18-AT38-H38/100*0.8)*0.1,(H38/1.18-H38/1.18/100*5.4-H38/100*0.8)*0.1)) -> 0 | BI38: Реаб. | BJ38: 44681 | BK38: Принят | BL38: Сакорггаз | BM38: 44650 | BN38: BC-220330-1/0 | BO38: 005-22 | BQ38: Yes
A39: 1527 | B39: Шида Картли | C39: Гори | D39: 1.11 Реабилитация газопровода в селе Бербуки. (P 3.109) | E39: Газ Констракт | F39: 29862 | H39: 29442 | J39: 29442 | K39: =F39-J39 -> 420 | L39: =H39-J39 -> 0 | M39: 768 | N39: =IF(OR(BK39="принят",BK39="Завершено",BK39="ПриПро"),H39-J39,F39-J39) -> 0 | O39: 0 | Q39: P 3.109 | R39: =T39+V39+X39+Z39+AB39+AD39+AF39+AH39+AJ39+AL39+AN39+AP39 -> 0 | S39: =U39+W39+Y39+AA39+AC39+AE39+AG39+AI39+AK39+AM39+AO39+AQ39 -> 0 | AS39: 0 | AT39: 0 | AU39: =IF(H39<50000,0,IF(AT39>0,(H39/1.18-AT39-H39/100*0.8)*0.1,(H39/1.18-H39/1.18/100*5.4-H39/100*0.8)*0.1)) -> 0 | BI39: Реаб. | BJ39: 44712 | BK39: принят | BL39: Сакорггаз | BM39: 44658 | BN39: BC-220407-1/0 | BQ39: Yes
A40: 1528 | B40: Самцхе Джавахети | C40: Адигени | D40: в Абастумани, строит. сети вместе с Фондом Муниц. Развития (II этап 1.8 км.) (проектирование и строительство) (P.3.231) | E40: Интер Газ | F40: 600000 | H40: =132163.32+166596.97+204135+400000+250000+30130.71+(13157*1.75)+N("23024,75") -> 1206050.8 | I40: =132163.32+166596.97+204135+400000+250000+30130.71 -> 1183026 | J40: =112002.81+20160.51+166596.97+31139.237+172995.763+61016.949+338983.051+AY40+42731.8+23024.75+S40 -> 1206050.8 | K40: =F40-J40 -> -606050.75 | L40: =H40-J40 -> 0 | M40: 7400 | N40: =IF(OR(BK40="принят",BK40="Завершено",BK40="ПриПро"),H40-J40,F40-J40) -> 0 | O40: 0 | Q40: P.3.231 | R40: =T40+V40+X40+Z40+AB40+AD40+AF40+AH40+AJ40+AL40+AN40+AP40 -> 0 | S40: =U40+W40+Y40+AA40+AC40+AE40+AG40+AI40+AK40+AM40+AO40+AQ40 -> 0 | AS40: 0 | AT40: 0 | AU40: 0 | AY40: =211864.41+25534.5 -> 237398.91 | AZ40: =13843.74+N("მეორე ფაქტორინგი აიღო საბოლოო ჩაბარების შემდეგ") -> 13843.74 | BA40: 0 | BB40: 0 | BI40: Реаб. | BJ40: 45593 | BK40: Принят | BL40: SGG | BM40: 44683 | BN40: BSP-220502-1/0 | BQ40: No
A41: 1529 | B41: Имерети | C41: Багдати | D41: 1.2.1. С. Рохи (проектирование и строительство) P.6.127 (5) | E41: Интер Газ | F41: 3154968.3 | H41: =1560000+500000+1000000+70262.5+N("ეს პროექტია")+180000+24730+N("რეგულატორები (301023)")-0+N("ეს პროექტია გამოკლებული")+2215.49 -> 3337208 | I41: =H41-70262.5 -> 3266945.5 | J41: =237966.1+76271.19+1000000+AS41+70262.5+27457.627+AV41+3772.37+337.956+22835.169 -> 3337208 | K41: =F41-J41 -> -182239.73 | L41: =H41-J41 -> 0 | M41: 34332.59 | N41: =IF(OR(BK41="принят",BK41="Завершено",BK41="ПриПро"),H41-J41,F41-J41) -> 0 | O41: 0 | Q41: P.6.127 (5) | R41: =T41+V41+X41+Z41+AB41+AD41+AF41+AH41+AJ41+AL41+AN41+AP41 -> 0 | S41: =U41+W41+Y41+AA41+AC41+AE41+AG41+AI41+AK41+AM41+AO41+AQ41 -> 0 | AS41: =1322033.898+423728.81 -> 1745762.7 | AT41: =(1322.03+131478.99)+(423.73+38832.13) -> 172056.88 | AU41: 0 | AV41: =152542.37 -> 152542.37 | AW41: 18980.03 | BG41: 2419436.3 | BH41: 44925 | BI41: Реаб. | BJ41: 45259 | BK41: Принят | BL41: Сакорггаз | BM41: 44648 | BN41: BCP-220328-1/2(1.2.1) | BP41: 6 სოფელია მოქცეული ერთ p-ში. | BQ41: No
A42: 1530 | B42: Имерети | C42: Вани | D42: 1.2.2 С. Зеиндари (проектирование и строительство) P.6.127 (5) | E42: Интер Газ | F42: 1871293 | H42: =1130000+500000+550000+41674.5+N("ეს პროექტია")+17228+N("რეგულატორები (301023)")-0+N("ეს პროექტია")+68105.32+N("ბოლო ჩაბარება") -> 2307007.8 | I42: =H42-41674.5 -> 2265333.3 | J42: =172372.88+76271.19+550000+AS42+AV42+41674.5+2628+10388.95+72316.369 -> 2307007.8 | K42: =F42-J42 -> -435714.82 | L42: =H42-J42 -> 0.0009999997 | M42: 23814 | N42: =IF(OR(BK42="принят",BK42="Завершено",BK42="ПриПро"),H42-J42,F42-J42) -> 0.0009999997 | O42: 0 | Q42: P.6.127 (5) | R42: =T42+V42+X42+Z42+AB42+AD42+AF42+AH42+AJ42+AL42+AN42+AP42 -> 0 | S42: =U42+W42+Y42+AA42+AC42+AE42+AG42+AI42+AK42+AM42+AO42+AQ42 -> 0 | AS42: =957627.12+423728.81 -> 1381355.9 | AT42: =(957.63+95237.98)+(423.73+38832.13) -> 135451.47 | AU42: 0 | AV42: 0 | AW42: 0 | BG42: 1557235.7 | BH42: 44925 | BI42: Реаб. | BJ42: 45259 | BK42: Принят | BL42: Сакорггаз | BM42: 44648 | BN42: BCP-220328-1/2(1.2.2) | BP42: 6 სოფელია მოქცეული ერთ p-ში. | BQ42: No
A43: 1531 | B43: Имерети | C43: Вани | D43: 1.2.3 С. Шуагора (проектирование и строительство) P.6.127 (5) | E43: Интер Газ | F43: 1180500.3 | G43: 2 | H43: =260000+600000+550000+26290.25+N("ეს პროექტია")+5126+N("რეგულატორები (301023)")+83898.7 -> 1525314.9 | I43: =H43-26290.25 -> 1499024.7 | J43: =39661.02+91525.42+AS43+110188.56+781.93+88242.77 -> 1525314.9 | K43: =F43-J43 -> -344814.62 | L43: =H43-J43 -> 0 | M43: 14170 | N43: =IF(OR(BK43="принят",BK43="Завершено",BK43="ПриПро"),H43-J43,F43-J43) -> 0 | O43: 0 | Q43: P.6.127 (5) | R43: =T43+V43+X43+Z43+AB43+AD43+AF43+AH43+AJ43+AL43+AN43+AP43 -> 0 | S43: =U43+W43+Y43+AA43+AC43+AE43+AG43+AI43+AK43+AM43+AO43+AQ43 -> 0 | AS43: =220338.98+508474.58+466101.69 -> 1194915.2 | AT43: =220.34+21913.16+508.47+46598.56+466.1+27391.46 -> 97098.09 | AU43: 0 | AV43: 0 | AW43: 0 | BA43: 0 | BB43: 0 | BG43: 1075565 | BH43: 44925 | BI43: Реаб. | BJ43: 45351 | BK43: Принят | BL43: Сакорггаз | BM43: 44648 | BN43: BCP-220328-1/2(1.2.3) | BP43: 6 სოფელია მოქცეული ერთ p-ში. | BQ43: No
A44: 1532 | B44: Имерети | C44: Вани | D44: 1.2.4 и 1.2.5 с. Гора и с. Зедагора (проектирование и строительство) P.6.127 (5) | E44: Интер Газ | F44: 1493011.1 | G44: 2 | H44: =747000+600000+400000+36296.75+N("ეს გორას პროექტია")+120000+2992.5+N("ეს ზედა გორას პროექტია")+N("ეს ბოლო 2 ჩაბარება ზედაგორაა")+147024+N("ეს საბოლოო შესრულება გორასა და ზედაგორასია ერთად!") -> 2053313.2 | I44: =H44-36296.75-2992.5 -> 2014024 | J44: =113949.15+91525.42+AS44+97313.71+50000+72992.5+N("ეს ბოლო 2 გადახდა ზედაგორაა")+147024 -> 2053313.3 | K44: =F44-J44 -> -560302.13 | L44: =H44-J44 -> -0.01 | M44: 22089 | N44: =IF(OR(BK44="принят",BK44="Завершено",BK44="ПриПро"),H44-J44,F44-J44) -> -0.01 | O44: 0 | Q44: P.6.127 (5) | R44: =T44+V44+X44+Z44+AB44+AD44+AF44+AH44+AJ44+AL44+AN44+AP44 -> 0 | S44: =U44+W44+Y44+AA44+AC44+AE44+AG44+AI44+AK44+AM44+AO44+AQ44 -> 0 | AS44: =633050.85+508474.58+338983.05 -> 1480508.5 | AT44: =62958.21+633.05+46598.56+508.47+19921.06+338.98 -> 130958.33 | AU44: 0 | BA44: 0 | BB44: 0 | BG44: 1030156.8 | BH44: 44925 | BI44: Реаб. | BJ44: 45576 | BK44: Принят | BL44: Сакорггаз | BM44: 44648 | BN44: BCP-220328-1/2(1.2.4 и 1.2.5) | BP44: 6 სოფელია მოქცეული ერთ p-ში. | BQ44: No
A45: 1533 | B45: Имерети | C45: Вани | D45: 1.2.5 С. Зедагора (проектирование и строительство) P.6.127 (5) | E45: Интер Газ | F45: 134371 | G45: ამოსაღებია, ჩაბარდა გორასთან ერთად | H45: 0 | I45: 0 | J45: 0 | K45: =F45-J45 -> 134371 | L45: =H45-J45 -> 0 | M45: 1710 | N45: =IF(OR(BK45="принят",BK45="Завершено",BK45="ПриПро"),H45-J45,F45-J45) -> 134371 | O45: X | Q45: P.6.127 (5) | R45: =T45+V45+X45+Z45+AB45+AD45+AF45+AH45+AJ45+AL45+AN45+AP45 -> 0 | S45: =U45+W45+Y45+AA45+AC45+AE45+AG45+AI45+AK45+AM45+AO45+AQ45 -> 0 | AS45: 0 | AT45: 0 | AU45: 0 | BI45: Реаб. | BK45: 0 | BL45: Сакорггаз | BM45: 44648 | BN45: BCP-220328-1/2(1.2.5) | BP45: 6 სოფელია მოქცეული ერთ p-ში. | BQ45: No
A46: 1534 | B46: Имерети | C46: Вани | D46: 1.2.6 С. Перета (проектирование и строительство) P.6.127 (5) | E46: Интер Газ | F46: 891956.28 | G46: 2 | H46: =300000+400000+330000+19864.25+N("ეს პროექტია")+5302 -> 1055166.2 | I46: =H46-19864.25 -> 1035302 | J46: =45762.71+73000+61016.95+AS46+276864.25+5302+N("გადაირიცხა პირდაპირ") -> 1055166.2 | K46: =F46-J46 -> -163209.97 | L46: =H46-J46 -> 0 | M46: 9970.2 | N46: =IF(OR(BK46="принят",BK46="Завершено",BK46="ПриПро"),H46-J46,F46-J46) -> 0 | O46: 0 | Q46: P.6.127 (5) | R46: =T46+V46+X46+Z46+AB46+AD46+AF46+AH46+AJ46+AL46+AN46+AP46 -> 0 | S46: =U46+W46+Y46+AA46+AC46+AE46+AG46+AI46+AK46+AM46+AO46+AQ46 -> 0 | AS46: =254237.29+338983.05 -> 593220.34 | AT46: =254.24+25284.42+338.98+31065.71 -> 56943.35 | AU46: 0 | BA46: 0 | BB46: 0 | BG46: 448527.74 | BH46: 44925 | BI46: Реаб. | BJ46: 45434 | BK46: Принят | BL46: Сакорггаз | BM46: 44648 | BN46: BCP-220328-1/2(1.2.6) | BP46: 6 სოფელია მოქცეული ერთ p-ში. | BQ46: No
A47: 1535 | B47: Рача | C47: Терджола | D47: 1.2.1 Участок Муджирети-Мухура (проектирование и строительство) (P.6.144) | E47: Интер Газ | F47: 1540000 | H47: =1800000+1500000+12519.5+N("ეს პროექტია")+390373.72 -> 3702893.2 | J47: =274576.27+AS47+241333.06+59548.54+AV47 -> 3702893.2 | K47: =F47-J47 -> -2162893.2 | L47: =H47-J47 -> -0.01 | M47: 7200 | N47: =IF(OR(BK47="принят",BK47="Завершено",BK47="ПриПро"),H47-J47,F47-J47) -> -0.01 | O47: 0 | Q47: P.6.144 | R47: =T47+V47+X47+Z47+AB47+AD47+AF47+AH47+AJ47+AL47+AN47+AP47 -> 0 | S47: =U47+W47+Y47+AA47+AC47+AE47+AG47+AI47+AK47+AM47+AO47+AQ47 -> 0 | AS47: =1525423.73+1271186.44 -> 2796610.2 | AT47: 217296.26 | AU47: 0 | AV47: =330825.19 -> 330825.19 | AW47: =0+N("არ ასახულა ფორმა2-ში") -> 0 | BG47: 2678697.9 | BH47: 44925 | BI47: Реаб. | BJ47: 45040 | BK47: Принят | BL47: Сакорггаз | BM47: 44648 | BN47: BCP-220328-2/2(1.2.1) | BQ47: No
A48: 1536 | B48: Рача | C48: Амбролаури | D48: (1.2.2 и 1.2.3) Участок Мухура-Хотеви-Амбролаури (проектные работы) P.6.144 (1) + P.6.140 | E48: (Пр)-Интер Газ | F48: =55000+30000 -> 85000 | H48: 62482 | J48: 62482 | K48: =F48-J48 -> 22518 | L48: =H48-J48 -> 0 | N48: =IF(OR(BK48="принят",BK48="Завершено",BK48="ПриПро"),H48-J48,F48-J48) -> 0 | O48: 0 | Q48: P.6.144 (1) + P.6.140 | R48: =T48+V48+X48+Z48+AB48+AD48+AF48+AH48+AJ48+AL48+AN48+AP48 -> 0 | S48: =U48+W48+Y48+AA48+AC48+AE48+AG48+AI48+AK48+AM48+AO48+AQ48 -> 0 | AS48: 0 | AT48: 0 | AU48: 0 | BI48: Проектирование | BJ48: 44922 | BK48: ПриПро | BL48: Сакорггаз | BM48: 44648 | BN48: BCP-220328-2/2(1.2.2)(1.2.3)
A49: 1538 | B49: Мцхета-Мтианети | C49: Мцхета | D49: 1.1.1. Ребилитационные работы питающего газопровода сёл Мухатцкаро-Цодорети Мцхетского муниципалитета. (P.3.153) | E49: Газ Констракт | F49: 432000 | H49: =720000+75672.53 -> 795672.53 | J49: =109830.51+AS49+11695.81+AV49 -> 795672.48 | K49: =F49-J49 -> -363672.48 | L49: =H49-J49 -> 0.05 | M49: 6709 | N49: =IF(OR(BK49="принят",BK49="Завершено",BK49="ПриПро"),H49-J49,F49-J49) -> 0.05 | O49: 0 | Q49: P.3.153 | R49: =T49+V49+X49+Z49+AB49+AD49+AF49+AH49+AJ49+AL49+AN49+AP49 -> 0 | S49: =U49+W49+Y49+AA49+AC49+AE49+AG49+AI49+AK49+AM49+AO49+AQ49 -> 0 | AS49: 610169.44 | AT49: 31202.23 | AU49: 0 | AV49: 63976.72 | AW49: 8123.29 | AX49: =(H49/1.18-AT49-AW49)*0.1 -> 63497.323 | BI49: Реаб. | BJ49: 45069 | BK49: Принят | BL49: SGG | BM49: 44656 | BN49: BSP-220405-1/2(1.1.1) | BQ49: Yes
A50: 1539 | B50: Мцхета-Мтианети | C50: Мцхета | D50: 1.1.2. Реаб. работы газопровода среднего давления В с. Сагурамо Мцхетского муниципалитета. (P.3.239) | E50: Газ Констракт | F50: 70000 | H50: 60010.52 | J50: =9154.147+50856.373 -> 60010.52 | K50: =F50-J50 -> 9989.48 | L50: =H50-J50 -> 0 | M50: 950 | N50: =IF(OR(BK50="принят",BK50="Завершено",BK50="ПриПро"),H50-J50,F50-J50) -> -7.2759576e-12 | O50: 0 | Q50: P.3.239 | R50: =T50+V50+X50+Z50+AB50+AD50+AF50+AH50+AJ50+AL50+AN50+AP50 -> 0 | S50: =U50+W50+Y50+AA50+AC50+AE50+AG50+AI50+AK50+AM50+AO50+AQ50 -> 0 | AS50: 0 | AT50: 0 | AU50: 0 | AV50: 0 | AW50: 0 | AX50: =(H50/1.18-AT50-AW50)*0.1 -> 5085.6373 | BI50: Реаб. | BJ50: 44985 | BK50: Принят | BL50: SGG | BM50: 44656 | BN50: BSP-220405-1/2(1.1.2) | BQ50: Yes
A51: 1540 | B51: Мцхета-Мтианети | C51: Мцхета | D51: 1.1.3. Реаб. работы газопрю ср. давления от с. Джигаура до с.Битсменди, | E51: Газ Констракт | F51: 35000 | H51: 29747.43 | J51: =4537.74+25209.69 -> 29747.43 | K51: =F51-J51 -> 5252.57 | L51: =H51-J51 -> 0 | M51: 510.5 | N51: =IF(OR(BK51="принят",BK51="Завершено",BK51="ПриПро"),H51-J51,F51-J51) -> 0 | O51: 0 | Q51: P.3.241 | R51: =T51+V51+X51+Z51+AB51+AD51+AF51+AH51+AJ51+AL51+AN51+AP51 -> 0 | S51: =U51+W51+Y51+AA51+AC51+AE51+AG51+AI51+AK51+AM51+AO51+AQ51 -> 0 | AS51: 0 | AT51: 0 | AU51: 0 | AV51: 0 | AW51: 0 | AX51: =(H51/1.18-AT51-AW51)*0.1 -> 2520.9686 | BI51: Реаб. | BJ51: 44985 | BK51: Принят | BL51: SGG | BM51: 44656 | BN51: BSP-220405-1/2(1.1.3) | BQ51: Yes
A52: 1541 | B52: Мцхета-Мтианети | C52: Мцхета | D52: 1.1.4. Реаб. Газопр. ср. давления в Марнис убани с.Сагурамо | E52: Газ Констракт | F52: 30000 | H52: 49694.01 | J52: =7580.44+42113.57 -> 49694.01 | K52: =F52-J52 -> -19694.01 | L52: =H52-J52 -> 0 | M52: 600 | N52: =IF(OR(BK52="принят",BK52="Завершено",BK52="ПриПро"),H52-J52,F52-J52) -> 0 | O52: 0 | Q52: P.3.242 | R52: =T52+V52+X52+Z52+AB52+AD52+AF52+AH52+AJ52+AL52+AN52+AP52 -> 0 | S52: =U52+W52+Y52+AA52+AC52+AE52+AG52+AI52+AK52+AM52+AO52+AQ52 -> 0 | AS52: 0 | AT52: 0 | AU52: 0 | AV52: 0 | AW52: 0 | AX52: =(H52/1.18-AT52-AW52)*0.1 -> 4211.3568 | BI52: Реаб. | BJ52: 44985 | BK52: принят | BL52: SGG | BM52: 44656 | BN52: BSP-220405-1/2(1.1.4) | BQ52: Yes
A53: 1542 | B53: Мцхета-Мтианети | C53: Мцхета | D53: 1.1.5. Реабилитация газопровода по улице Тевзадзе (P.3.64), улица Горького (P.3.63), тупик Бараташвили (P.3.76), Цкарос Убани (P.3.75) в пос.Коджори. | E53: Газ Констракт | F53: 30000 | G53: 2 | H53: =1429*1.75+84081 -> 86581.75 | I53: =H53-2500.75 -> 84081 | J53: =381.47+12825.915+AS53+AV53+73374.365 -> 86581.75 | K53: =F53-J53 -> -56581.75 | L53: =H53-J53 -> 0 | M53: 1428 | N53: =IF(OR(BK53="принят",BK53="Завершено",BK53="ПриПро"),H53-J53,F53-J53) -> 0 | O53: 0 | Q53: P.3.64; P.3.63; P.3.76; P.3.75 | R53: =T53+V53+X53+Z53+AB53+AD53+AF53+AH53+AJ53+AL53+AN53+AP53 -> 0 | S53: =U53+W53+Y53+AA53+AC53+AE53+AG53+AI53+AK53+AM53+AO53+AQ53 -> 0 | AS53: 0 | AT53: 0 | AU53: 0 | AV53: 0 | AW53: 0 | BA53: =IF(BK53="Принят",(I53/1.18-AW53-AZ53)*0.1,I53/1.18*0.8*0.1) -> 7125.5085 | BB53: =(I53/1.18-AT53-AW53-AZ53)*0.1-BA53 -> 0 | BE53: =(I53/1.18-AT53-AW53-AZ53-BD53)*0.1-AU53-AX53-BA53-BB53 -> 0 | BI53: Реаб. | BJ53: 45322 | BK53: принят | BL53: SGG | BM53: 44656 | BN53: BSP-220405-1/2(1.1.5) | BP53: დასრულდა | BQ53: Yes
A54: 1543 | B54: Шида Картли | C54: Карели | D54: 1.1.6. Реаб. Газопр. пос.Агара Карельского муниципалитета. (проектирование и строительство) | E54: Газ Констракт | F54: 33000 | H54: =1181.25+44626.64 -> 45807.89 | J54: =180.19+6807.45+38820.25 -> 45807.89 | K54: =F54-J54 -> -12807.89 | L54: =H54-J54 -> 0 | M54: 690 | N54: =IF(OR(BK54="принят",BK54="Завершено",BK54="ПриПро"),H54-J54,F54-J54) -> 0 | O54: 0 | Q54: P.3.4 | R54: =T54+V54+X54+Z54+AB54+AD54+AF54+AH54+AJ54+AL54+AN54+AP54 -> 0 | S54: =U54+W54+Y54+AA54+AC54+AE54+AG54+AI54+AK54+AM54+AO54+AQ54 -> 0 | AS54: 0 | AT54: 0 | AU54: 0 | AV54: 0 | AW54: 0 | AX54: =((H54-1181.25)/1.18-AT54-AW54)*0.1 -> 3781.9186 | BI54: Реаб. | BJ54: 44985 | BK54: Принят | BL54: SGG | BM54: 44656 | BN54: BSP-220405-1/2(1.1.6) | BQ54: Yes
A55: 1544 | B55: Шида Картли | C55: Хашури | D55: 1.1.7. Г. Хашури, Реабилитация газопровода на улицах Сумбаташвили (P.3.10), Св. Нино и Хетагурова (P.3.11). | E55: Газ Констракт | F55: 70000 | H55: 108334.6 | J55: =16525.62+AS55+AV55 -> 108334.6 | K55: =F55-J55 -> -38334.6 | L55: =H55-J55 -> 0 | M55: 1580 | N55: =IF(OR(BK55="принят",BK55="Завершено",BK55="ПриПро"),H55-J55,F55-J55) -> 1.4551915e-11 | O55: 0 | Q55: P.3.10; P.3.11 | R55: =T55+V55+X55+Z55+AB55+AD55+AF55+AH55+AJ55+AL55+AN55+AP55 -> 0 | S55: =U55+W55+Y55+AA55+AC55+AE55+AG55+AI55+AK55+AM55+AO55+AQ55 -> 0 | AS55: 0 | AT55: 0 | AU55: 0 | AV55: 91808.98 | AW55: 11657.23 | AX55: =(H55/1.18-AT55-AW55)*0.1 -> 8015.1753 | BI55: Реаб. | BJ55: 45069 | BK55: Принят | BL55: SGG | BM55: 44656 | BN55: BSP-220405-1/2(1.1.7) | BP55: გადმოსატანია 2023-ში, ჩასაბარებელია. | BQ55: Yes
A56: 1545 | B56: Шида Картли | C56: Хашури | D56: 1.1.8. Г. Хашури, вынос счетчиков на Улицах Цхвирашвили и Руставели. P.3.26 | E56: Газ Констракт | F56: 30000 | G56: 2 | H56: =1782+73801.39 -> 75583.39 | I56: =H56-1782 -> 73801.39 | J56: =271.83+1510.17+11257.84+62543.55 -> 75583.39 | K56: =F56-J56 -> -45583.39 | L56: =H56-J56 -> 0 | M56: 2080.4 | N56: =IF(OR(BK56="принят",BK56="Завершено",BK56="ПриПро"),H56-J56,F56-J56) -> 0 | O56: 0 | Q56: P.3.26 | R56: =T56+V56+X56+Z56+AB56+AD56+AF56+AH56+AJ56+AL56+AN56+AP56 -> 0 | S56: =U56+W56+Y56+AA56+AC56+AE56+AG56+AI56+AK56+AM56+AO56+AQ56 -> 0 | AS56: 0 | AT56: 0 | AU56: 0 | BA56: =IF(BK56="Принят",(I56/1.18-AW56-AZ56)*0.1,I56/1.18*0.8*0.1) -> 6254.3551 | BB56: =(I56/1.18-AT56-AW56-AZ56)*0.1-BA56 -> 0 | BE56: =(I56/1.18-AT56-AW56-AZ56-BD56)*0.1-AU56-AX56-BA56-BB56 -> 0 | BI56: Реаб. | BJ56: 45351 | BK56: Принят | BL56: SGG | BM56: 44656 | BN56: BSP-220405-1/2(1.1.8) | BP56: დასრულდა | BQ56: Yes
A57: 1546 | B57: Шида Картли | C57: Хашури | D57: 1.1.9. Г. Хашури, ул Хачидзе, (cанаторий «Сурами») вынос счетчиков. | E57: Газ Констракт | F57: 25000 | H57: 29184.28 | J57: =4451.839+24732.441 -> 29184.28 | K57: =F57-J57 -> -4184.28 | L57: =H57-J57 -> 0 | M57: 513.5 | N57: =IF(OR(BK57="принят",BK57="Завершено",BK57="ПриПро"),H57-J57,F57-J57) -> 0 | O57: 0 | Q57: P.3.235 | R57: =T57+V57+X57+Z57+AB57+AD57+AF57+AH57+AJ57+AL57+AN57+AP57 -> 0 | S57: =U57+W57+Y57+AA57+AC57+AE57+AG57+AI57+AK57+AM57+AO57+AQ57 -> 0 | AS57: 0 | AT57: 0 | AU57: 0 | AV57: 0 | AW57: 0 | AX57: =(H57/1.18-AT57-AW57)*0.1 -> 2473.2441 | BI57: Реаб. | BJ57: 44985 | BK57: Принят | BL57: SGG | BM57: 44656 | BN57: BSP-220405-1/2(1.1.9) | BQ57: Yes
A58: 1547 | B58: Шида Картли | C58: Карели | D58: 1.1.10. Окольцование газопровода с.Цвери Карельского муниципалитета. (проектирование и строительство) ( P.3.147) | E58: Газ Констракт | F58: 40000 | H58: =1664.25+70734.34 -> 72398.59 | J58: =253.868+10789.98+61354.742 -> 72398.59 | K58: =F58-J58 -> -32398.59 | L58: =H58-J58 -> 0 | M58: 849.3 | N58: =IF(OR(BK58="принят",BK58="Завершено",BK58="ПриПро"),H58-J58,F58-J58) -> 0 | O58: 0 | Q58: P.3.147 | R58: =T58+V58+X58+Z58+AB58+AD58+AF58+AH58+AJ58+AL58+AN58+AP58 -> 0 | S58: =U58+W58+Y58+AA58+AC58+AE58+AG58+AI58+AK58+AM58+AO58+AQ58 -> 0 | AS58: 0 | AT58: 0 | AU58: 0 | AV58: 0 | AW58: 0 | AX58: =((H58-1664.25)/1.18-AT58-AW58)*0.1 -> 5994.4356 | BI58: Реаб. | BJ58: 44985 | BK58: Принят | BL58: SGG | BM58: 44656 | BN58: BSP-220405-1/2(1.1.10) | BQ58: Yes
A59: 1548 | B59: Шида Картли | C59: Хашури | D59: 1.1.11. Переключение 110 абонентов с узла №1 на узел №29 в с.Цхрамуха Хашурского муниципалитета. (проектирование и строительство) | E59: Газ Констракт | F59: 5000 | H59: 5388.94 | J59: =822.041+4566.899 -> 5388.94 | K59: =F59-J59 -> -388.94 | L59: =H59-J59 -> 0 | M59: 69.9 | N59: =IF(OR(BK59="принят",BK59="Завершено",BK59="ПриПро"),H59-J59,F59-J59) -> -9.094947e-13 | O59: 0 | Q59: P.3.16 | R59: =T59+V59+X59+Z59+AB59+AD59+AF59+AH59+AJ59+AL59+AN59+AP59 -> 0 | S59: =U59+W59+Y59+AA59+AC59+AE59+AG59+AI59+AK59+AM59+AO59+AQ59 -> 0 | AS59: 0 | AT59: 0 | AU59: 0 | AV59: 0 | AW59: 0 | AX59: =(H59/1.18-AT59-AW59)*0.1 -> 456.68983 | BI59: Реаб. | BJ59: 44985 | BK59: Принят | BL59: SGG | BM59: 44656 | BN59: BSP-220405-1/2(1.1.11) | BQ59: Yes
A60: 1549 | B60: Самцхе Джавахети | C60: Аспиндза | D60: 1.1.1. В муниципалитете Адигени, с. Саро и с. Хизабавра Реабилитация сети, замена и вынос счетчиков. (P.3.104, P.3.112, P.3.30, P.3.31, P.3.32, P.3.33) | E60: Газ Констракт | F60: 350000 | H60: =19355+N("Project")+488913.92+130000+7938+5670+N("080823")+160000+N("310823")+6399+N("290923")+1072+13114.59+N("პროექტი გადაერთებები")+29552.87 -> 862015.38 | I60: =H60-19355-13114.59 -> 829545.79 | J60: =74580.089+2952.457+430736.374+19830.51+1210.88+AS60+AV60+864.915+24406.779+976.12+163.53+2000.53+53725.4059 -> 862015.38 | K60: =F60-J60 -> -512015.38 | L60: =H60-J60 -> 9.9999714e-05 | M60: 18554.75 | N60: =IF(OR(BK60="принят",BK60="Завершено",BK60="ПриПро"),H60-J60,F60-J60) -> 9.9999714e-05 | O60: 0 | Q60: P.3.104; P.3.112; P.3.30; P.3.31; P.3.32; P.3.33 | R60: =T60+V60+X60+Z60+AB60+AD60+AF60+AH60+AJ60+AL60+AN60+AP60 -> 0 | S60: =U60+W60+Y60+AA60+AC60+AE60+AG60+AI60+AK60+AM60+AO60+AQ60 -> 0 | AS60: 0 | AT60: 0 | AU60: 0 | AV60: =110169.49+4805.08+135593.22 -> 250567.79 | AW60: =13848.15+530.01+13143.26 -> 27521.42 | AX60: =((H60-19355+N("გარე ქს.")-13114.59+N("შიდა ქს."))/1.18-AT60-AW60)*0.1 -> 67548.349 | BG60: =488913.92 -> 488913.92 | BH60: 44925 | BI60: Реаб. | BJ60: 45287 | BK60: Принят | BL60: Сакорггаз | BM60: 44676 | BN60: BCP-220425-1/2(1.1.1) | BQ60: Yes
A61: 1550 | B61: Шида Картли | C61: Гори | D61: 1.1.2. В муниципалитете Гори, реабилитация газопровода от ГРС-а Начармагеви до c. Кицниси. (P.3.93) (проектирование и строительство) | E61: Газ Констракт | F61: 2200000 | H61: =1128400+542500+564200+25371.5+N("პროექტი")+645026.17+81278.8 -> 2986776.5 | I61: =H61-25371.5 -> 2961405 | J61: =172128.81+82754.24+86064.406+98393.82+3870.228+AS61+568133.626+AV61+12398.46+68880.33 -> 2986776.5 | K61: =F61-J61 -> -786776.46 | L61: =H61-J61 -> 0.0099999993 | M61: 15217 | N61: =IF(OR(BK61="принят",BK61="Завершено",BK61="ПриПро"),H61-J61,F61-J61) -> 0.0099999993 | O61: 0 | Q61: P.3.93 | R61: =T61+V61+X61+Z61+AB61+AD61+AF61+AH61+AJ61+AL61+AN61+AP61 -> 0 | S61: =U61+W61+Y61+AA61+AC61+AE61+AG61+AI61+AK61+AM61+AO61+AQ61 -> 0 | AS61: =856271.19+100000+459745.76+478135.59 -> 1894152.5 | AT61: =56103.36+6305.48+26533+21699.5 -> 110641.34 | AU61: 0 | AV61: 0 | AW61: 0 | AX61: =((H61-25371.5)/1.18-AT61-AW61)*0.1 -> 239902.39 | BG61: =1128400+542500+564200+645026.17 -> 2880126.2 | BH61: 44925 | BI61: Реаб. | BJ61: 45169 | BK61: Принят | BL61: Сакорггаз | BM61: 44676 | BN61: BCP-220425-1/2(1.1.2) | BQ61: Yes
A62: 1551 | B62: Шида Картли | C62: Гори | D62: 1.1.3. Г. Гори замена-вынос счётчиков на ул. Пушкина, Цхинвалское шоссе, с. Свенети и реабилитационные работы сети в с. Тинисхиди. (P.3.94 (1)) | E62: Газ Констракт | F62: 250000 | G62: 2 | K62: =F62-J62 -> 250000 | L62: =H62-J62 -> 0 | N62: =IF(OR(BK62="принят",BK62="Завершено",BK62="ПриПро"),H62-J62,F62-J62) -> 250000 | O62: 1 | Q62: P.3.94 (1) | R62: =T62+V62+X62+Z62+AB62+AD62+AF62+AH62+AJ62+AL62+AN62+AP62 -> 0 | S62: =U62+W62+Y62+AA62+AC62+AE62+AG62+AI62+AK62+AM62+AO62+AQ62 -> 0 | AS62: 0 | AT62: 0 | AU62: 0 | BI62: Реаб. | BK62: 0 | BL62: Сакорггаз | BM62: 44676 | BN62: BCP-220425-1/2(1.1.3) | BP62: გადმოსატანია 2023-ში
A63: 1552 | B63: Шида Картли | C63: Гори | D63: 1.1.4. Г. Гори работы по выносу счётчиков на улицах Тамар Мепе, Беруашвили, Чантурия, Багратиони, Кутаиси и Чочишвили. (P.3.95) | E63: Газ Констракт | F63: 240000 | G63: 2 | H63: =804+N("რეგულატორების ჩამოწერა") -> 804 | J63: =804 -> 804 | K63: =F63-J63 -> 239196 | L63: =H63-J63 -> 0 | N63: =IF(OR(BK63="принят",BK63="Завершено",BK63="ПриПро"),H63-J63,F63-J63) -> 239196 | O63: 1 | Q63: P.3.95 | R63: =T63+V63+X63+Z63+AB63+AD63+AF63+AH63+AJ63+AL63+AN63+AP63 -> 0 | S63: =U63+W63+Y63+AA63+AC63+AE63+AG63+AI63+AK63+AM63+AO63+AQ63 -> 0 | AS63: 0 | AT63: 0 | AU63: 0 | BI63: Реаб. | BK63: 0 | BL63: Сакорггаз | BM63: 44676 | BN63: BCP-220425-1/2(1.1.4)
A64: 1553 | B64: Шида Картли | C64: Гори | D64: 1.1.5. В муниципалитете Гори, в с. Меджврисхеви реабилитация питающего газопровода от узла учета до центра села. (P.3.81) | E64: Газ Констракт | F64: 200000 | H64: =320000+52000+609.3 -> 372609.3 | J64: =48813.56+AS64+AV64+7932.203+44677.097 -> 372609.3 | K64: =F64-J64 -> -172609.3 | L64: =H64-J64 -> 0 | M64: 2130 | N64: =IF(OR(BK64="принят",BK64="Завершено",BK64="ПриПро"),H64-J64,F64-J64) -> 0 | O64: 0 | Q64: P.3.81 | R64: =T64+V64+X64+Z64+AB64+AD64+AF64+AH64+AJ64+AL64+AN64+AP64 -> 0 | S64: =U64+W64+Y64+AA64+AC64+AE64+AG64+AI64+AK64+AM64+AO64+AQ64 -> 0 | AS64: 0 | AT64: 0 | AU64: 0 | AV64: =271186.44 -> 271186.44 | AW64: 32014.86 | AX64: =(H64/1.18-AT64-AW64)*0.1 -> 28375.573 | BI64: Реаб. | BJ64: 45289 | BK64: принят | BL64: Сакорггаз | BM64: 44676 | BN64: BCP-220425-1/2(1.1.5) | BQ64: Yes
A65: 1554 | B65: Шида Картли | C65: Гори | D65: 1.1.6. Работы по реабилитации газопровода от центра Меджврисхеви по направлению Ахалубани в Горийском муниципалитете. (P.3.101) (проектирование и строительство) | E65: Газ Констракт | F65: 130000 | H65: =3741.5+N("პროექტი")+205000+722.14-0+N("პროექტი") -> 209463.64 | I65: =H65-3741.5 -> 205722.14 | J65: =570.737+3170.763+31271.186+AS65+AV65+722.14 -> 209463.64 | K65: =F65-J65 -> -79463.636 | L65: =H65-J65 -> 0.004 | M65: 2246.4 | N65: =IF(OR(BK65="принят",BK65="Завершено",BK65="ПриПро"),H65-J65,F65-J65) -> 0.004 | O65: 0 | Q65: P.3.101 | R65: =T65+V65+X65+Z65+AB65+AD65+AF65+AH65+AJ65+AL65+AN65+AP65 -> 0 | S65: =U65+W65+Y65+AA65+AC65+AE65+AG65+AI65+AK65+AM65+AO65+AQ65 -> 0 | AS65: 0 | AT65: 0 | AU65: 0 | AV65: =173728.81 -> 173728.81 | AW65: 20509.52 | AX65: =((H65-3741.5)/1.18-AT65-AW65)*0.1 -> 15383.128 | BI65: Реаб. | BJ65: 45260 | BK65: принят | BL65: Сакорггаз | BM65: 44676 | BN65: BCP-220425-1/2(1.1.6) | BQ65: Yes
A66: 1555 | B66: Шида Картли | C66: Гори | D66: 1.1.7. В муниципалитете Гори, с. Реха работы по реабилитации питающего газопровода (P.3.98) (проектирование и строительство) | E66: Газ Констракт | F66: 90000 | H66: =182370+5575.5+N("პროექტი")+43620.58 -> 231566.08 | I66: =H66-5575.5 -> 225990.58 | J66: =27819.15+850.5+AS66+4725+6653.99+AV66 -> 231566.08 | K66: =F66-J66 -> -141566.08 | L66: =H66-J66 -> 0 | M66: 3062 | N66: =IF(OR(BK66="принят",BK66="Завершено",BK66="ПриПро"),H66-J66,F66-J66) -> 2.910383e-11 | O66: 0 | Q66: P.3.98 | R66: =T66+V66+X66+Z66+AB66+AD66+AF66+AH66+AJ66+AL66+AN66+AP66 -> 0 | S66: =U66+W66+Y66+AA66+AC66+AE66+AG66+AI66+AK66+AM66+AO66+AQ66 -> 0 | AS66: 154550.85 | AT66: 5743.79 | AU66: 0 | AV66: 36966.59 | AW66: 4646.65 | AX66: =((H66-5575.5)/1.18-AT66-AW66)*0.1 -> 18112.7 | BI66: Реаб. | BJ66: 45069 | BK66: Принят | BL66: Сакорггаз | BM66: 44676 | BN66: BCP-220425-1/2(1.1.7) | BQ66: Yes
A67: 1556 | B67: Шида Картли | C67: Гори | D67: 1.1.8. Реабилитационные работы газопровода возле Университета в Гори. (P.3.90) (проектирование и строительство) | E67: Газ Констракт | F67: 90000 | H67: =2546.25+N("პროექტი")+191383.97 -> 193930.22 | I67: =H67-2546.25 -> 191383.97 | J67: =388.41+29194.165+AS67+AV67 -> 193930.23 | K67: =F67-J67 -> -103930.23 | L67: =H67-J67 -> -0.005 | M67: 1416.5 | N67: =IF(OR(BK67="принят",BK67="Завершено",BK67="ПриПро"),H67-J67,F67-J67) -> -0.005 | O67: 0 | Q67: P.3.90 | R67: =T67+V67+X67+Z67+AB67+AD67+AF67+AH67+AJ67+AL67+AN67+AP67 -> 0 | S67: =U67+W67+Y67+AA67+AC67+AE67+AG67+AI67+AK67+AM67+AO67+AQ67 -> 0 | AS67: 0 | AT67: 0 | AU67: 0 | AV67: 164347.65 | AW67: 20387.04 | AX67: =((H67-2546.25)/1.18-AT67-AW67)*0.1 -> 14180.277 | BI67: Реаб. | BJ67: 45076 | BK67: Принят | BL67: Сакорггаз | BM67: 44676 | BN67: BCP-220425-1/2(1.1.8) | BP67: გადმოსატანია 2023-ში | BQ67: Yes
A68: 1557 | B68: Шида Картли | C68: Гори | D68: 1.1.9. В муниципалитете Гори, реабилитация газопровода от с. Тквиави по направлению сёл Тирдзниси-Дици. (P.3.97) | E68: Газ Констракт | F68: 460000 | H68: =378000+619763.31 -> 997763.31 | J68: =57661.02+AS68+94540.17+AV68 -> 997763.33 | K68: =F68-J68 -> -537763.33 | L68: =H68-J68 -> -0.02 | M68: 6028 | N68: =IF(OR(BK68="принят",BK68="Завершено",BK68="ПриПро"),H68-J68,F68-J68) -> -0.02 | O68: 0 | Q68: P.3.97 | R68: =T68+V68+X68+Z68+AB68+AD68+AF68+AH68+AJ68+AL68+AN68+AP68 -> 0 | S68: =U68+W68+Y68+AA68+AC68+AE68+AG68+AI68+AK68+AM68+AO68+AQ68 -> 0 | AS68: 320339 | AT68: 16381.17 | AU68: 0 | AV68: 525223.14 | AW68: 65573.75 | AX68: =(H68/1.18-AT68-AW68)*0.1 -> 76360.721 | BI68: Реаб. | BJ68: 45044 | BK68: Принят | BL68: Сакорггаз | BM68: 44676 | BN68: BCP-220425-1/2(1.1.9) | BQ68: Yes
A69: 1558 | B69: Шида Картли | C69: Гори | D69: 1.1.10. В г. Гори реабилитация участка ул. Сухишвили и ул. Меджврисхеви. (P.3.114) (проектирование и строительство) | E69: Газ Констракт | F69: 50000 | H69: =2682.75+143371.09 -> 146053.84 | I69: =H69-2682.75 -> 143371.09 | J69: =409.23+2273.52+21870.17+AS69+AV69 -> 146053.84 | K69: =F69-J69 -> -96053.84 | L69: =H69-J69 -> 0 | M69: 1056 | N69: =IF(OR(BK69="принят",BK69="Завершено",BK69="ПриПро"),H69-J69,F69-J69) -> 0 | O69: 0 | Q69: P.3.114 | R69: =T69+V69+X69+Z69+AB69+AD69+AF69+AH69+AJ69+AL69+AN69+AP69 -> 0 | S69: =U69+W69+Y69+AA69+AC69+AE69+AG69+AI69+AK69+AM69+AO69+AQ69 -> 0 | AS69: 0 | AT69: 0 | AU69: 0 | AV69: 121500.92 | AW69: 15272.9 | AX69: =((H69-2682.75)/1.18-AT69-AW69)*0.1 -> 10622.802 | BI69: Реаб. | BJ69: 45076 | BK69: Принят | BL69: Сакорггаз | BM69: 44676 | BN69: BCP-220425-1/2(1.1.10) | BP69: მხოლოდ პროექტია მიღებული 2022-ის დეკემბერში, შესაძლებელია გაყოფა. | BQ69: Yes
A70: 1559 | B70: Шида Картли | C70: Гори | D70: 1.1.11. В муниципалитете Гори, в с. Шавшвеби реабилитационные работы по восстановлению/реконструкции газопровода. (P.3.80) (проектирование и строительство) | E70: Газ Констракт | F70: 145000 | H70: =167601+6041+N("პროექტი გარე ქსელი")+85000+N("080823")+2103.5+N("პროექტი გადართვები")+4341.6+N("რეგულატორების ჩამოწერა")-0+N("პროექტი გარე ქსელი")-0+N("პროექტი გადართვები")+7428.27 -> 272515.37 | I70: =H70-6041-2103.5 -> 264370.87 | J70: =25566.25+921.508+AS70+5119.492+AV70+12966.1+320.873+662.277+1133.125+11757.095 -> 272515.37 | K70: =F70-J70 -> -127515.37 | L70: =H70-J70 -> 0 | M70: 4580.4 | N70: =IF(OR(BK70="принят",BK70="Завершено",BK70="ПриПро"),H70-J70,F70-J70) -> 0 | O70: 0 | Q70: P.3.80 | R70: =T70+V70+X70+Z70+AB70+AD70+AF70+AH70+AJ70+AL70+AN70+AP70 -> 0 | S70: =U70+W70+Y70+AA70+AC70+AE70+AG70+AI70+AK70+AM70+AO70+AQ70 -> 0 | AS70: =142034.75+N("2022") -> 142034.75 | AT70: =5136.6+142.03 -> 5278.63 | AU70: 0 | AV70: =72033.9 -> 72033.9 | AW70: =7945.44 -> 7945.44 | AX70: =((H70-6041-2103.5)/1.18-AT70-AW70)*0.1 -> 21081.904 | BI70: Реаб. | BJ70: 45260 | BK70: Принят | BL70: Сакорггаз | BM70: 44676 | BN70: BCP-220425-1/2(1.1.11) | BQ70: Yes
A71: 1596 | B71: Кахети | C71: Гурджаани | D71: 1.1.5. Гурджаанском муниципалитете реабилитационные работы на газопроводах низкого давления в с.Чумлаки: участок Баги (P.2.24), участок Липарташвили (P.2.23), участок Гогра (P.2.180), участок Бадуашвили (P.2.19), Гагма Чумлаки (P.2.33), по направлению с. Китаани (P.2.31). | E71: Интерсервис 2011 | F71: 365000 | H71: =250000+95000+100000+30474 -> 475474 | J71: =38135.59+14491.525+200000+15254.24+AS71-10559+N("გადავიდა წერილით 1.1.11-ზე")-14030+N("გადავიდა წერილით 1.1.3-ზე")-14113+N("გადავიდა წერილით 1.1.7-ზე")-10521+N("გადავიდა წერილით 1.1.8-ზე")-5321+N("გადავიდა წერილით 1.1.9-ზე")-30236.24+N("გადავიდა წერილით 1.1.4-ზე") -> 475473.99 | K71: =F71-J71 -> -110473.99 | L71: =H71-J71 -> 0.005 | M71: 7694 | N71: =IF(OR(BK71="принят",BK71="Завершено",BK71="ПриПро"),H71-J71,F71-J71) -> 0.005 | O71: 0 | Q71: P.2.24; P.2.23; P.2.180; P.2.19; P.2.33; P.2.31 | R71: =T71+V71+X71+Z71+AB71+AD71+AF71+AH71+AJ71+AL71+AN71+AP71 -> 0 | S71: =U71+W71+Y71+AA71+AC71+AE71+AG71+AI71+AK71+AM71+AO71+AQ71 -> 0 | AS71: =211864.41+80508.47 -> 292372.88 | AT71: 13268.92 | AU71: =IF(H71<50000,0,IF(AT71>0,(H71/1.18-AT71-H71/100*0.8)*0.1,(H71/1.18-H71/1.18/100*5.4-H71/100*0.8)*0.1)) -> 38587.136 | AV71: 0 | AW71: 0 | BE71: 0 | BI71: Реаб. | BJ71: 44925 | BK71: Принят | BL71: SGG | BM71: 44680 | BN71: BSP-220429-1/2(1.1.5) | BQ71: Yes
A72: 1627 | B72: Имерети | C72: Кутаиси | D72: 1.1.18. В г. Кутаиси, реаибилитация газопровода по алее Агмашенебели. (P.6.799) | E72: Газсервис | F72: 420000 | H72: =270000+111332.28+14121.39 -> 395453.67 | J72: =41186.44+0+16982.89+2154.11+11967.28+AS72 -> 395453.67 | K72: =F72-J72 -> 24546.33 | L72: =H72-J72 -> 0 | M72: 1684 | N72: =IF(OR(BK72="принят",BK72="Завершено",BK72="ПриПро"),H72-J72,F72-J72) -> 0 | O72: 0 | Q72: P.6.799 | R72: =T72+V72+X72+Z72+AB72+AD72+AF72+AH72+AJ72+AL72+AN72+AP72 -> 0 | S72: =U72+W72+Y72+AA72+AC72+AE72+AG72+AI72+AK72+AM72+AO72+AQ72 -> 0 | AS72: 323162.95 | AT72: 30911.43 | AU72: =IF(H72<50000,0,IF(AT72>0,(H72/1.18-AT72-H72/100*0.8)*0.1,(H72/1.18-H72/1.18/100*5.4-H72/100*0.8)*0.1)) -> 30105.517 | BI72: Реаб. | BJ72: 44925 | BK72: Принят | BL72: Сакорггаз | BM72: 44641 | BN72: BCP-220321-1/2(1.1.18)
A73: 1617 | B73: Имерети | C73: Терджола | D73: 1.1.8. В г. Терджола, реабилитация газопровода по ул. Леселидзе. (P.6.138) | E73: Газсервис | F73: 226000 | H73: =120000+150000+77820.83 -> 347820.83 | J73: =18305.08+22881.36+11870.97+AS73+65949.86 -> 347820.83 | K73: =F73-J73 -> -121820.83 | L73: =H73-J73 -> 0 | M73: 1658 | N73: =IF(OR(BK73="принят",BK73="Завершено",BK73="ПриПро"),H73-J73,F73-J73) -> 5.8207661e-11 | O73: 0 | Q73: P.6.138 | R73: =T73+V73+X73+Z73+AB73+AD73+AF73+AH73+AJ73+AL73+AN73+AP73 -> 0 | S73: =U73+W73+Y73+AA73+AC73+AE73+AG73+AI73+AK73+AM73+AO73+AQ73 -> 0 | AS73: 228813.56 | AT73: 19484.67 | AU73: =IF(H73<50000,0,IF(AT73>0,(H73/1.18-AT73-H73/100*0.8)*0.1,(H73/1.18-H73/1.18/100*5.4-H73/100*0.8)*0.1)) -> 27249.618 | BI73: Реаб. | BJ73: 44925 | BK73: Принят | BL73: Сакорггаз | BM73: 44641 | BN73: BCP-220321-1/2(1.1.8)
A74: 1606 | B74: Аджара | C74: Кобулети | D74: 1.1.2. Замена металлического газопровода D=200мм, проходящего через реку В Кобулети, с. Бобоквати на металлический газопровод D=500мм. (P.5.4) | E74: Газсервис | F74: 210000 | H74: =220000+111198.46 -> 331198.46 | J74: =33559.32+16962.4769+AS74+94235.6631 -> 331198.46 | K74: =F74-J74 -> -121198.46 | L74: =H74-J74 -> 0 | M74: 246 | N74: =IF(OR(BK74="принят",BK74="Завершено",BK74="ПриПро"),H74-J74,F74-J74) -> 0 | O74: 0 | Q74: P.5.4 | R74: =T74+V74+X74+Z74+AB74+AD74+AF74+AH74+AJ74+AL74+AN74+AP74 -> 0 | S74: =U74+W74+Y74+AA74+AC74+AE74+AG74+AI74+AK74+AM74+AO74+AQ74 -> 0 | AS74: 186441 | AT74: 13594.85 | AU74: =IF(H74<50000,0,IF(AT74>0,(H74/1.18-AT74-H74/100*0.8)*0.1,(H74/1.18-H74/1.18/100*5.4-H74/100*0.8)*0.1)) -> 26443.222 | BI74: Реаб. | BJ74: 44925 | BK74: Принят | BL74: SGG | BM74: 44683 | BN74: BSP-220502-2/3(1.1.2)
A75: 1564 | B75: Мцхета-Мтианети | C75: Мцхета | D75: 1.1.16. В муниципалитете Мцхета, в с. Церовани, с. Презети и с. Цилкани вынос сетей газопроводов и узлов учета с частных территорий. (ფრეზეთი) (P.3.58) | E75: Газ Констракт | F75: 3287000 | G75: 2 | H75: =661030.75+124000+16133.6+60.02+R75 -> 864766.84 | I75: =H75-AF75 -> 853684.09 | J75: =97937.656+100835.199+AS75+1564754.866+18915.25+45762.711+30508.475+45762.71+15254.24+2461.057+2853.518+3483.09+61016.95+30508.47+S75+AV75+AY75+BC75 -> 2325875.6 | K75: =F75-J75 -> 961124.4 | L75: =H75-J75 -> -1461108.8 | M75: =19683-6333 -> 13350 | N75: =IF(OR(BK75="принят",BK75="Завершено",BK75="ПриПро"),H75-J75,F75-J75) -> -1461108.8 | O75: 1 | Q75: P.3.58 | R75: =T75+V75+X75+Z75+AB75+AD75+AF75+AH75+AJ75+AL75+AN75+AP75 -> 63542.47 | S75: =U75+W75+Y75+AA75+AC75+AE75+AG75+AI75+AK75+AM75+AO75+AQ75 -> 200736.65 | U75: =9.16+N("ფრეზეთი")+155.645+N("წილკანი")+8899.24+N("წეროვანი") -> 9064.045 | Y75: 68644.07 | AE75: 45762.71 | AF75: =6333*1.75 -> 11082.75 | AH75: 52459.72 | AI75: 1690.59 | AK75: 75575.24 | AS75: 0 | AT75: 0 | AU75: 0 | AV75: 105084.75 | AY75: 0 | BA75: =6199595.34/1.18*0.8*0.1 -> 420311.55 | BC75: 0 | BG75: 661030.75 | BH75: 44925 | BI75: Реаб. | BJ75: 45894 | BK75: Принят | BL75: Сакорггаз | BM75: 44676 | BN75: BCP-220425-1/2(1.1.16) | BQ75: Yes
A76: 1565 | B76: Шида Картли | C76: Каспи | D76: 1.1.17. В г. Каспи реабилитация газопровода на улицах Мириан Мепе, Леселидзе, Костава, Руставели и Чавчавадзе. (P.3.105 (1)) | E76: Газ Констракт | F76: 300000 | G76: 2 | K76: =F76-J76 -> 300000 | L76: =H76-J76 -> 0 | N76: =IF(OR(BK76="принят",BK76="Завершено",BK76="ПриПро"),H76-J76,F76-J76) -> 300000 | O76: 1 | Q76: P.3.105 (1) | R76: =T76+V76+X76+Z76+AB76+AD76+AF76+AH76+AJ76+AL76+AN76+AP76 -> 0 | S76: =U76+W76+Y76+AA76+AC76+AE76+AG76+AI76+AK76+AM76+AO76+AQ76 -> 0 | AS76: 0 | AT76: 0 | AU76: 0 | BI76: Реаб. | BK76: 0 | BL76: Сакорггаз | BM76: 44676 | BN76: BCP-220425-1/2(1.1.17) | BP76: ეს გასაუქმებელია რადგან კეთდება P.3.49 (1)-თან ერთად.
A77: 1566 | B77: Шида Картли | C77: Каспи | D77: 1.1.18. В г. Каспи замена и вынос счетчиков на улицах Церетели, 26 Мая, Шарикашвили, Гурамишвили и Агмашенебели (II Этап). (P.3.49 (1)) | E77: Газ Констракт | F77: 1200000 | G77: 2 | H77: =1377+162+81+12800+1053+3726+1863+234+243+81 -> 21620 | J77: =210.05+24.71+12.36+1372.88+1952.54+10847.46+160.627+568.37+284.19+243+81+S77+AW77 -> 19483.187 | K77: =F77-J77 -> 1180516.8 | L77: =H77-J77 -> 2136.813 | N77: =IF(OR(BK77="принят",BK77="Завершено",BK77="ПриПро"),H77-J77,F77-J77) -> 1180516.8 | O77: 1 | Q77: P.3.49 (1) | R77: =T77+V77+X77+Z77+AB77+AD77+AF77+AH77+AJ77+AL77+AN77+AP77 -> 0 | S77: =U77+W77+Y77+AA77+AC77+AE77+AG77+AI77+AK77+AM77+AO77+AQ77 -> 0 | AS77: 0 | AT77: 0 | AU77: 0 | AW77: 3726 | BI77: Реаб. | BK77: 45 | BL77: Сакорггаз | BM77: 44676 | BN77: BCP-220425-1/2(1.1.18) | BQ77: Yes
A78: 1567 | B78: Шида Картли | C78: Каспи | D78: 1.1.19. В г. Каспи реабилитационные работы газопровода по улице Бахтриони-Мазанашвили. (P.3.43) | E78: Газ Констракт | F78: 18000 | H78: 20844.45 | J78: =3179.66+17664.79 -> 20844.45 | K78: =F78-J78 -> -2844.45 | L78: =H78-J78 -> 0 | M78: 103 | N78: =IF(OR(BK78="принят",BK78="Завершено",BK78="ПриПро"),H78-J78,F78-J78) -> 0 | O78: 0 | Q78: P.3.43 | R78: =T78+V78+X78+Z78+AB78+AD78+AF78+AH78+AJ78+AL78+AN78+AP78 -> 0 | S78: =U78+W78+Y78+AA78+AC78+AE78+AG78+AI78+AK78+AM78+AO78+AQ78 -> 0 | AS78: 0 | AT78: 0 | AU78: =IF(H78<50000,0,IF(AT78>0,(H78/1.18-AT78-H78/100*0.8)*0.1,(H78/1.18-H78/1.18/100*5.4-H78/100*0.8)*0.1)) -> 0 | BI78: Реаб. | BJ78: 44925 | BK78: Принят | BL78: Сакорггаз | BM78: 44676 | BN78: BCP-220425-1/2(1.1.19)
A79: 1568 | B79: Шида Картли | C79: Каспи | D79: 1.1.20. В Каспском муниципалитете, в с. Кодисцкаро установка стояков. (P.3.48) | E79: Газ Констракт | F79: 9000 | H79: 19192.85 | J79: =2927.72+16265.13 -> 19192.85 | K79: =F79-J79 -> -10192.85 | L79: =H79-J79 -> 0 | M79: 0 | N79: =IF(OR(BK79="принят",BK79="Завершено",BK79="ПриПро"),H79-J79,F79-J79) -> 0 | O79: 0 | Q79: P.3.48 | R79: =T79+V79+X79+Z79+AB79+AD79+AF79+AH79+AJ79+AL79+AN79+AP79 -> 0 | S79: =U79+W79+Y79+AA79+AC79+AE79+AG79+AI79+AK79+AM79+AO79+AQ79 -> 0 | AS79: 0 | AT79: 0 | AU79: 0 | AV79: 0 | AW79: 0 | AX79: =(H79/1.18-AT79-AW79)*0.1 -> 1626.5127 | BI79: Реаб. | BJ79: 44985 | BK79: Принят | BL79: Сакорггаз | BM79: 44676 | BN79: BCP-220425-1/2(1.1.20) | BQ79: Yes
A80: 1569 | B80: Шида Картли | C80: Каспи | D80: 1.1.21. В г. Каспи реабилитационные работы газопроводов на пересечении улиц Агмашенебели и Габашвили. (P.3.47, P.3.50) | E80: Газ Констракт | F80: 23000 | G80: 2 | H80: 63711.67 | I80: 63711.67 | J80: =9718.729+53992.941 -> 63711.67 | K80: =F80-J80 -> -40711.67 | L80: =H80-J80 -> 0 | M80: 535 | N80: =IF(OR(BK80="принят",BK80="Завершено",BK80="ПриПро"),H80-J80,F80-J80) -> 0 | O80: 0 | Q80: P.3.47; P.3.50 | R80: =T80+V80+X80+Z80+AB80+AD80+AF80+AH80+AJ80+AL80+AN80+AP80 -> 0 | S80: =U80+W80+Y80+AA80+AC80+AE80+AG80+AI80+AK80+AM80+AO80+AQ80 -> 0 | AS80: 0 | AT80: 0 | AU80: 0 | BA80: 0 | BB80: =(H80/1.18-AT80-AW80-AZ80)*0.1-BA80 -> 5399.2941 | BE80: =(H80/1.18-AT80-AW80-AZ80-BD80)*0.1-AU80-AX80-BA80-BB80 -> 0 | BI80: Реаб. | BJ80: 45621 | BK80: Принят | BL80: Сакорггаз | BM80: 44676 | BN80: BCP-220425-1/2(1.1.21) | BQ80: Yes
A81: 1570 | B81: Самцхе Джавахети | C81: Борджоми | D81: 1.1.22. В Боржоми проектно-строительные работы по реабилитации подземного стального газопровода от моста Чархисцкали до церкви Давида. (P.3.34) (проектирование и строительство) | E81: Газ Констракт | F81: 50000 | G81: 2 | K81: =F81-J81 -> 50000 | L81: =H81-J81 -> 0 | N81: =IF(OR(BK81="принят",BK81="Завершено",BK81="ПриПро"),H81-J81,F81-J81) -> 50000 | O81: 1 | Q81: P.3.34 | R81: =T81+V81+X81+Z81+AB81+AD81+AF81+AH81+AJ81+AL81+AN81+AP81 -> 0 | S81: =U81+W81+Y81+AA81+AC81+AE81+AG81+AI81+AK81+AM81+AO81+AQ81 -> 0 | AS81: 0 | AT81: 0 | AU81: 0 | BI81: Реаб. | BK81: 0 | BL81: Сакорггаз | BM81: 44676 | BN81: BCP-220425-1/2(1.1.22) | BP81: გასაუქმებელია ხელშეკრულება. ვეღარ კეთდება, დაგებულია ახალი ასფალტი. (გასარკვევია, რატომ ჩასვეს 2025-ის გეგმაში!)
A82: 1571 | B82: Самцхе Джавахети | C82: Бакуриани | D82: 1.1.23. В пос. Бакуриани реабилитационные работы воздушного газопровода D200 по ул. Агмашенебели в районе "Никора" (P.3.35) | E82: Газ Констракт | F82: 18000 | H82: 41721.87 | J82: =6364.35+35357.52 -> 41721.87 | K82: =F82-J82 -> -23721.87 | L82: =H82-J82 -> 0 | M82: 150.95 | N82: =IF(OR(BK82="принят",BK82="Завершено",BK82="ПриПро"),H82-J82,F82-J82) -> 7.2759576e-12 | O82: 0 | Q82: P.3.35 | R82: =T82+V82+X82+Z82+AB82+AD82+AF82+AH82+AJ82+AL82+AN82+AP82 -> 0 | S82: =U82+W82+Y82+AA82+AC82+AE82+AG82+AI82+AK82+AM82+AO82+AQ82 -> 0 | AS82: 0 | AT82: 0 | AU82: =IF(H82<50000,0,IF(AT82>0,(H82/1.18-AT82-H82/100*0.8)*0.1,(H82/1.18-H82/1.18/100*5.4-H82/100*0.8)*0.1)) -> 0 | BI82: Реаб. | BJ82: 44925 | BK82: Принят | BL82: Сакорггаз | BM82: 44676 | BN82: BCP-220425-1/2(1.1.23)
A83: 1572 | B83: Самцхе Джавахети | C83: Борджоми | D83: 1.1.24. В г. Боржоми реабилитация/реконструкция наружных сетей в корпусах на улицах Руставели и Месхети. (P.3.106) (проектирование и строительство) | E83: Газ Констракт | F83: 105000 | G83: კორპუსების ჩანართზეა დეტალურად 2024 წელი | H83: =6874+N("9 პროექტი")+29848.81+N("2023-ში")+26708.12+N("2023-ში")+27667+N("2023-ში")+29222.91+N("2023-ში")+25660.88+N("2023-ში")+22779.16+N("2023-ში")+16983.31+N("2023-ში")+5359.61+N("2023-ში")+28417.62+N("2023-ში")+4980.5+N("5 პროექტი")+666.75+N("1 პროექტი") -> 225168.67 | I83: =H83-(6874+4980.5+666.75) -> 212647.42 | J83: =1048.576+4553.21+4074.12+4220.39+4457.73+3914.37+123713.324+11217.92+N("მარტის 4 მიღების დღგ")+759.737+101.707 -> 158061.08 | K83: =F83-J83 -> -53061.084 | L83: =H83-J83 -> 67107.586 | M83: =659.3+522.8+546.2+495+458.3+269+227.6+137.4+582.1 -> 3897.7 | N83: =IF(OR(BK83="принят",BK83="Завершено",BK83="ПриПро"),H83-J83,F83-J83) -> -53061.084 | O83: შესამოწმებელიადა ამოსაღებია | Q83: P.3.106 | R83: =T83+V83+X83+Z83+AB83+AD83+AF83+AH83+AJ83+AL83+AN83+AP83 -> 0 | S83: =U83+W83+Y83+AA83+AC83+AE83+AG83+AI83+AK83+AM83+AO83+AQ83 -> 0 | AS83: 0 | AT83: 0 | AU83: 0 | AV83: 0 | AW83: 0 | BG83: 212647.42 | BI83: Реаб. | BK83: 65 | BL83: Сакорггаз | BM83: 44676 | BN83: BCP-220425-1/2(1.1.24) | BQ83: Yes
A84: 1573 | B84: Самцхе Джавахети | C84: Борджоми | D84: 1.1.25. Замена старых счетчиков G 4 в Сервис/центре Боржоми (I этап). (P.3.42 (1)) | E84: Газ Констракт | F84: 80000 | H84: =4050+6561+1863+2025+38238.01 -> 52737.01 | J84: =617.8+1000.83+284.19+308.9+AS84+3294.91+5832.916+32405.094 -> 52737.01 | K84: =F84-J84 -> 27262.99 | L84: =H84-J84 -> 0 | M84: 23.7 | N84: =IF(OR(BK84="принят",BK84="Завершено",BK84="ПриПро"),H84-J84,F84-J84) -> 0 | O84: 0 | Q84: P.3.42 (1) | R84: =T84+V84+X84+Z84+AB84+AD84+AF84+AH84+AJ84+AL84+AN84+AP84 -> 0 | S84: =U84+W84+Y84+AA84+AC84+AE84+AG84+AI84+AK84+AM84+AO84+AQ84 -> 0 | AS84: 8992.37 | AT84: 652.01 | AU84: 0 | AV84: 0 | AW84: 0 | AX84: =(H84/1.18-AT84-AW84)*0.1 -> 4404.0371 | BI84: Реаб. | BJ84: 45015 | BK84: Принят | BL84: Сакорггаз | BM84: 44676 | BN84: BCP-220425-1/2(1.1.25) | BQ84: Yes
A85: 1574 | B85: Самцхе Джавахети | C85: Бакуриани | D85: 1.1.26. В Бакуриани реабилитация питающего газопровода (D 150 мм) от участка №53 по улицам Цакадзе и Боржоми до улицы 9 Апреля. (P.3.128) (проектирование и строительство) | E85: Газ Констракт | F85: 140000 | H85: =1548.75+143959.13 -> 145507.88 | I85: =H85-1548.75 -> 143959.13 | J85: =236.25+21959.87+123311.76 -> 145507.88 | K85: =F85-J85 -> -5507.88 | L85: =H85-J85 -> 0 | M85: 858 | N85: =IF(OR(BK85="принят",BK85="Завершено",BK85="ПриПро"),H85-J85,F85-J85) -> 0 | O85: 0 | Q85: P.3.128 | R85: =T85+V85+X85+Z85+AB85+AD85+AF85+AH85+AJ85+AL85+AN85+AP85 -> 0 | S85: =U85+W85+Y85+AA85+AC85+AE85+AG85+AI85+AK85+AM85+AO85+AQ85 -> 0 | AS85: 0 | AT85: 0 | AU85: 0 | AV85: 0 | AW85: 0 | AX85: =((H85-1548.75)/1.18-AT85-AW85)*0.1 -> 12199.926 | BI85: Реаб. | BJ85: 44985 | BK85: Принят | BL85: Сакорггаз | BM85: 44676 | BN85: BCP-220425-1/2(1.1.26) | BQ85: Yes
A86: 1575 | B86: Самцхе Джавахети | C86: Бакуриани | D86: 1.1.27. В Бакуриани, от ГРС-а Квибиси до с. Квибиси реабилитация трассы газопровода среднего давления (мохрешва). (P.3.121) | E86: Газ Констракт | F86: 70000 | H86: 59440.47 | J86: =9067.19+50373.28 -> 59440.47 | K86: =F86-J86 -> 10559.53 | L86: =H86-J86 -> 0 | M86: 0 | N86: =IF(OR(BK86="принят",BK86="Завершено",BK86="ПриПро"),H86-J86,F86-J86) -> 0 | O86: 0 | Q86: P.3.121 | R86: =T86+V86+X86+Z86+AB86+AD86+AF86+AH86+AJ86+AL86+AN86+AP86 -> 0 | S86: =U86+W86+Y86+AA86+AC86+AE86+AG86+AI86+AK86+AM86+AO86+AQ86 -> 0 | AS86: 0 | AT86: 0 | AU86: 0 | AV86: 0 | AW86: 0 | AX86: =(H86/1.18-AT86-AW86)*0.1 -> 5037.328 | BI86: Реаб. | BJ86: 44985 | BK86: Принят | BL86: Сакорггаз | BM86: 44676 | BN86: BCP-220425-1/2(1.1.27) | BQ86: Yes
A87: 1561 | B87: Шида Картли | C87: Гори | D87: 1.1.13. II этап работ по реабилитации газопровода от ООО «Гори» до въезда в село Меджврисхеви Горийского муниципалитета (P.3.100) | E87: Газ Констракт | F87: 240000 | H87: =305067+17015.1 -> 322082.1 | J87: =46535.64+2595.52+AS87+14419.59 -> 322082.1 | K87: =F87-J87 -> -82082.1 | L87: =H87-J87 -> 0 | M87: 3326 | N87: =IF(OR(BK87="принят",BK87="Завершено",BK87="ПриПро"),H87-J87,F87-J87) -> -5.8207661e-11 | O87: 0 | Q87: P.3.100 | R87: =T87+V87+X87+Z87+AB87+AD87+AF87+AH87+AJ87+AL87+AN87+AP87 -> 0 | S87: =U87+W87+Y87+AA87+AC87+AE87+AG87+AI87+AK87+AM87+AO87+AQ87 -> 0 | AS87: 258531.35 | AT87: 9608.16 | AU87: =IF(H87<50000,0,IF(AT87>0,(H87/1.18-AT87-H87/100*0.8)*0.1,(H87/1.18-H87/1.18/100*5.4-H87/100*0.8)*0.1)) -> 26076.612 | BI87: Реаб. | BJ87: 44925 | BK87: Принят | BL87: Сакорггаз | BM87: 44676 | BN87: BCP-220425-1/2(1.1.13)
A88: 1506 | B88: Кахети | C88: Гурджаани | D88: В г. Гурджаани район Ибра замена газопровода до с. Веджини | E88: Интерсервис 2011 | F88: 300457 | H88: 300386 | J88: =45821.59+200000+54564.41 -> 300386 | K88: =F88-J88 -> 71 | L88: =H88-J88 -> 0 | M88: =3574+57 -> 3631 | N88: =IF(OR(BK88="принят",BK88="Завершено",BK88="ПриПро"),H88-J88,F88-J88) -> 0 | O88: 0 | Q88: Поручение | R88: =T88+V88+X88+Z88+AB88+AD88+AF88+AH88+AJ88+AL88+AN88+AP88 -> 0 | S88: =U88+W88+Y88+AA88+AC88+AE88+AG88+AI88+AK88+AM88+AO88+AQ88 -> 0 | AS88: 0 | AT88: 0 | AU88: =IF(H88<50000,0,IF(AT88>0,(H88/1.18-AT88-H88/100*0.8)*0.1,(H88/1.18-H88/1.18/100*5.4-H88/100*0.8)*0.1)) -> 23841.484 | BE88: 0 | BI88: Реаб. | BJ88: 44620 | BK88: Принят | BL88: SGG | BM88: 44495 | BN88: BS-211026-1/0 | BO88: 1475 | BQ88: Yes
A89: 1578 | B89: Квемо Картли | C89: Болниси | D89: 1.1.1. В муниципалитетах Болниси и Тетрицкаро замена и вынос счетчиков (этап I). (P.2.156 (1)) (проектирование и строительство) | E89: Интерсервис 2011 | F89: 430000 | G89: 2 | K89: =F89-J89 -> 430000 | L89: =H89-J89 -> 0 | N89: =IF(OR(BK89="принят",BK89="Завершено",BK89="ПриПро"),H89-J89,F89-J89) -> 430000 | O89: 1 | Q89: P.2.156 (1) | R89: =T89+V89+X89+Z89+AB89+AD89+AF89+AH89+AJ89+AL89+AN89+AP89 -> 0 | S89: =U89+W89+Y89+AA89+AC89+AE89+AG89+AI89+AK89+AM89+AO89+AQ89 -> 0 | AS89: 0 | AT89: 0 | AU89: 0 | BI89: Реаб. | BK89: 0 | BL89: Сакорггаз | BM89: 44677 | BN89: BCP-220426-1/2(1.1.1)
A90: 1579 | B90: Квемо Картли | C90: Болниси | D90: 1.1.2. В муниципалитете Болниси в посёлке Казрети с корпусов, вынос счётчиков. (P.2.401) (проектирование и строительство) | E90: Интерсервис 2011 | F90: 670000 | G90: 2 | K90: =F90-J90 -> 670000 | L90: =H90-J90 -> 0 | N90: =IF(OR(BK90="принят",BK90="Завершено",BK90="ПриПро"),H90-J90,F90-J90) -> 670000 | O90: 0 | Q90: P.2.401 | R90: =T90+V90+X90+Z90+AB90+AD90+AF90+AH90+AJ90+AL90+AN90+AP90 -> 0 | S90: =U90+W90+Y90+AA90+AC90+AE90+AG90+AI90+AK90+AM90+AO90+AQ90 -> 0 | AS90: 0 | AT90: 0 | AU90: 0 | BI90: Реаб. | BK90: 0 | BL90: Сакорггаз | BM90: 44677 | BN90: BCP-220426-1/2(1.1.2) | BP90: ინტერსერვისმა შეასრულა 45 კორპუსის მხოლოდ პროექტირება, მშენებლობა გაუფორმდა ბრიჯს.
A91: 1580 | B91: Квемо Картли | C91: Болниси | D91: 1.1.3. В муниципалитете Болниси посёлок Казрети реабилитация газопровода на 350 абонентов. (P.2.141) | E91: Интерсервис 2011 | F91: 130000 | G91: 2 | H91: =120000+18000+15000+4283+2000+R91 -> 159900.56 | J91: =18305.08+2745.76+2288.14+653.3389+AS91+305.084+S91+AV91+AY91+BC91 -> 159900.56 | K91: =F91-J91 -> -29900.56 | L91: =H91-J91 -> 0 | M91: 2009.8 | N91: =IF(OR(BK91="принят",BK91="Завершено",BK91="ПриПро"),H91-J91,F91-J91) -> 0 | O91: 1 | Q91: P.2.141 | R91: =T91+V91+X91+Z91+AB91+AD91+AF91+AH91+AJ91+AL91+AN91+AP91 -> 617.56 | S91: =U91+W91+Y91+AA91+AC91+AE91+AG91+AI91+AK91+AM91+AO91+AQ91 -> 617.4771 | AD91: 617.56 | AG91: =94.2 -> 94.2 | AK91: 523.2771 | AS91: =116949.16+12711.86 -> 129661.02 | AT91: =4513.58+677.04+491.06 -> 5681.68 | AU91: 0 | AV91: =3629.66 -> 3629.66 | AY91: 1695 | AZ91: 75.68 | BC91: 0 | BD91: 0 | BI91: Реаб. | BJ91: 45827 | BK91: Принят | BL91: Сакорггаз | BM91: 44677 | BN91: BCP-220426-1/2(1.1.3) | BQ91: Yes
A92: 1581 | B92: Квемо Картли | C92: Болниси | D92: 1.1.4. В г. Болниси реабилитация газопровода на улице Сулхан Саба. (P.2.140) | E92: Интерсервис 2011 | F92: 40000 | G92: 2 | H92: =60000+8210 -> 68210 | I92: =60000+8210 -> 68210 | J92: =9152.54+AS92+AV92+1252.37+6957.63 -> 68210 | K92: =F92-J92 -> -28210 | L92: =H92-J92 -> 0 | M92: 308 | N92: =IF(OR(BK92="принят",BK92="Завершено",BK92="ПриПро"),H92-J92,F92-J92) -> 0 | O92: 0 | Q92: P.2.140 | R92: =T92+V92+X92+Z92+AB92+AD92+AF92+AH92+AJ92+AL92+AN92+AP92 -> 0 | S92: =U92+W92+Y92+AA92+AC92+AE92+AG92+AI92+AK92+AM92+AO92+AQ92 -> 0 | AS92: 0 | AT92: 0 | AU92: 0 | AV92: 50847.46 | AW92: 2545.16 | BA92: =IF(BK92="Принят",(H92/1.18-AW92)*0.1,H92/1.18*0.8*0.1) -> 5525.9925 | BB92: =(H92/1.18-AT92-AW92-AZ92)*0.1-AU92-AX92-BA92 -> 0 | BE92: =(H92/1.18-AT92-AW92-AZ92-BD92)*0.1-AU92-AX92-BA92-BB92 -> 0 | BI92: Реаб. | BJ92: 45321 | BK92: Принят | BL92: Сакорггаз | BM92: 44677 | BN92: BCP-220426-1/2(1.1.4) | BP92: გადასატანია 2023-ში ეს სუხან-საბას ქუჩა უკვე გაკეთებულია, მაგრამ ამავე პროექტშია თამარ მეფის ქუჩაც, რომელიც იყო P.2.138 მაგრამ ეს P სემეკს უკვე რატომღაც აღარ უზის და გასარკვევია რატომ. | BQ92: Yes
A93: 1582 | B93: Квемо Картли | C93: Болниси | D93: 1.1.5. В г. Болниси реабилитация газопровода на улице Тамар Мепе. (P.2.138) | E93: Интерсервис 2011 | F93: 30000 | G93: 2 | K93: =F93-J93 -> 30000 | L93: =H93-J93 -> 0 | N93: =IF(OR(BK93="принят",BK93="Завершено",BK93="ПриПро"),H93-J93,F93-J93) -> 30000 | O93: X | Q93: P.2.138 | R93: =T93+V93+X93+Z93+AB93+AD93+AF93+AH93+AJ93+AL93+AN93+AP93 -> 0 | S93: =U93+W93+Y93+AA93+AC93+AE93+AG93+AI93+AK93+AM93+AO93+AQ93 -> 0 | AS93: 0 | AT93: 0 | AU93: 0 | BI93: Реаб. | BK93: 0 | BL93: Сакорггаз | BM93: 44677 | BN93: BCP-220426-1/2(1.1.5) | BP93: გადასატანია 2023-ში კეთდება P.2.140-თან ერთად, მაგრამ ეს P.2.138 სემეკს უკვე რატომღაც აღარ უზის და გასარკვევია რატომ.
A94: 1583 | B94: Квемо Картли | C94: Болниси | D94: 1.1.6. В муниципалитете Болниси, в с. Нахидури установка стояков. (P.2.139) | E94: Интерсервис 2011 | F94: 29000 | G94: 2 | K94: =F94-J94 -> 29000 | L94: =H94-J94 -> 0 | N94: =IF(OR(BK94="принят",BK94="Завершено",BK94="ПриПро"),H94-J94,F94-J94) -> 29000 | O94: X | Q94: P.2.139 | R94: =T94+V94+X94+Z94+AB94+AD94+AF94+AH94+AJ94+AL94+AN94+AP94 -> 0 | S94: =U94+W94+Y94+AA94+AC94+AE94+AG94+AI94+AK94+AM94+AO94+AQ94 -> 0 | AS94: 0 | AT94: 0 | AU94: 0 | BI94: Реаб. | BK94: 0 | BL94: Сакорггаз | BM94: 44677 | BN94: BCP-220426-1/2(1.1.6) | BP94: საერთოდ არ არის გასაკეთებელი, ვერ გაკეთდება, გასაუქმებელია!
A95: 1609 | B95: Имерети | C95: Чиатура | D95: 1.1.5. Работы по реабилитации газопровода в г. Чиатура на улице Иашвили проведение. (P.6.53) | E95: Газсервис | F95: 100000 | H95: =85000+120000+48393.342867701 -> 253393.34 | J95: =12966.1+18305.08+7382.035+AS95+41011.1278677009 -> 253393.34 | K95: =F95-J95 -> -153393.34 | L95: =H95-J95 -> 0 | M95: 1007 | N95: =IF(OR(BK95="принят",BK95="Завершено",BK95="ПриПро"),H95-J95,F95-J95) -> 8.7311491e-11 | O95: 0 | Q95: P.6.53 | R95: =T95+V95+X95+Z95+AB95+AD95+AF95+AH95+AJ95+AL95+AN95+AP95 -> 0 | S95: =U95+W95+Y95+AA95+AC95+AE95+AG95+AI95+AK95+AM95+AO95+AQ95 -> 0 | AS95: =101695+72034 -> 173729 | AT95: 14059.27 | AU95: =IF(H95<50000,0,IF(AT95>0,(H95/1.18-AT95-H95/100*0.8)*0.1,(H95/1.18-H95/1.18/100*5.4-H95/100*0.8)*0.1)) -> 19865.37 | BI95: Реаб. | BJ95: 44925 | BK95: Принят | BL95: SGG | BM95: 44683 | BN95: BSP-220502-2/3(1.1.5)
A96: 1585 | B96: Квемо Картли | C96: Рустави | D96: 1.1.8. В г. Рустави работы по замене счетчиков и ящиков для счётчиков (этап I) (P.2.157 (1)) | E96: Интерсервис 2011 | F96: 1400000 | G96: ამოსაღებია, ეს პროექტი ფაქტობრივად გაკეთდა (P.2.72 (1 и 2)-თან ერთად. | K96: =F96-J96 -> 1400000 | L96: =H96-J96 -> 0 | N96: =IF(OR(BK96="принят",BK96="Завершено",BK96="ПриПро"),H96-J96,F96-J96) -> 1400000 | O96: X | Q96: P.2.157 (1) | R96: =T96+V96+X96+Z96+AB96+AD96+AF96+AH96+AJ96+AL96+AN96+AP96 -> 0 | S96: =U96+W96+Y96+AA96+AC96+AE96+AG96+AI96+AK96+AM96+AO96+AQ96 -> 0 | AS96: 0 | AT96: 0 | AU96: 0 | BI96: Реаб. | BK96: 0 | BL96: Сакорггаз | BM96: 44677 | BN96: BCP-220426-1/2(1.1.8) | BP96: ეს პროექტი ფაქტობრივად გაკეთდა (P.2.72 (1 и 2)-თან ერთად. ამიტომ არსად გადასატანი არ არის.
A97: 1586 | B97: Квемо Картли | C97: Рустави | D97: 1.1.9. В г. Рустави работы по переводу сетей в VII (а) микрорайоне на среднее давление. (P.2.402) (новый номер P.2.765) (проектирование и строительство) | E97: Интерсервис 2011 | F97: 78000 | G97: 2 | K97: =F97-J97 -> 78000 | L97: =H97-J97 -> 0 | N97: =IF(OR(BK97="принят",BK97="Завершено",BK97="ПриПро"),H97-J97,F97-J97) -> 78000 | O97: 1 | Q97: P.2.402 (новый номер P.2.765) | R97: =T97+V97+X97+Z97+AB97+AD97+AF97+AH97+AJ97+AL97+AN97+AP97 -> 0 | S97: =U97+W97+Y97+AA97+AC97+AE97+AG97+AI97+AK97+AM97+AO97+AQ97 -> 0 | AS97: 0 | AT97: 0 | AU97: 0 | BI97: Реаб. | BK97: 0 | BL97: Сакорггаз | BM97: 44677 | BN97: BCP-220426-1/2(1.1.9) | BP97: გადასატანია 2023-ში!
A98: 1587 | B98: Квемо Картли | C98: Рустави | D98: 1.1.10. В г. Рустави работы по переводу сетей в XVII Микро районе на среднее давление. (P.2.404) (новый номер P.2.767) (проектирование и строительство) | E98: Интерсервис 2011 | F98: 65000 | G98: 2 | H98: =308*1.75+20000+5000 -> 25539 | I98: =H98-539 -> 25000 | J98: =539+3050.847+762.71+S98+AY98+BC98 -> 25538.707 | K98: =F98-J98 -> 39461.293 | L98: =H98-J98 -> 0.293 | N98: =IF(OR(BK98="принят",BK98="Завершено",BK98="ПриПро"),H98-J98,F98-J98) -> 39461.293 | O98: 1 | Q98: P.2.404 (новый номер P.2.767) | R98: =T98+V98+X98+Z98+AB98+AD98+AF98+AH98+AJ98+AL98+AN98+AP98 -> 0 | S98: =U98+W98+Y98+AA98+AC98+AE98+AG98+AI98+AK98+AM98+AO98+AQ98 -> 0 | AS98: 0 | AT98: 0 | AU98: 0 | AY98: =16949.15+4237 -> 21186.15 | BI98: Реаб. | BK98: 30 | BL98: Сакорггаз | BM98: 44677 | BN98: BCP-220426-1/2(1.1.10)
A99: 1588 | B99: Квемо Картли | C99: Рустави | D99: 1.1.11. В г. Рустави работы по переводу сетей в VII Микро районе на среднее давление. (P.2.405) (новый номер P.2.768) (проектирование и строительство) | E99: Интерсервис 2011 | F99: 65000 | G99: 2 | K99: =F99-J99 -> 65000 | L99: =H99-J99 -> 0 | N99: =IF(OR(BK99="принят",BK99="Завершено",BK99="ПриПро"),H99-J99,F99-J99) -> 65000 | O99: 1 | Q99: P.2.405 (новый номер P.2.768) | R99: =T99+V99+X99+Z99+AB99+AD99+AF99+AH99+AJ99+AL99+AN99+AP99 -> 0 | S99: =U99+W99+Y99+AA99+AC99+AE99+AG99+AI99+AK99+AM99+AO99+AQ99 -> 0 | AS99: 0 | AT99: 0 | AU99: 0 | BI99: Реаб. | BK99: 0 | BL99: Сакорггаз | BM99: 44677 | BN99: BCP-220426-1/2(1.1.11) | BP99: გადასატანია 2023-ში!
A100: 1589 | B100: Квемо Картли | C100: Рустави | D100: 1.1.12. В г. Рустави работы по переводу сетей в IXХ Микро районе на среднее давление. (P.2.408) (новый номер P.2.769) (проектирование и строительство) | E100: Интерсервис 2011 | F100: 33000 | G100: 2 | K100: =F100-J100 -> 33000 | L100: =H100-J100 -> 0 | N100: =IF(OR(BK100="принят",BK100="Завершено",BK100="ПриПро"),H100-J100,F100-J100) -> 33000 | O100: 1 | Q100: P.2.408 (новый номер P.2.769) | R100: =T100+V100+X100+Z100+AB100+AD100+AF100+AH100+AJ100+AL100+AN100+AP100 -> 0 | S100: =U100+W100+Y100+AA100+AC100+AE100+AG100+AI100+AK100+AM100+AO100+AQ100 -> 0 | AS100: 0 | AT100: 0 | AU100: 0 | BI100: Реаб. | BK100: 0 | BL100: Сакорггаз | BM100: 44677 | BN100: BCP-220426-1/2(1.1.12) | BP100: გადასატანია 2023-ში!
A101: 1590 | B101: Квемо Картли | C101: Дманиси | D101: Село Мтисдзири, строиетльство газораспределительной сети (газификация). (P.2.407) | E101: Бриджи | F101: 104630 | H101: 104630.23 | J101: =15960.543559322+88669.686440678+S101 -> 104630.23 | K101: -0.23 | L101: =H101-J101 -> 0 | M101: =3325-163 -> 3162 | N101: =IF(OR(BK101="принят",BK101="Завершено",BK101="ПриПро"),H101-J101,F101-J101) -> 0 | O101: 0 | P101: 55 | Q101: P.2.407 | R101: =T101+V101+X101+Z101+AB101+AD101+AF101+AH101+AJ101+AL101+AN101+AP101 -> 0 | S101: =U101+W101+Y101+AA101+AC101+AE101+AG101+AI101+AK101+AM101+AO101+AQ101 -> 0 | AS101: 0 | AT101: 0 | AU101: 0 | BI101: Н. Стр. | BJ101: 44740 | BK101: Принят | BL101: SGG | BM101: 44694 | BN101: BS-220513-1/0
...

Sheet კორპუსები
A1: СОКАР ДЖОРДЖИЯ ГАЗ строительство-реабилитация | F1: 73429.4 | H1: =F1-I210 -> 0 | I1: 1.75 | J1: ="მშენებლობა რეაბილიტაციისა და კორპუსების ჯამი"&TEXT(ДВД!#REF!+კორპუსები!I4," ### ###") -> #REF! | AA1: =AA7+AA3 -> 17560.569 | AB1: საქორი | AI1: Квемо Картли | AJ1: Рустави | AK1: (1) გამოსატანი მრიცხველების გამოტანა (P.2.647) (დავით გარეჯის ქ. №18 კორპ) | AL1: დავით გარეჯის ქ. №18 კორპ
B3: Договорн. стоймость обьектов: | D3: =SUBTOTAL(9,H11:H961) -> 0 | N3: =SUBTOTAL(9,N11:N961) -> 0 | AA3: 17560.569
B4: Сданы по фактуре: | D4: =SUBTOTAL(9,I11:I961) -> 305400 | F4: =ROUND(D4/D3*100,2)&"% от дог. стойм." -> #DIV/0! | H4: Дл. газопр. | I4: =SUBTOTAL(9,N11:N961) -> 0 | J4: =I17+I18+I19+I20+I21+I32 -> 142980.92 | L4: Цена | M4: 1 пог.м. | N4: 1 абон.
B5: Всего оплачено: | D5: =SUBTOTAL(9,K11:K961) -> 46418.636 | F5: =ROUND(D5/D3*100,2)&"% от дог. стойм." -> #DIV/0! | H5: Кол-во. абон. | I5: =SUBTOTAL(9,Q11:Q961) -> 0 | J5: =J4-J7 -> 142980.92 | L5: Мах. | M5: =SUBTOTAL(4,AF11:AF961) -> 0 | N5: =SUBTOTAL(4,AG11:AG961) -> 0 | O5: =N6/1.18 -> #DIV/0!
B6: Осталось по договор.: | D6: =SUBTOTAL(9,L11:L961) -> -46418.636 | F6: =ROUND(D6/D3*100,2)&"% от дог. стойм." -> #DIV/0! | H6: Реальн. абон. | I6: =SUBTOTAL(9,R11:R961) -> 0 | L6: Ср. | M6: =D4/I4 -> #DIV/0! | N6: =D4/I6 -> #DIV/0! | O6: =M6/1.18 -> #DIV/0! | S6: =S7+V7 -> 0 | T6: =T7+W7 -> 0
A7: =SUBTOTAL(3,A11:A961) -> 9 | B7: Осталось по сданным: | D7: =SUBTOTAL(9,M11:M961) -> 258981.36 | F7: =ROUND(D7/D4*100,2)&"% от сд. стойм." -> 84.8% от сд. стойм. | H7: "Признано" аб. | I7: =SUBTOTAL(9,AD11:AD961) -> 0 | J7: =SUBTOTAL(9,J11:J961) -> 0 | K7: =SUBTOTAL(9,K11:K961) -> 46418.636 | L7: Мин. | M7: =SUBTOTAL(5,AF11:AF961) -> 0 | N7: =SUBTOTAL(5,AG11:AG961) -> 0 | O7: =SUBTOTAL(9,O11:O961) -> -46418.636 | Q7: =SUBTOTAL(9,Q11:Q961) -> 0 | R7: =SUBTOTAL(9,R11:R961) -> 0 | S7: =SUBTOTAL(9,S11:S961) -> 0 | T7: =SUBTOTAL(9,T11:T961) -> 0 | U7: =SUBTOTAL(9,U11:U961) -> 0 | V7: =SUBTOTAL(9,V11:V961) -> 0 | W7: =SUBTOTAL(9,W11:W961) -> 0 | X7: =SUBTOTAL(9,X11:X961) -> 0 | ... AD7: =SUBTOTAL(9,AD11:AD961) -> 0 | AI7: =SUBTOTAL(3,AI11:AI961) -> 0 | AJ7: =SUBTOTAL(3,AJ11:AJ961) -> 9 | AK7: =SUBTOTAL(3,AK11:AK961) -> 9 | AN7: =SUBTOTAL(3,AN11:AN961) -> 0 | AP7: =SUBTOTAL(3,AP11:AP961) -> 9 | AQ7: =SUBTOTAL(3,AQ11:AQ961) -> 0
A9: № пп | B9: Регион | C9: Район/ Город | D9: Обьект | E9: კორპუსის დასახელება | F9: Подрядная организация | H9: Договорная стоймость обьекта | I9: Работы сданы по фактуре (A) | J9: ღირებულება პროექტის გარეშე | K9: Оплачено | L9: Осталось от договорн. стоймости | M9: Осталось от сданных работ | N9: Дл. (м) строящ. газопр. | O9: Возможный долг (Д) | P9: 1 | Q9: Кол. нов. абон. | R9: Кол-во реальн. Абон. | S9: ფაქტორ. თანხა 2022 | T9: ფაქტორ. ხარჯი 2022 | U9: სხვაობა 2022 | V9: ფაქტორ. თანხა 2023 | W9: ფაქტორ. ხარჯი 2023 | X9: სხვაობა 2023 | Y9: ფაქტორ. თანხა 2024 | Z9: ფაქტორ. ხარჯი 2024 | AA9: სხვაობა 2024 (1) | AB9: სხვაობა 2024 (2) | AC9: ნაწილი მიღებულია ექსპლუატაციაში 2022 წელს | AD9: "Признано" КАПТО | AE9: для КАПТО | AF9: Расход на 1 п/м | AG9: Расход на 1-го абонента | AH9: Тип пр. | AI9: Дата приема | AJ9: Статус/прием в эксплуатацию | AK9: Примеч. Или Компания | AL9: Дата закл. договора | AM9: № Догов. | AN9: № Эксп. Сметы | AO9: План/ Год | AP9: № по бюджету | AQ9: Регистрация/ კომენტარი
A11: 2040 | B11: Квемо Картли | C11: Рустави | D11: (6) გამოტანილი მრიცხველების პოლიეთილენის მილების შეცვლა რკინის მილებით (P.2.619) (მე-16-ე მკრ. 2 კორპ) | E11: მე-16-ე მკრ. 2 კორპ | F11: Интерсервис 2011 | G11: 619 | H11: =1130.5+50000+9134 -> 60264.5 | I11: =1130.5+50000+9134 -> 60264.5 | J11: =1130.5+50000-1130.5+9134 -> 59134 | K11: =172.45+958.05+7627.12+S11+V11+1393.32+7740.68 -> 60264.5 | L11: =H11-K11 -> 0 | M11: =I11-K11 -> 0 | N11: 675 | O11: =IF(OR(AJ11="принят",AJ11="Завершено",AJ11="ПриПро"),I11-K11,H11-K11) -> 0 | P11: 0 | S11: 0 | T11: 0 | U11: 0 | V11: 42372.88 | W11: 2120.97 | AA11: =IF(AJ11="Принят",(J11/1.18-W11-Z11)*0.1,J11/1.18*0.8*0.1) -> 4799.2589 | AB11: =IF(AJ11="Принят",(J11/1.18-W11-Z11)*0.1,J11/1.18*0.8*0.1)-AA11 -> 0 | AF11: =IF(OR(I11="",I11=0,N11="",N11=0),"Нет инфо",I11/N11) -> 89.280741 | AG11: =IF(OR(I11="",I11=0,R11="",R11=0),"Нет инфо",I11/R11) -> Нет инфо | AH11: Реаб. | AI11: 45321 | AJ11: Принят | AK11: Сакорггаз | AL11: 44935 | AM11: BCG-230109-1/0(6) | AO11: P.2.619 | AP11: P.2.619
A12: 2041 | B12: Квемо Картли | C12: Рустави | D12: (6) გამოტანილი მრიცხველების პოლიეთილენის მილების შეცვლა რკინის მილებით (P.2.619) (მე-16-ე მკრ. 3 კორპ) | E12: მე-16-ე მკრ. 3 კორპ | F12: Интерсервис 2011 | G12: 619 | H12: =1291.5+50000+12068 -> 63359.5 | I12: =1291.5+50000+12068 -> 63359.5 | J12: =1291.5+50000-1291.5+12068 -> 62068 | K12: =197.01+1094.49+7627.12+S12+V12+1840.88+10227.12 -> 63359.5 | L12: =H12-K12 -> 0 | M12: =I12-K12 -> 0 | N12: 789 | O12: =IF(OR(AJ12="принят",AJ12="Завершено",AJ12="ПриПро"),I12-K12,H12-K12) -> 0 | P12: 0 | S12: 0 | T12: 0 | U12: 0 | V12: 42372.88 | W12: 2120.97 | AA12: =IF(AJ12="Принят",(J12/1.18-W12-Z12)*0.1,J12/1.18*0.8*0.1) -> 5047.903 | AB12: =IF(AJ12="Принят",(J12/1.18-W12-Z12)*0.1,J12/1.18*0.8*0.1)-AA12 -> 0 | AF12: =IF(OR(I12="",I12=0,N12="",N12=0),"Нет инфо",I12/N12) -> 80.303549 | AG12: =IF(OR(I12="",I12=0,R12="",R12=0),"Нет инфо",I12/R12) -> Нет инфо | AH12: Реаб. | AI12: 45321 | AJ12: Принят | AK12: Сакорггаз | AL12: 44935 | AM12: BCG-230109-1/0(6) | AO12: P.2.619 | AP12: P.2.619
A13: 2042 | B13: Квемо Картли | C13: Рустави | D13: (6) გამოტანილი მრიცხველების პოლიეთილენის მილების შეცვლა რკინის მილებით (P.2.619) (მე-16-ე მკრ. 10 კორპ) | E13: მე-16-ე მკრ. 10 კორპ | F13: Интерсервис 2011 | G13: 619 | H13: =1195.25+50000+9970 -> 61165.25 | I13: =1195.25+50000+9970 -> 61165.25 | J13: =1195.25+50000-1195.25+9970 -> 59970 | K13: =182.33+1012.92+S13+V13+7627.12+1520.85+8449.15 -> 61165.25 | L13: =H13-K13 -> 0 | M13: =I13-K13 -> 0 | N13: 719 | O13: =IF(OR(AJ13="принят",AJ13="Завершено",AJ13="ПриПро"),I13-K13,H13-K13) -> 0 | P13: 0 | S13: 0 | T13: 0 | U13: 0 | V13: 42372.88 | W13: 2120.97 | AA13: =IF(AJ13="Принят",(J13/1.18-W13-Z13)*0.1,J13/1.18*0.8*0.1) -> 4870.1064 | AB13: =IF(AJ13="Принят",(J13/1.18-W13-Z13)*0.1,J13/1.18*0.8*0.1)-AA13 -> 0 | AF13: =IF(OR(I13="",I13=0,N13="",N13=0),"Нет инфо",I13/N13) -> 85.069889 | AG13: =IF(OR(I13="",I13=0,R13="",R13=0),"Нет инфо",I13/R13) -> Нет инфо | AH13: Реаб. | AI13: 45321 | AJ13: Принят | AK13: Сакорггаз | AL13: 44935 | AM13: BCG-230109-1/0(6) | AO13: P.2.619 | AP13: P.2.619
A14: 2043 | B14: Квемо Картли | C14: Рустави | D14: (4) გამოსატანი მრიცხველების გამოტანა P.2.577 (მესხიშვ. I გასასვლ. №7) | E14: მესხიშვ. I გასასვლ. №7 | F14: Интерсервис 2011 | G14: 577 | H14: =2264.5+80000+5000+8049 -> 95313.5 | I14: =2264.5+80000+5000+8049 -> 95313.5 | J14: =80000+5000-2264.5+8049 -> 90784.5 | K14: =S14+V14+12203.39+345.43+762.71+1227.81+8740.26 -> 95313.5 | L14: =H14-K14 -> 0 | M14: =I14-K14 -> 0 | N14: 908 | O14: =IF(OR(AJ14="принят",AJ14="Завершено",AJ14="ПриПро"),I14-K14,H14-K14) -> 1.4551915e-11 | P14: 0 | S14: 0 | T14: 0 | U14: 0 | V14: =67796.61+4237.29 -> 72033.9 | W14: =4318.55+212.1 -> 4530.65 | AA14: =IF(AJ14="Принят",(J14/1.18-W14-Z14)*0.1,J14/1.18*0.8*0.1) -> 7240.5367 | AB14: =IF(AJ14="Принят",(J14/1.18-W14-Z14)*0.1,J14/1.18*0.8*0.1)-AA14 -> 0 | AF14: =IF(OR(I14="",I14=0,N14="",N14=0),"Нет инфо",I14/N14) -> 104.97081 | AG14: =IF(OR(I14="",I14=0,R14="",R14=0),"Нет инфо",I14/R14) -> Нет инфо | AH14: Реаб. | AI14: 45321 | AJ14: Принят | AK14: Сакорггаз | AL14: 44935 | AM14: BCG-230109-1/0(4) | AO14: P.2.577 | AP14: P.2.577
A15: 2044 | B15: Квемо Картли | C15: Рустави | D15: (4) გამოსატანი მრიცხველების გამოტანა P.2.577 (მესხიშვ. I გასასვლ. №9) | E15: მესხიშვ. I გასასვლ. №9 | F15: Интерсервис 2011 | G15: 577 | H15: =1737.75+80000+28338 -> 110075.75 | I15: =1737.75+80000+28338 -> 110075.75 | J15: =1737.75-1737.75+80000+28338 -> 108338 | K15: =S15+V15+12203.39+265.08+4322.75+25487.92 -> 110075.75 | L15: =H15-K15 -> 0 | M15: =I15-K15 -> 0 | N15: 1253 | O15: =IF(OR(AJ15="принят",AJ15="Завершено",AJ15="ПриПро"),I15-K15,H15-K15) -> 0 | P15: 0 | S15: 0 | T15: 0 | U15: 0 | V15: 67796.61 | W15: 4318.55 | AA15: =IF(AJ15="Принят",(J15/1.18-W15-Z15)*0.1,J15/1.18*0.8*0.1) -> 8749.3314 | AB15: =IF(AJ15="Принят",(J15/1.18-W15-Z15)*0.1,J15/1.18*0.8*0.1)-AA15 -> 0 | AF15: =IF(OR(I15="",I15=0,N15="",N15=0),"Нет инфо",I15/N15) -> 87.849761 | AG15: =IF(OR(I15="",I15=0,R15="",R15=0),"Нет инфо",I15/R15) -> Нет инфо | AH15: Реаб. | AI15: 45321 | AJ15: Принят | AK15: Сакорггаз | AL15: 44935 | AM15: BCG-230109-1/0(4) | AO15: P.2.577 | AP15: P.2.577
A16: 2045 | B16: Квемо Картли | C16: Рустави | D16: (2) გამოტანილი მრიცხველების პოლიეთილენის მილების შეცვლა რკინის მილებით P.2.744 (რუსთაველის ქ. №28 კორპ) | E16: რუსთაველის ქ. №28 კორპ | F16: Интерсервис 2011 | G16: 744 | H16: =1610+50000+743 -> 52353 | I16: =1610+50000+743 -> 52353 | J16: =1610-1610+50000+743 -> 50743 | K16: =S16+V16+245.59+7627.12+743+1364.41 -> 52353 | L16: =H16-K16 -> 0 | M16: =I16-K16 -> 0 | N16: 702 | O16: =IF(OR(AJ16="принят",AJ16="Завершено",AJ16="ПриПро"),I16-K16,H16-K16) -> 0 | P16: 0 | S16: 0 | T16: 0 | U16: 0 | V16: 42372.88 | W16: 2120.97 | AA16: =IF(AJ16="Принят",(J16/1.18-W16-Z16)*0.1,J16/1.18*0.8*0.1) -> 4088.1572 | AB16: =IF(AJ16="Принят",(J16/1.18-W16-Z16)*0.1,J16/1.18*0.8*0.1)-AA16 -> 0 | AF16: 86.462889 | AG16: Нет инфо | AH16: Реаб. | AI16: 45321 | AJ16: Принят | AK16: Сакорггаз | AL16: 44935 | AM16: BCG-230109-1/0(2) | AO16: P.2.744 | AP16: P.2.744
A17: 2046 | B17: Самцхе Джавахети | C17: Борджоми | D17: 1.1.24. В г. Боржоми реабилитация/реконструкция наружных сетей в корпусах на улицах Руставели и Месхети. (P.3.106) (проектирование и строительство) (რუსთაველის ქ. №85) | E17: რუსთაველის ქ. №85 | F17: Газ Констракт | H17: =1055.25+26491.26 -> 27546.51 | I17: =1055.25+26491.26 -> 27546.51 | J17: =I17-1055.25 -> 26491.26 | K17: =160.97+4041.039+23344.5 -> 27546.509 | L17: =H17-K17 -> 0.001 | M17: =I17-K17 -> 0.001 | N17: 569.6 | O17: =IF(OR(AJ17="принят",AJ17="Завершено",AJ17="ПриПро"),I17-K17,H17-K17) -> 0.001 | P17: 0 | S17: 0 | T17: 0 | U17: 0 | V17: 0 | W17: 0 | AA17: =J17/1.18*0.1 -> 2245.022 | AB17: =IF(AJ17="Принят",(J17/1.18-W17-Z17)*0.1,J17/1.18*0.8*0.1)-AA17 -> 0 | AF17: =IF(OR(I17="",I17=0,N17="",N17=0),"Нет инфо",I17/N17) -> 48.361148 | AG17: =IF(OR(I17="",I17=0,R17="",R17=0),"Нет инфо",I17/R17) -> Нет инфо | AH17: Реаб. | AI17: 45322 | AJ17: Принят | AK17: Сакорггаз | AL17: 44676 | AM17: BCP-220425-1/2(1.1.24) | AO17: P.3.106 | AP17: P.3.106
A18: 2047 | B18: Самцхе Джавахети | C18: Борджоми | D18: 1.1.24. В г. Боржоми реабилитация/реконструкция наружных сетей в корпусах на улицах Руставели и Месхети. (P.3.106) (проектирование и строительство) (რუსთაველის ქ. №89) | E18: რუსთაველის ქ. №89 | F18: Газ Констракт | H18: =666.75+20650.93 -> 21317.68 | I18: =666.75+20650.93 -> 21317.68 | J18: =I18-666.75 -> 20650.93 | K18: =101.71+3150.14+18065.83 -> 21317.68 | L18: =H18-K18 -> 0 | M18: =I18-K18 -> 0 | N18: 368.2 | O18: =IF(OR(AJ18="принят",AJ18="Завершено",AJ18="ПриПро"),I18-K18,H18-K18) -> 0 | P18: 0 | S18: 0 | T18: 0 | U18: 0 | V18: 0 | W18: 0 | AA18: =J18/1.18*0.1 -> 1750.0788 | AB18: =IF(AJ18="Принят",(J18/1.18-W18-Z18)*0.1,J18/1.18*0.8*0.1)-AA18 -> 0 | AF18: =IF(OR(I18="",I18=0,N18="",N18=0),"Нет инфо",I18/N18) -> 57.897012 | AG18: =IF(OR(I18="",I18=0,R18="",R18=0),"Нет инфо",I18/R18) -> Нет инфо | AH18: Реаб. | AI18: 45322 | AJ18: Принят | AK18: Сакорггаз | AL18: 44676 | AM18: BCP-220425-1/2(1.1.24) | AO18: P.3.106 | AP18: P.3.106
A19: 2048 | B19: Самцхе Джавахети | C19: Борджоми | D19: 1.1.24. В г. Боржоми реабилитация/реконструкция наружных сетей в корпусах на улицах Руставели и Месхети. (P.3.106) (проектирование и строительство) (რუსთაველის ქ. №91) | E19: რუსთაველის ქ. №91 | F19: Газ Констракт | H19: =1237.25+28404.56 -> 29641.81 | I19: =1237.25+28404.56 -> 29641.81 | J19: =I19-1237.25 -> 28404.56 | K19: =188.74+4332.898+25120.17 -> 29641.808 | L19: =H19-K19 -> 0.002 | M19: =I19-K19 -> 0.002 | N19: 706.5 | O19: =IF(OR(AJ19="принят",AJ19="Завершено",AJ19="ПриПро"),I19-K19,H19-K19) -> 0.002 | P19: 0 | S19: 0 | T19: 0 | U19: 0 | V19: 0 | W19: 0 | AA19: =J19/1.18*0.1 -> 2407.1661 | AB19: =IF(AJ19="Принят",(J19/1.18-W19-Z19)*0.1,J19/1.18*0.8*0.1)-AA19 -> 0 | AF19: =IF(OR(I19="",I19=0,N19="",N19=0),"Нет инфо",I19/N19) -> 41.955853 | AG19: =IF(OR(I19="",I19=0,R19="",R19=0),"Нет инфо",I19/R19) -> Нет инфо | AH19: Реаб. | AI19: 45322 | AJ19: Принят | AK19: Сакорггаз | AL19: 44676 | AM19: BCP-220425-1/2(1.1.24) | AO19: P.3.106 | AP19: P.3.106
A20: 2049 | B20: Самцхе Джавахети | C20: Борджоми | D20: 1.1.24. В г. Боржоми реабилитация/реконструкция наружных сетей в корпусах на улицах Руставели и Месхети. (P.3.106) (проектирование и строительство) (რუსთაველის ქ. №95) | E20: რუსთაველის ქ. №95 | F20: Газ Констракт | H20: =217+6357.74 -> 6574.74 | I20: =217+6357.74 -> 6574.74 | J20: =I20-217 -> 6357.74 | K20: =33.1+969.82+5571.82 -> 6574.74 | L20: =H20-K20 -> 0 | M20: =I20-K20 -> 0 | N20: 112.8 | O20: =IF(OR(AJ20="принят",AJ20="Завершено",AJ20="ПриПро"),I20-K20,H20-K20) -> 0 | P20: 0 | S20: 0 | T20: 0 | U20: 0 | V20: 0 | W20: 0 | AA20: =J20/1.18*0.1 -> 538.79153 | AB20: =IF(AJ20="Принят",(J20/1.18-W20-Z20)*0.1,J20/1.18*0.8*0.1)-AA20 -> 0 | AF20: =IF(OR(I20="",I20=0,N20="",N20=0),"Нет инфо",I20/N20) -> 58.286702 | AG20: =IF(OR(I20="",I20=0,R20="",R20=0),"Нет инфо",I20/R20) -> Нет инфо | AH20: Реаб. | AI20: 45322 | AJ20: Принят | AK20: Сакорггаз | AL20: 44676 | AM20: BCP-220425-1/2(1.1.24) | AO20: P.3.106 | AP20: P.3.106
A21: 2050 | B21: Самцхе Джавахети | C21: Борджоми | D21: 1.1.24. В г. Боржоми реабилитация/реконструкция наружных сетей в корпусах на улицах Руставели и Месхети. (P.3.106) (проектирование и строительство) (რუსთაველის ქ. №109) | E21: რუსთაველის ქ. №109 | F21: Газ Констракт | H21: =318.5+7711.34 -> 8029.84 | I21: =318.5+7711.34 -> 8029.84 | J21: =I21-318.5 -> 7711.34 | K21: =48.58+1176.306+6804.95 -> 8029.836 | L21: =H21-K21 -> 0.004 | M21: =I21-K21 -> 0.004 | N21: 182.2 | O21: =IF(OR(AJ21="принят",AJ21="Завершено",AJ21="ПриПро"),I21-K21,H21-K21) -> 0.004 | P21: 0 | S21: 0 | T21: 0 | U21: 0 | V21: 0 | W21: 0 | AA21: =J21/1.18*0.1 -> 653.50339 | AB21: =IF(AJ21="Принят",(J21/1.18-W21-Z21)*0.1,J21/1.18*0.8*0.1)-AA21 -> 0 | AF21: =IF(OR(I21="",I21=0,N21="",N21=0),"Нет инфо",I21/N21) -> 44.07157 | AG21: =IF(OR(I21="",I21=0,R21="",R21=0),"Нет инфо",I21/R21) -> Нет инфо | AH21: Реаб. | AI21: 45322 | AJ21: Принят | AK21: Сакорггаз | AL21: 44676 | AM21: BCP-220425-1/2(1.1.24) | AO21: P.3.106 | AP21: P.3.106
A22: 2051 | B22: Квемо Картли | C22: Рустави | D22: (4) გამოსატანი მრიცხველების გამოტანა P.2.577 (შარტავას ქ. №9 კორპუსი) | E22: შარტავას ქ. №9 კორპუსი | F22: Интерсервис 2011 | G22: 577 | H22: =2070.25+80000+36640 -> 118710.25 | I22: =2070.25+80000+36640 -> 118710.25 | J22: =I22-2070.25 -> 116640 | K22: =315.8+V22+12203.39+5589.15+32805.3 -> 118710.25 | L22: =H22-K22 -> 0 | M22: =I22-K22 -> 0 | N22: 1447 | O22: =IF(OR(AJ22="принят",AJ22="Завершено",AJ22="ПриПро"),I22-K22,H22-K22) -> 0 | P22: 0 | S22: 0 | T22: 0 | U22: 0 | V22: 67796.61 | W22: 3393.55 | AA22: =IF(AJ22="Принят",(J22/1.18-W22-Z22)*0.1,J22/1.18*0.8*0.1) -> 9545.3908 | AB22: =IF(AJ22="Принят",(J22/1.18-W22-Z22)*0.1,J22/1.18*0.8*0.1)-AA22 -> 0 | AF22: =IF(OR(I22="",I22=0,N22="",N22=0),"Нет инфо",I22/N22) -> 82.038874 | AG22: =IF(OR(I22="",I22=0,R22="",R22=0),"Нет инфо",I22/R22) -> Нет инфо | AH22: Реаб. | AI22: 45380 | AJ22: Принят | AK22: Сакорггаз | AL22: 44935 | AM22: BCG-230109-1/0(4) | AO22: P.2.577 | AP22: P.2.577
A23: 2052 | B23: Квемо Картли | C23: Рустави | D23: (10) გამოტანილი მრიცხველების პოლიეთილენის მილების შეცვლა რკინის მილებით P.2.721 (მე-7ა-ე მკრ. №3 კორპ) | E23: მე-7ა-ე მკრ. №3 კორპ | F23: Интерсервис 2011 | G23: 721 | H23: =1153.25+35000+1000+10260 -> 47413.25 | I23: =1153.25+35000+1000+10260 -> 47413.25 | J23: =I23-1153.25 -> 46260 | K23: =S23+V23+175.92+5338.98+152.54+1565.08+9672.25 -> 47413.25 | L23: =H23-K23 -> 0 | M23: =I23-K23 -> 0 | N23: 714 | O23: =IF(OR(AJ23="принят",AJ23="Завершено",AJ23="ПриПро"),I23-K23,H23-K23) -> 0 | P23: 0 | S23: 0 | T23: 0 | U23: 0 | V23: =29661.02+847.46 -> 30508.48 | W23: =1889.37+25.92 -> 1915.29 | AA23: =IF(AJ23="Принят",(J23/1.18-W23-Z23)*0.1,J23/1.18*0.8*0.1) -> 3728.81 | AB23: =IF(AJ23="Принят",(J23/1.18-W23-Z23)*0.1,J23/1.18*0.8*0.1)-AA23 -> 0 | AF23: =IF(OR(I23="",I23=0,N23="",N23=0),"Нет инфо",I23/N23) -> 66.405112 | AG23: =IF(OR(I23="",I23=0,R23="",R23=0),"Нет инфо",I23/R23) -> Нет инфо | AH23: Реаб. | AI23: 45380 | AJ23: Принят | AK23: Сакорггаз | AL23: 44935 | AM23: BCG-230109-1/0(10) | AO23: P.2.721 | AP23: P.2.721
A24: 2053 | B24: Квемо Картли | C24: Рустави | D24: (8) გამოტანილი მრიცხველების პოლიეთილენის მილების შეცვლა რკინის მილებით (P.2.701) (მეგობრობის ქ. №23 კორპუსი) | E24: მეგობრობის ქ. №23 კორპუსი | F24: Интерсервис 2011 | G24: 701 | H24: =483+50000+2000+5000+3635 -> 61118 | I24: =483+50000+2000+5000+3635 -> 61118 | J24: =I24-483 -> 60635 | K24: =483+V24+7627.12+Y24+305.08+762.71+3635 -> 61118 | L24: =H24-K24 -> 0 | M24: =I24-K24 -> 0 | N24: 523 | O24: =IF(OR(AJ24="принят",AJ24="Завершено",AJ24="ПриПро"),I24-K24,H24-K24) -> 0 | P24: 0 | S24: 0 | T24: 0 | U24: 0 | V24: 42372.88 | W24: 2120.97 | Y24: =1694.92+4237.29 -> 5932.21 | Z24: =51.85+79.12 -> 130.97 | AA24: =IF(AJ24="Принят",(J24/1.18-W24-Z24)*0.1,J24/1.18*0.8*0.1) -> 4913.3653 | AB24: =IF(AJ24="Принят",(J24/1.18-W24-Z24)*0.1,J24/1.18*0.8*0.1)-AA24 -> 0 | AF24: =IF(OR(I24="",I24=0,N24="",N24=0),"Нет инфо",I24/N24) -> 116.86042 | AG24: =IF(OR(I24="",I24=0,R24="",R24=0),"Нет инфо",I24/R24) -> Нет инфо | AH24: Реаб. | AI24: 45393 | AJ24: Принят | AK24: Сакорггаз | AL24: 44935 | AM24: BCG-230109-1/0(8) | AO24: P.2.701 | AP24: P.2.701
A25: 2054 | B25: Квемо Картли | C25: Рустави | D25: (6) გამოტანილი მრიცხველების პოლიეთილენის მილების შეცვლა რკინის მილებით (P.2.619) (შარტავას ქ. №11 კორპ) | E25: შარტავას ქ. №11 კორპ | F25: Интерсервис 2011 | G25: 619 | H25: =1440.25+55000+9360 -> 65800.25 | I25: =1440.25+55000+9360 -> 65800.25 | J25: =I25-1440.25 -> 64360 | K25: =1440.25+8389.83+Y25+1427.8+7932.2 -> 65800.25 | L25: =H25-K25 -> 0 | M25: =I25-K25 -> 0 | N25: 989 | O25: =IF(OR(AJ25="принят",AJ25="Завершено",AJ25="ПриПро"),I25-K25,H25-K25) -> 0 | P25: 0 | S25: 0 | T25: 0 | U25: 0 | Y25: 46610.17 | Z25: 1425.76 | AA25: =IF(AJ25="Принят",(J25/1.18-W25-Z25)*0.1,J25/1.18*0.8*0.1) -> 5311.6613 | AB25: =IF(AJ25="Принят",(J25/1.18-W25-Z25)*0.1,J25/1.18*0.8*0.1)-AA25 -> 0 | AF25: =IF(OR(I25="",I25=0,N25="",N25=0),"Нет инфо",I25/N25) -> 66.532103 | AG25: =IF(OR(I25="",I25=0,R25="",R25=0),"Нет инфо",I25/R25) -> Нет инфо | AH25: Реаб. | AI25: 45370 | AJ25: Принят | AK25: Сакорггаз | AL25: 44935 | AM25: BCG-230109-1/0(6) | AO25: P.2.619 | AP25: P.2.619
A26: 2055 | B26: Квемо Картли | C26: Рустави | D26: (4) გამოსატანი მრიცხველების გამოტანა P.2.577 (შარტავას ქ. №5 კორპუსი) | E26: შარტავას ქ. №5 კორპუსი | F26: Интерсервис 2011 | G26: 577 | H26: =2051+80000+2000 -> 84051 | I26: =2051+80000+2000+10000+13567 -> 107618 | J26: =I26-2051 -> 105567 | K26: =312.86+S26+12203.39+V26+Y26+305.08+1525.42+15305.14 -> 107618 | L26: =H26-K26 -> -23567 | M26: =I26-K26 -> 0 | N26: 1136 | O26: =IF(OR(AJ26="принят",AJ26="Завершено",AJ26="ПриПро"),I26-K26,H26-K26) -> 0 | P26: 0 | S26: 0 | T26: 0 | U26: 0 | V26: =67796.61 -> 67796.61 | W26: 3393.55 | Y26: =1694.92+8474.58 -> 10169.5 | Z26: =51.85+158.23 -> 210.08 | AA26: =IF(AJ26="Принят",(J26/1.18-W26-Z26)*0.1,J26/1.18*0.8*0.1) -> 8585.9929 | AB26: =IF(AJ26="Принят",(J26/1.18-W26-Z26)*0.1,J26/1.18*0.8*0.1)-AA26 -> 0 | AF26: =IF(OR(I26="",I26=0,N26="",N26=0),"Нет инфо",I26/N26) -> 94.734155 | AG26: =IF(OR(I26="",I26=0,R26="",R26=0),"Нет инфо",I26/R26) -> Нет инфо | AH26: Реаб. | AI26: 45393 | AJ26: Принят | AK26: Сакорггаз | AL26: 44935 | AM26: BCG-230109-1/0(4) | AO26: P.2.577 | AP26: P.2.577
A27: 2056 | B27: Квемо Картли | C27: Рустави | D27: (4) გამოსატანი მრიცხველების გამოტანა P.2.577 (მესხიშვ. II გასასვლ. №6 კორპ) | E27: მესხიშვ. II გასასვლ. №6 კორპ | F27: Интерсервис 2011 | G27: 577 | H27: =789.25+40000+48407 -> 89196.25 | I27: =789.25+40000+48407 -> 89196.25 | J27: =I27-789.25 -> 88407 | K27: =789.25+Y27+6101.69+7384.12+41022.88 -> 89196.25 | L27: =H27-K27 -> 0 | M27: =I27-K27 -> 0 | N27: 1281 | O27: =IF(OR(AJ27="принят",AJ27="Завершено",AJ27="ПриПро"),I27-K27,H27-K27) -> 0 | P27: 0 | S27: 0 | T27: 0 | U27: 0 | V27: 0 | Y27: 33898.31 | Z27: 1036.92 | AA27: =IF(AJ27="Принят",(J27/1.18-W27-Z27)*0.1,J27/1.18*0.8*0.1) -> 7388.4266 | AB27: =IF(AJ27="Принят",(J27/1.18-W27-Z27)*0.1,J27/1.18*0.8*0.1)-AA27 -> 0 | AF27: =IF(OR(I27="",I27=0,N27="",N27=0),"Нет инфо",I27/N27) -> 69.630172 | AG27: =IF(OR(I27="",I27=0,R27="",R27=0),"Нет инфо",I27/R27) -> Нет инфо | AH27: Реаб. | AI27: 45380 | AJ27: Принят | AK27: Сакорггаз | AL27: 44935 | AM27: BCG-230109-1/0(4) | AO27: P.2.577 | AP27: P.2.577
A28: 2057 | B28: Квемо Картли | C28: Рустави | D28: (4) გამოსატანი მრიცხველების გამოტანა P.2.577 (მესხიშვ. II გასასვლ. №4 კორპ) | E28: მესხიშვ. II გასასვლ. №4 კორპ | F28: Интерсервис 2011 | G28: 577 | H28: =1214.5+40000+41772 -> 82986.5 | I28: =1214.5+40000+41772 -> 82986.5 | J28: =I28-1214.5 -> 81772 | K28: =185.26+6101.69+Y28+6372+36429.24 -> 82986.5 | L28: =H28-K28 -> 0 | M28: =I28-K28 -> 0 | N28: 1004 | O28: =IF(OR(AJ28="принят",AJ28="Завершено",AJ28="ПриПро"),I28-K28,H28-K28) -> 0 | P28: 0 | S28: 0 | T28: 0 | U28: 0 | V28: 0 | Y28: 33898.31 | Z28: 1036.92 | AA28: =IF(AJ28="Принят",(J28/1.18-W28-Z28)*0.1,J28/1.18*0.8*0.1) -> 6826.1385 | AB28: =IF(AJ28="Принят",(J28/1.18-W28-Z28)*0.1,J28/1.18*0.8*0.1)-AA28 -> 0 | AF28: =IF(OR(I28="",I28=0,N28="",N28=0),"Нет инфо",I28/N28) -> 82.655876 | AG28: =IF(OR(I28="",I28=0,R28="",R28=0),"Нет инфо",I28/R28) -> Нет инфо | AH28: Реаб. | AI28: 45380 | AJ28: Принят | AK28: Сакорггаз | AL28: 44935 | AM28: BCG-230109-1/0(4) | AO28: P.2.577 | AP28: P.2.577
A29: 2058 | B29: Квемо Картли | C29: Рустави | D29: (4) გამოსატანი მრიცხველების გამოტანა P.2.577 (მესხიშვ. II გასასვლ. №8 კორპ) | E29: მესხიშვ. II გასასვლ. №8 კორპ | F29: Интерсервис 2011 | G29: 577 | H29: =778.75+40000 -> 40778.75 | I29: =778.75+40000+31053 -> 71831.75 | J29: =I29-778.75 -> 71053 | K29: =778.75+6101.69+Y29+4736.89+26316.11 -> 71831.75 | L29: =H29-K29 -> -31053 | M29: =I29-K29 -> 0 | N29: 785 | O29: =IF(OR(AJ29="принят",AJ29="Завершено",AJ29="ПриПро"),I29-K29,H29-K29) -> 0 | P29: 0 | S29: 0 | T29: 0 | U29: 0 | V29: 0 | Y29: 33898.31 | Z29: 1036.92 | AA29: =IF(AJ29="Принят",(J29/1.18-W29-Z29)*0.1,J29/1.18*0.8*0.1) -> 5917.7487 | AB29: =IF(AJ29="Принят",(J29/1.18-W29-Z29)*0.1,J29/1.18*0.8*0.1)-AA29 -> 0 | AF29: =IF(OR(I29="",I29=0,N29="",N29=0),"Нет инфо",I29/N29) -> 91.505414 | AG29: =IF(OR(I29="",I29=0,R29="",R29=0),"Нет инфо",I29/R29) -> Нет инфо | AH29: Реаб. | AI29: 45380 | AJ29: Принят | AK29: Сакорггаз | AL29: 44935 | AM29: BCG-230109-1/0(4) | AO29: P.2.577 | AP29: P.2.577
A30: 2059 | B30: Квемо Картли | C30: Рустави | D30: (4) გამოსატანი მრიცხველების გამოტანა P.2.577 (შარტავას ქ. №15 კორპუსი) | E30: შარტავას ქ. №15 კორპუსი | F30: Интерсервис 2011 | G30: 577 | H30: =866.25+50000+29540 -> 80406.25 | I30: =866.25+50000+29540 -> 80406.25 | J30: =I30-866.25 -> 79540 | K30: =866.25+7627.12+Y30+4506.1+25033.9 -> 80406.25 | L30: =H30-K30 -> 0 | M30: =I30-K30 -> 0 | N30: 1201 | O30: =IF(OR(AJ30="принят",AJ30="Завершено",AJ30="ПриПро"),I30-K30,H30-K30) -> 0 | P30: 0 | S30: 0 | T30: 0 | U30: 0 | V30: 0 | Y30: 42372.88 | Z30: 1296.15 | AA30: =IF(AJ30="Принят",(J30/1.18-W30-Z30)*0.1,J30/1.18*0.8*0.1) -> 6611.063 | AB30: =IF(AJ30="Принят",(J30/1.18-W30-Z30)*0.1,J30/1.18*0.8*0.1)-AA30 -> 0 | AF30: =IF(OR(I30="",I30=0,N30="",N30=0),"Нет инфо",I30/N30) -> 66.949417 | AG30: =IF(OR(I30="",I30=0,R30="",R30=0),"Нет инфо",I30/R30) -> Нет инфо | AH30: Реаб. | AI30: 45370 | AJ30: Принят | AK30: Сакорггаз | AL30: 44935 | AM30: BCG-230109-1/0(4) | AO30: P.2.577 | AP30: P.2.577
A31: 2060 | B31: Квемо Картли | C31: Рустави | D31: (6) გამოტანილი მრიცხველების პოლიეთილენის მილების შეცვლა რკინის მილებით (P.2.619) (შარტავას ქ. №7 კორპ) | E31: შარტავას ქ. №7 კორპუსი | F31: Интерсервис 2011 | G31: 619 | H31: =1400+55000+24730 -> 81130 | I31: =1400+55000+24730 -> 81130 | J31: =I31-1400 -> 79730 | K31: =1400+8389.83+Y31+3772.37+20957.63 -> 81130 | L31: =H31-K31 -> 0 | M31: =I31-K31 -> 0 | N31: 1088 | O31: =IF(OR(AJ31="принят",AJ31="Завершено",AJ31="ПриПро"),I31-K31,H31-K31) -> 0 | P31: 0 | S31: 0 | T31: 0 | U31: 0 | Y31: 46610.17 | Z31: 1425.76 | AA31: =IF(AJ31="Принят",(J31/1.18-W31-Z31)*0.1,J31/1.18*0.8*0.1) -> 6614.2037 | AB31: =IF(AJ31="Принят",(J31/1.18-W31-Z31)*0.1,J31/1.18*0.8*0.1)-AA31 -> 0 | AF31: =IF(OR(I31="",I31=0,N31="",N31=0),"Нет инфо",I31/N31) -> 74.568015 | AG31: =IF(OR(I31="",I31=0,R31="",R31=0),"Нет инфо",I31/R31) -> Нет инфо | AH31: Реаб. | AI31: 45370 | AJ31: Принят | AK31: Сакорггаз | AL31: 44935 | AM31: BCG-230109-1/0(6) | AO31: P.2.619 | AP31: P.2.619
A32: 2061 | B32: Самцхе Джавахети | C32: Борджоми | D32: 1.1.24. В г. Боржоми реабилитация/реконструкция наружных сетей в корпусах на улицах Руставели и Месхети. (P.3.106) (проектирование и строительство) (აღმაშენებლის 35) | E32: აღმაშენებლის 35 | F32: Газ Констракт | H32: =47717.84+2152.5 -> 49870.34 | I32: =47717.84+2152.5 -> 49870.34 | J32: =I32-2152.5 -> 47717.84 | K32: =328.35+47717.84+1824.15 -> 49870.34 | L32: =H32-K32 -> 0 | M32: =I32-K32 -> 0 | N32: 1289.3 | O32: =IF(OR(AJ32="принят",AJ32="Завершено",AJ32="ПриПро"),I32-K32,H32-K32) -> 0 | P32: 0 | S32: 0 | T32: 0 | U32: 0 | V32: 0 | W32: 0 | Y32: 0 | Z32: 0 | AA32: =J32/1.18*0.1 -> 4043.8847 | AB32: =IF(AJ32="Принят",(J32/1.18-W32-Z32)*0.1,J32/1.18*0.8*0.1)-AA32 -> 0 | AF32: =IF(OR(I32="",I32=0,N32="",N32=0),"Нет инфо",I32/N32) -> 38.680168 | AG32: =IF(OR(I32="",I32=0,R32="",R32=0),"Нет инфо",I32/R32) -> Нет инфо | AH32: Реаб. | AI32: 45351 | AJ32: Принят | AK32: Сакорггаз | AL32: 44676 | AM32: BCP-220425-1/2(1.1.24) | AO32: P.3.106 | AP32: P.3.106
A33: 2062 | B33: Квемо Картли | C33: Рустави | D33: (4) გამოსატანი მრიცხველების გამოტანა P.2.577 (შარტავას ქ. №17 კორპუსი) | E33: შარტავას ქ. №17 კორპუსი | F33: Интерсервис 2011 | G33: 577 | H33: =1550.5+70000+40956 -> 112506.5 | I33: =1550.5+70000+40956 -> 112506.5 | J33: =I33-1550.5 -> 110956 | K33: =236.52+Y33+10677.97+42269.98 -> 112506.5 | L33: =H33-K33 -> 0 | M33: =I33-K33 -> 0 | N33: 1103 | O33: =IF(OR(AJ33="принят",AJ33="Завершено",AJ33="ПриПро"),I33-K33,H33-K33) -> 0 | P33: 0 | S33: 0 | T33: 0 | U33: 0 | Y33: 59322.03 | Z33: 1107.62 | AA33: =IF(AJ33="Принят",(J33/1.18-W33-Z33)*0.1,J33/1.18*0.8*0.1) -> 9292.2888 | AB33: =IF(AJ33="Принят",(J33/1.18-W33-Z33)*0.1,J33/1.18*0.8*0.1)-AA33 -> 0 | AF33: =IF(OR(I33="",I33=0,N33="",N33=0),"Нет инфо",I33/N33) -> 102.00045 | AG33: =IF(OR(I33="",I33=0,R33="",R33=0),"Нет инфо",I33/R33) -> Нет инфо | AH33: Реаб. | AI33: 45400 | AJ33: Принят | AK33: Сакорггаз | AL33: 44935 | AM33: BCG-230109-1/0(4) | AO33: P.2.577 | AP33: P.2.577
A34: 2063 | B34: Квемо Картли | C34: Рустави | D34: (4) გამოსატანი მრიცხველების გამოტანა P.2.577 (ტაშკენტის ქ. №5 კორპუსი) | E34: ტაშკენტის ქ. №5 კორპუსი | F34: Интерсервис 2011 | G34: 577 | H34: =2096.5+120000+20000+39778 -> 181874.5 | I34: =2096.5+120000+20000+39778 -> 181874.5 | J34: =I34-2096.5 -> 179778 | K34: =319.81+Y34+18305.08+3050.847+58503.843 -> 181874.5 | L34: =H34-K34 -> 0 | M34: =I34-K34 -> 0 | N34: 1851 | O34: =IF(OR(AJ34="принят",AJ34="Завершено",AJ34="ПриПро"),I34-K34,H34-K34) -> 0 | P34: 0 | S34: 0 | T34: 0 | U34: 0 | Y34: 101694.92 | Z34: 1898.77 | AA34: =IF(AJ34="Принят",(J34/1.18-W34-Z34)*0.1,J34/1.18*0.8*0.1) -> 15045.547 | AB34: =IF(AJ34="Принят",(J34/1.18-W34-Z34)*0.1,J34/1.18*0.8*0.1)-AA34 -> 0 | AF34: =IF(OR(I34="",I34=0,N34="",N34=0),"Нет инфо",I34/N34) -> 98.257428 | AG34: =IF(OR(I34="",I34=0,R34="",R34=0),"Нет инфо",I34/R34) -> Нет инфо | AH34: Реаб. | AI34: 45400 | AJ34: Принят | AK34: Сакорггаз | AL34: 44935 | AM34: BCG-230109-1/0(4) | AO34: P.2.577 | AP34: P.2.577
A35: 2064 | B35: Квемо Картли | C35: Рустави | D35: (4) გამოსატანი მრიცხველების გამოტანა P.2.577 (ტაშკენტის ქ. №7 კორპუსი) | E35: ტაშკენტის ქ. №7 კორპუსი | F35: Интерсервис 2011 | G35: 577 | H35: =560+50000+10000+13943 -> 74503 | I35: =560+50000+10000+13943 -> 74503 | J35: =I35-560 -> 73943 | K35: =560+Y35+7627.12+1525.42+22417.58 -> 74503 | L35: =H35-K35 -> 0 | M35: =I35-K35 -> 0 | N35: 788 | O35: =IF(OR(AJ35="принят",AJ35="Завершено",AJ35="ПриПро"),I35-K35,H35-K35) -> 0 | P35: 0 | S35: 0 | T35: 0 | U35: 0 | Y35: 42372.88 | Z35: 791.15 | AA35: =IF(AJ35="Принят",(J35/1.18-W35-Z35)*0.1,J35/1.18*0.8*0.1) -> 6187.2409 | AB35: =IF(AJ35="Принят",(J35/1.18-W35-Z35)*0.1,J35/1.18*0.8*0.1)-AA35 -> 0 | AF35: =IF(OR(I35="",I35=0,N35="",N35=0),"Нет инфо",I35/N35) -> 94.546954 | AG35: =IF(OR(I35="",I35=0,R35="",R35=0),"Нет инфо",I35/R35) -> Нет инфо | AH35: Реаб. | AI35: 45400 | AJ35: Принят | AK35: Сакорггаз | AL35: 44935 | AM35: BCG-230109-1/0(4) | AO35: P.2.577 | AP35: P.2.577
A36: 2065 | B36: Квемо Картли | C36: Рустави | D36: (4) გამოსატანი მრიცხველების გამოტანა P.2.577 (მესხიშვ. ქუჩა №6 კორპ) | E36: მესხიშვ. ქუჩა №6 კორპ | F36: Интерсервис 2011 | G36: 577 | H36: =759.5+40000+10000+24276 -> 75035.5 | I36: =759.5+40000+10000+24276 -> 75035.5 | J36: =I36-759.5 -> 74276 | K36: =759.5+6101.69+Y36+1525.42+32750.58 -> 75035.5 | L36: =H36-K36 -> 0 | M36: =I36-K36 -> 0 | N36: 983 | O36: =IF(OR(AJ36="принят",AJ36="Завершено",AJ36="ПриПро"),I36-K36,H36-K36) -> 0 | P36: 0 | S36: 0 | T36: 0 | U36: 0 | Y36: 33898.31 | Z36: 632.92 | AA36: =IF(AJ36="Принят",(J36/1.18-W36-Z36)*0.1,J36/1.18*0.8*0.1) -> 6231.2843 | AB36: =IF(AJ36="Принят",(J36/1.18-W36-Z36)*0.1,J36/1.18*0.8*0.1)-AA36 -> 0 | AF36: =IF(OR(I36="",I36=0,N36="",N36=0),"Нет инфо",I36/N36) -> 76.333164 | AG36: =IF(OR(I36="",I36=0,R36="",R36=0),"Нет инфо",I36/R36) -> Нет инфо | AH36: Реаб. | AI36: 45400 | AJ36: Принят | AK36: Сакорггаз | AL36: 44935 | AM36: BCG-230109-1/0(4) | AO36: P.2.577 | AP36: P.2.577
A37: 2066 | B37: Квемо Картли | C37: Рустави | D37: (12) გამოტანილი მრიცხველების პოლიეთილენის მილების შეცვლა რკინის მილებით (P.2.648) (მე-12-ე მკრ. № 19 კორპ) | E37: მე-12-ე მკრ. № 19 კორპ | F37: Интерсервис 2011 | G37: 648 | H37: =3290+80000+2000+25842 -> 111132 | I37: =3290+80000+2000+25842 -> 111132 | J37: =I37-3290 -> 107842 | K37: =501.86+Y37+12203.39+305.08+28630.14 -> 111132 | L37: =H37-K37 -> 0 | M37: =I37-K37 -> 0 | N37: 2146 | O37: =IF(OR(AJ37="принят",AJ37="Завершено",AJ37="ПриПро"),I37-K37,H37-K37) -> 0 | P37: 0 | S37: 0 | T37: 0 | U37: 0 | V37: 0 | W37: 0 | Y37: =67796.61+1694.92 -> 69491.53 | Z37: =2073.83+31.65 -> 2105.48 | AA37: =IF(AJ37="Принят",(J37/1.18-W37-Z37)*0.1,J37/1.18*0.8*0.1) -> 8928.6045 | AB37: =IF(AJ37="Принят",(J37/1.18-W37-Z37)*0.1,J37/1.18*0.8*0.1)-AA37 -> 0 | AF37: =IF(OR(I37="",I37=0,N37="",N37=0),"Нет инфо",I37/N37) -> 51.785648 | AG37: =IF(OR(I37="",I37=0,R37="",R37=0),"Нет инфо",I37/R37) -> Нет инфо | AH37: Реаб. | AI37: 45393 | AJ37: Принят | AK37: Сакорггаз | AL37: 44935 | AM37: BCG-230109-1/0(12) | AO37: P.2.648 | AP37: P.2.648
A38: 2067 | B38: Квемо Картли | C38: Рустави | D38: (8) გამოტანილი მრიცხველების პოლიეთილენის მილების შეცვლა რკინის მილებით (P.2.701) (ფალიაშვილის ქ. №5 კორპ) | E38: ფალიაშვილის ქ. №5 კორპ | F38: Интерсервис 2011 | G38: 701 | H38: =2247+90000+10000+11965 -> 114212 | I38: =2247+90000+10000+11965 -> 114212 | J38: =I38-2247 -> 111965 | K38: =342.76+Y38+13728.81+1525.42+22343.82 -> 114212 | L38: =H38-K38 -> 0 | M38: =I38-K38 -> 0 | N38: 1009 | O38: =IF(OR(AJ38="принят",AJ38="Завершено",AJ38="ПриПро"),I38-K38,H38-K38) -> 0 | P38: 0 | S38: 0 | T38: 0 | U38: 0 | V38: 0 | W38: 0 | Y38: 76271.19 | Z38: 1424.08 | AA38: =IF(AJ38="Принят",(J38/1.18-W38-Z38)*0.1,J38/1.18*0.8*0.1) -> 9346.1513 | AB38: =IF(AJ38="Принят",(J38/1.18-W38-Z38)*0.1,J38/1.18*0.8*0.1)-AA38 -> 0 | AF38: =IF(OR(I38="",I38=0,N38="",N38=0),"Нет инфо",I38/N38) -> 113.19326 | AG38: =IF(OR(I38="",I38=0,R38="",R38=0),"Нет инфо",I38/R38) -> Нет инфо | AH38: Реаб. | AI38: 45400 | AJ38: Принят | AK38: Сакорггаз | AL38: 44935 | AM38: BCG-230109-1/0(8) | AO38: P.2.701 | AP38: P.2.701
A39: 2068 | B39: Квемо Картли | C39: Рустави | D39: (4) გამოსატანი მრიცხველების გამოტანა P.2.577 (მე-15-ე მკრ. 8 კორპ) | E39: მე-15-ე მკრ. 8 კორპ | F39: Интерсервис 2011 | G39: 577 | H39: =35000+12233.96 -> 47233.96 | I39: =1389.5+35000+12233.96 -> 48623.46 | J39: =I39-1389.5 -> 47233.96 | K39: =211.96+S39+V39+Y39+5338.98+1866.2+11545.3 -> 48623.46 | L39: =H39-K39 -> -1389.5 | M39: =I39-K39 -> 0 | N39: 771 | O39: =IF(OR(AJ39="принят",AJ39="Завершено",AJ39="ПриПро"),I39-K39,H39-K39) -> 7.2759576e-12 | P39: 0 | S39: 0 | T39: 0 | U39: 0 | V39: 29661.02 | W39: 1484.68 | AA39: =IF(AJ39="Принят",(J39/1.18-W39-Z39)*0.1,J39/1.18*0.8*0.1) -> 3854.41 | AB39: =IF(AJ39="Принят",(J39/1.18-W39-Z39)*0.1,J39/1.18*0.8*0.1)-AA39 -> 0 | AF39: =IF(OR(I39="",I39=0,N39="",N39=0),"Нет инфо",I39/N39) -> 63.065447 | AG39: =IF(OR(I39="",I39=0,R39="",R39=0),"Нет инфо",I39/R39) -> Нет инфо | AH39: Реаб. | AI39: 45351 | AJ39: Принят | AK39: Сакорггаз | AL39: 44935 | AM39: BCG-230109-1/0(4) | AO39: P.2.577 | AP39: P.2.577
A40: 2069 | B40: Квемо Картли | C40: Рустави | D40: (6) გამოტანილი მრიცხველების პოლიეთილენის მილების შეცვლა რკინის მილებით (P.2.619) (მე-16-ე მკრ. 11 კორპ) | E40: მე-16-ე მკრ. 11 კორპ | F40: Интерсервис 2011 | G40: 619 | H40: =1312.5+30000+2000+5557 -> 38869.5 | I40: =1312.5+30000+2000+5557 -> 38869.5 | J40: =I40-1312.5 -> 37557 | K40: =200.21+V40+4576.27+Y40+305.08+6669.29 -> 38869.5 | L40: =H40-K40 -> 0 | M40: =I40-K40 -> 0 | N40: 680 | O40: =IF(OR(AJ40="принят",AJ40="Завершено",AJ40="ПриПро"),I40-K40,H40-K40) -> 0 | P40: 0 | S40: 0 | T40: 0 | U40: 0 | V40: 25423.73 | W40: 1272.58 | Y40: 1694.92 | Z40: 31.65 | AA40: =IF(AJ40="Принят",(J40/1.18-W40-Z40)*0.1,J40/1.18*0.8*0.1) -> 3052.3736 | AB40: =IF(AJ40="Принят",(J40/1.18-W40-Z40)*0.1,J40/1.18*0.8*0.1)-AA40 -> 0 | AF40: =IF(OR(I40="",I40=0,N40="",N40=0),"Нет инфо",I40/N40) -> 57.161029 | AG40: =IF(OR(I40="",I40=0,R40="",R40=0),"Нет инфо",I40/R40) -> Нет инфо | AH40: Реаб. | AI40: 45393 | AJ40: Принят | AK40: Сакорггаз | AL40: 44935 | AM40: BCG-230109-1/0(6) | AO40: P.2.619 | AP40: P.2.619
A41: 2070 | B41: Квемо Картли | C41: Рустави | D41: (4) გამოსატანი მრიცხველების გამოტანა P.2.577 (მე-14-ე მკრ. 47 კორპ) | E41: მე-14-ე მკრ. 47 კორპ | F41: Интерсервис 2011 | G41: 577 | H41: =1086.75+35000+5000+22059 -> 63145.75 | I41: =1086.75+35000+5000+22059 -> 63145.75 | J41: =I41-1086.75 -> 62059 | K41: =165.78+V41+5338.98+Y41+762.71+22979.97 -> 63145.75 | L41: =H41-K41 -> 0 | M41: =I41-K41 -> 0 | N41: 706 | O41: =IF(OR(AJ41="принят",AJ41="Завершено",AJ41="ПриПро"),I41-K41,H41-K41) -> 0 | P41: 0 | S41: 0 | T41: 0 | U41: 0 | V41: 29661.02 | W41: 1484.68 | Y41: 4237.29 | Z41: 79.12 | AA41: =IF(AJ41="Принят",(J41/1.18-W41-Z41)*0.1,J41/1.18*0.8*0.1) -> 5102.8573 | AB41: =IF(AJ41="Принят",(J41/1.18-W41-Z41)*0.1,J41/1.18*0.8*0.1)-AA41 -> 0 | AF41: =IF(OR(I41="",I41=0,N41="",N41=0),"Нет инфо",I41/N41) -> 89.441572 | AG41: =IF(OR(I41="",I41=0,R41="",R41=0),"Нет инфо",I41/R41) -> Нет инфо | AH41: Реаб. | AI41: 45393 | AJ41: Принят | AK41: Сакорггаз | AL41: 44935 | AM41: BCG-230109-1/0(4) | AO41: P.2.577 | AP41: P.2.577
A42: 2071 | B42: Квемо Картли | C42: Рустави | D42: (4) გამოსატანი მრიცხველების გამოტანა P.2.577 (მე-15-ე მკრ. 9 კორპ) | E42: მე-15-ე მკრ. 9 კორპ | F42: Интерсервис 2011 | G42: 577 | H42: =1370.25+35000+5000+8022 -> 49392.25 | I42: =1370.25+35000+5000+8022 -> 49392.25 | J42: =I42-1370.25 -> 48022 | K42: =209.02+V42+5338.98+Y42+762.71+9183.23 -> 49392.25 | L42: =H42-K42 -> 0 | M42: =I42-K42 -> 0 | N42: 725 | O42: =IF(OR(AJ42="принят",AJ42="Завершено",AJ42="ПриПро"),I42-K42,H42-K42) -> 0 | P42: 0 | S42: 0 | T42: 0 | U42: 0 | V42: 29661.02 | W42: 1484.68 | Y42: 4237.29 | Z42: 79.12 | AA42: =IF(AJ42="Принят",(J42/1.18-W42-Z42)*0.1,J42/1.18*0.8*0.1) -> 3913.281 | AB42: =IF(AJ42="Принят",(J42/1.18-W42-Z42)*0.1,J42/1.18*0.8*0.1)-AA42 -> 0 | AF42: =IF(OR(I42="",I42=0,N42="",N42=0),"Нет инфо",I42/N42) -> 68.127241 | AG42: =IF(OR(I42="",I42=0,R42="",R42=0),"Нет инфо",I42/R42) -> Нет инфо | AH42: Реаб. | AI42: 45393 | AJ42: Принят | AK42: Сакорггаз | AL42: 44935 | AM42: BCG-230109-1/0(4) | AO42: P.2.577 | AP42: P.2.577
A43: 2072 | B43: Квемо Картли | C43: Рустави | D43: (10) გამოტანილი მრიცხველების პოლიეთილენის მილების შეცვლა რკინის მილებით P.2.721 (მე-7ა-ე მკრ. №1 კორპ) | E43: მე-7ა-ე მკრ. №1 კორპ | F43: Интерсервис 2011 | G43: 721 | H43: =3724+60000+2000+36122.19 -> 101846.19 | I43: =3724+60000+2000+36122.19 -> 101846.19 | J43: =I43-3724 -> 98122.19 | K43: =568.07+9152.54+305.08+S43+V43+Y43+5510.16+33767.96 -> 101846.19 | L43: =H43-K43 -> 0 | M43: =I43-K43 -> 0 | N43: 2046 | O43: =IF(OR(AJ43="принят",AJ43="Завершено",AJ43="ПриПро"),I43-K43,H43-K43) -> 0 | P43: 0 | S43: 0 | T43: 0 | U43: 0 | V43: =50847.46+1694.92 -> 52542.38 | W43: =3615.05+84.84 -> 3699.89 | Y43: 0 | Z43: 0 | AA43: =IF(AJ43="Принят",(J43/1.18-W43-Z43)*0.1,J43/1.18*0.8*0.1) -> 7945.4508 | AB43: =IF(AJ43="Принят",(J43/1.18-W43-Z43)*0.1,J43/1.18*0.8*0.1)-AA43 -> 0 | AF43: =IF(OR(I43="",I43=0,N43="",N43=0),"Нет инфо",I43/N43) -> 49.778196 | AG43: =IF(OR(I43="",I43=0,R43="",R43=0),"Нет инфо",I43/R43) -> Нет инфо | AH43: Реаб. | AI43: 45370 | AJ43: Принят | AK43: Сакорггаз | AL43: 44935 | AM43: BCG-230109-1/0(10) | AO43: P.2.721 | AP43: P.2.721
A44: 2073 | B44: Квемо Картли | C44: Рустави | D44: (10) გამოტანილი მრიცხველების პოლიეთილენის მილების შეცვლა რკინის მილებით P.2.721 (მე-7ა-ე მკრ. №2 კორპ) | E44: მე-7ა-ე მკრ. №2 კორპ | F44: Интерсервис 2011 | G44: 721 | H44: =3466.75+60000+35568 -> 99034.75 | I44: =3466.75+60000+35568 -> 99034.75 | J44: =I44-3466.75 -> 95568 | K44: =S44+V44+Y44+9152.54+528.83+5425.63+33080.29 -> 99034.75 | L44: =H44-K44 -> 0 | M44: =I44-K44 -> 0 | N44: 2005 | O44: =IF(OR(AJ44="принят",AJ44="Завершено",AJ44="ПриПро"),I44-K44,H44-K44) -> 0 | P44: 0 | S44: 0 | T44: 0 | U44: 0 | V44: 50847.46 | W44: 3615.05 | AA44: =IF(AJ44="Принят",(J44/1.18-W44-Z44)*0.1,J44/1.18*0.8*0.1) -> 7737.4781 | AB44: =IF(AJ44="Принят",(J44/1.18-W44-Z44)*0.1,J44/1.18*0.8*0.1)-AA44 -> 0 | AF44: =IF(OR(I44="",I44=0,N44="",N44=0),"Нет инфо",I44/N44) -> 49.39389 | AG44: =IF(OR(I44="",I44=0,R44="",R44=0),"Нет инфо",I44/R44) -> Нет инфо | AH44: Реаб. | AI44: 45370 | AJ44: Принят | AK44: Сакорггаз | AL44: 44935 | AM44: BCG-230109-1/0(10) | AO44: P.2.721 | AP44: P.2.721
A45: 2074 | B45: Квемо Картли | C45: Болниси | D45: (1.1.2) დაბა კაზრეთის კორპუსების ქსელის რეაბ. და მრიცხველების გამოტანა (P.2.401)კორპ. №9/1 | E45: კორპუსი №9/1 | F45: (Пр)-Интерсервис 2011 | H45: 1529.5 | I45: 1529.5 | K45: =233.31+1296.19 -> 1529.5 | L45: =H45-K45 -> 0 | M45: =I45-K45 -> 0 | O45: =IF(OR(AJ45="принят",AJ45="Завершено",AJ45="ПриПро"),I45-K45,H45-K45) -> 0 | P45: 0 | S45: 0 | T45: 0 | U45: 0 | AB45: =IF(AJ45="Принят",(J45/1.18-W45-Z45)*0.1,J45/1.18*0.8*0.1)-AA45 -> 0 | AF45: =IF(OR(I45="",I45=0,N45="",N45=0),"Нет инфо",I45/N45) -> Нет инфо | AG45: =IF(OR(I45="",I45=0,R45="",R45=0),"Нет инфо",I45/R45) -> Нет инфо | AH45: Проектирование | AI45: 45363 | AJ45: ПриПро | AK45: Сакорггаз | AL45: 44677 | AM45: BCP-220426-1/2(1.1.2) | AO45: P.2.401 | AP45: P.2.401
A46: 2075 | B46: Квемо Картли | C46: Болниси | D46: (1.1.2) დაბა კაზრეთის კორპუსების ქსელის რეაბ. და მრიცხველების გამოტანა (P.2.401)კორპ. №9/2. | E46: კორპუსი №9/2. | F46: (Пр)-Интерсервис 2011 | H46: 1622.25 | I46: 1622.25 | K46: =247.46+1374.79 -> 1622.25 | L46: =H46-K46 -> 0 | M46: =I46-K46 -> 0 | O46: =IF(OR(AJ46="принят",AJ46="Завершено",AJ46="ПриПро"),I46-K46,H46-K46) -> 0 | P46: 0 | S46: 0 | T46: 0 | U46: 0 | AB46: =IF(AJ46="Принят",(J46/1.18-W46-Z46)*0.1,J46/1.18*0.8*0.1)-AA46 -> 0 | AF46: =IF(OR(I46="",I46=0,N46="",N46=0),"Нет инфо",I46/N46) -> Нет инфо | AG46: =IF(OR(I46="",I46=0,R46="",R46=0),"Нет инфо",I46/R46) -> Нет инфо | AH46: Проектирование | AI46: 45363 | AJ46: ПриПро | AK46: Сакорггаз | AL46: 44677 | AM46: BCP-220426-1/2(1.1.2) | AO46: P.2.401 | AP46: P.2.401
A47: 2076 | B47: Квемо Картли | C47: Болниси | D47: (1.1.2) დაბა კაზრეთის კორპუსების ქსელის რეაბ. და მრიცხველების გამოტანა (P.2.401)კორპ. №9/3 | E47: კორპუსი №9/3 | F47: (Пр)-Интерсервис 2011 | H47: 1683.5 | I47: 1683.5 | K47: =256.8+1426.7 -> 1683.5 | L47: =H47-K47 -> 0 | M47: =I47-K47 -> 0 | O47: =IF(OR(AJ47="принят",AJ47="Завершено",AJ47="ПриПро"),I47-K47,H47-K47) -> 0 | P47: 0 | S47: 0 | T47: 0 | U47: 0 | AB47: =IF(AJ47="Принят",(J47/1.18-W47-Z47)*0.1,J47/1.18*0.8*0.1)-AA47 -> 0 | AF47: =IF(OR(I47="",I47=0,N47="",N47=0),"Нет инфо",I47/N47) -> Нет инфо | AG47: =IF(OR(I47="",I47=0,R47="",R47=0),"Нет инфо",I47/R47) -> Нет инфо | AH47: Проектирование | AI47: 45363 | AJ47: ПриПро | AK47: Сакорггаз | AL47: 44677 | AM47: BCP-220426-1/2(1.1.2) | AO47: P.2.401 | AP47: P.2.401
A48: 2077 | B48: Квемо Картли | C48: Болниси | D48: (1.1.2) დაბა კაზრეთის კორპუსების ქსელის რეაბ. და მრიცხველების გამოტანა (P.2.401)კორპ. №9/4 | E48: კორპუსი №9/4 | F48: (Пр)-Интерсервис 2011 | H48: 1604.75 | I48: 1604.75 | K48: =244.79+1359.96 -> 1604.75 | L48: =H48-K48 -> 0 | M48: =I48-K48 -> 0 | O48: =IF(OR(AJ48="принят",AJ48="Завершено",AJ48="ПриПро"),I48-K48,H48-K48) -> 0 | P48: 0 | S48: 0 | T48: 0 | U48: 0 | AB48: =IF(AJ48="Принят",(J48/1.18-W48-Z48)*0.1,J48/1.18*0.8*0.1)-AA48 -> 0 | AF48: =IF(OR(I48="",I48=0,N48="",N48=0),"Нет инфо",I48/N48) -> Нет инфо | AG48: =IF(OR(I48="",I48=0,R48="",R48=0),"Нет инфо",I48/R48) -> Нет инфо | AH48: Проектирование | AI48: 45363 | AJ48: ПриПро | AK48: Сакорггаз | AL48: 44677 | AM48: BCP-220426-1/2(1.1.2) | AO48: P.2.401 | AP48: P.2.401
A49: 2078 | B49: Квемо Картли | C49: Болниси | D49: (1.1.2) დაბა კაზრეთის კორპუსების ქსელის რეაბ. და მრიცხველების გამოტანა (P.2.401)კორპ. №9/5 | E49: კორპუსი №9/5 | F49: (Пр)-Интерсервис 2011 | H49: 1538.25 | I49: 1538.25 | K49: =234.65+1303.6 -> 1538.25 | L49: =H49-K49 -> 0 | M49: =I49-K49 -> 0 | O49: =IF(OR(AJ49="принят",AJ49="Завершено",AJ49="ПриПро"),I49-K49,H49-K49) -> 0 | P49: 0 | S49: 0 | T49: 0 | U49: 0 | AB49: =IF(AJ49="Принят",(J49/1.18-W49-Z49)*0.1,J49/1.18*0.8*0.1)-AA49 -> 0 | AF49: =IF(OR(I49="",I49=0,N49="",N49=0),"Нет инфо",I49/N49) -> Нет инфо | AG49: =IF(OR(I49="",I49=0,R49="",R49=0),"Нет инфо",I49/R49) -> Нет инфо | AH49: Проектирование | AI49: 45363 | AJ49: ПриПро | AK49: Сакорггаз | AL49: 44677 | AM49: BCP-220426-1/2(1.1.2) | AO49: P.2.401 | AP49: P.2.401
A50: 2079 | B50: Квемо Картли | C50: Болниси | D50: (1.1.2) დაბა კაზრეთის კორპუსების ქსელის რეაბ. და მრიცხველების გამოტანა (P.2.401)კორპ. №9/13 | E50: კორპუსი №9/13 | F50: (Пр)-Интерсервис 2011 | H50: 1531.25 | I50: 1531.25 | K50: =233.58+1297.67 -> 1531.25 | L50: =H50-K50 -> 0 | M50: =I50-K50 -> 0 | O50: =IF(OR(AJ50="принят",AJ50="Завершено",AJ50="ПриПро"),I50-K50,H50-K50) -> 0 | P50: 0 | S50: 0 | T50: 0 | U50: 0 | AB50: =IF(AJ50="Принят",(J50/1.18-W50-Z50)*0.1,J50/1.18*0.8*0.1)-AA50 -> 0 | AF50: =IF(OR(I50="",I50=0,N50="",N50=0),"Нет инфо",I50/N50) -> Нет инфо | AG50: =IF(OR(I50="",I50=0,R50="",R50=0),"Нет инфо",I50/R50) -> Нет инфо | AH50: Проектирование | AI50: 45363 | AJ50: ПриПро | AK50: Сакорггаз | AL50: 44677 | AM50: BCP-220426-1/2(1.1.2) | AO50: P.2.401 | AP50: P.2.401
A51: 2080 | B51: Квемо Картли | C51: Болниси | D51: (1.1.2) დაბა კაზრეთის კორპუსების ქსელის რეაბ. და მრიცხველების გამოტანა (P.2.401)კორპ. №12/1 | E51: კორპუსი №12/1 | F51: (Пр)-Интерсервис 2011 | H51: 224 | I51: 224 | K51: 224 | L51: =H51-K51 -> 0 | M51: =I51-K51 -> 0 | O51: =IF(OR(AJ51="принят",AJ51="Завершено",AJ51="ПриПро"),I51-K51,H51-K51) -> 0 | P51: 0 | S51: 0 | T51: 0 | U51: 0 | AB51: =IF(AJ51="Принят",(J51/1.18-W51-Z51)*0.1,J51/1.18*0.8*0.1)-AA51 -> 0 | AF51: =IF(OR(I51="",I51=0,N51="",N51=0),"Нет инфо",I51/N51) -> Нет инфо | AG51: =IF(OR(I51="",I51=0,R51="",R51=0),"Нет инфо",I51/R51) -> Нет инфо | AH51: Проектирование | AI51: 45363 | AJ51: ПриПро | AK51: Сакорггаз | AL51: 44677 | AM51: BCP-220426-1/2(1.1.2) | AO51: P.2.401 | AP51: P.2.401
A52: 2081 | B52: Квемо Картли | C52: Болниси | D52: (1.1.2) დაბა კაზრეთის კორპუსების ქსელის რეაბ. და მრიცხველების გამოტანა (P.2.401)კორპ. №12/2 | E52: კორპუსი №12/2 | F52: (Пр)-Интерсервис 2011 | H52: 78.75 | I52: 78.75 | K52: 78.75 | L52: =H52-K52 -> 0 | M52: =I52-K52 -> 0 | O52: =IF(OR(AJ52="принят",AJ52="Завершено",AJ52="ПриПро"),I52-K52,H52-K52) -> 0 | P52: 0 | S52: 0 | T52: 0 | U52: 0 | AB52: =IF(AJ52="Принят",(J52/1.18-W52-Z52)*0.1,J52/1.18*0.8*0.1)-AA52 -> 0 | AF52: =IF(OR(I52="",I52=0,N52="",N52=0),"Нет инфо",I52/N52) -> Нет инфо | AG52: =IF(OR(I52="",I52=0,R52="",R52=0),"Нет инфо",I52/R52) -> Нет инфо | AH52: Проектирование | AI52: 45363 | AJ52: ПриПро | AK52: Сакорггаз | AL52: 44677 | AM52: BCP-220426-1/2(1.1.2) | AO52: P.2.401 | AP52: P.2.401
A53: 2082 | B53: Квемо Картли | C53: Болниси | D53: (1.1.2) დაბა კაზრეთის კორპუსების ქსელის რეაბ. და მრიცხველების გამოტანა (P.2.401)კორპ. №12/3 | E53: კორპუსი №12/3 | F53: (Пр)-Интерсервис 2011 | H53: 120.75 | I53: 120.75 | K53: 120.75 | L53: =H53-K53 -> 0 | M53: =I53-K53 -> 0 | O53: =IF(OR(AJ53="принят",AJ53="Завершено",AJ53="ПриПро"),I53-K53,H53-K53) -> 0 | P53: 0 | S53: 0 | T53: 0 | U53: 0 | AB53: =IF(AJ53="Принят",(J53/1.18-W53-Z53)*0.1,J53/1.18*0.8*0.1)-AA53 -> 0 | AF53: =IF(OR(I53="",I53=0,N53="",N53=0),"Нет инфо",I53/N53) -> Нет инфо | AG53: =IF(OR(I53="",I53=0,R53="",R53=0),"Нет инфо",I53/R53) -> Нет инфо | AH53: Проектирование | AI53: 45363 | AJ53: ПриПро | AK53: Сакорггаз | AL53: 44677 | AM53: BCP-220426-1/2(1.1.2) | AO53: P.2.401 | AP53: P.2.401
A54: 2083 | B54: Квемо Картли | C54: Болниси | D54: (1.1.2) დაბა კაზრეთის კორპუსების ქსელის რეაბ. და მრიცხველების გამოტანა (P.2.401)კორპ. №12/4 | E54: კორპუსი №12/4 | F54: (Пр)-Интерсервис 2011 | H54: 208.25 | I54: 208.25 | K54: 208.25 | L54: =H54-K54 -> 0 | M54: =I54-K54 -> 0 | O54: =IF(OR(AJ54="принят",AJ54="Завершено",AJ54="ПриПро"),I54-K54,H54-K54) -> 0 | P54: 0 | S54: 0 | T54: 0 | U54: 0 | AB54: =IF(AJ54="Принят",(J54/1.18-W54-Z54)*0.1,J54/1.18*0.8*0.1)-AA54 -> 0 | AF54: =IF(OR(I54="",I54=0,N54="",N54=0),"Нет инфо",I54/N54) -> Нет инфо | AG54: =IF(OR(I54="",I54=0,R54="",R54=0),"Нет инфо",I54/R54) -> Нет инфо | AH54: Проектирование | AI54: 45363 | AJ54: ПриПро | AK54: Сакорггаз | AL54: 44677 | AM54: BCP-220426-1/2(1.1.2) | AO54: P.2.401 | AP54: P.2.401
A55: 2084 | B55: Квемо Картли | C55: Болниси | D55: (1.1.2) დაბა კაზრეთის კორპუსების ქსელის რეაბ. და მრიცხველების გამოტანა (P.2.401)კორპ. №12/5 | E55: კორპუსი №12/5 | F55: (Пр)-Интерсервис 2011 | H55: 208.25 | I55: 208.25 | K55: 208.25 | L55: =H55-K55 -> 0 | M55: =I55-K55 -> 0 | O55: =IF(OR(AJ55="принят",AJ55="Завершено",AJ55="ПриПро"),I55-K55,H55-K55) -> 0 | P55: 0 | S55: 0 | T55: 0 | U55: 0 | AB55: =IF(AJ55="Принят",(J55/1.18-W55-Z55)*0.1,J55/1.18*0.8*0.1)-AA55 -> 0 | AF55: =IF(OR(I55="",I55=0,N55="",N55=0),"Нет инфо",I55/N55) -> Нет инфо | AG55: =IF(OR(I55="",I55=0,R55="",R55=0),"Нет инфо",I55/R55) -> Нет инфо | AH55: Проектирование | AI55: 45363 | AJ55: ПриПро | AK55: Сакорггаз | AL55: 44677 | AM55: BCP-220426-1/2(1.1.2) | AO55: P.2.401 | AP55: P.2.401
A56: 2085 | B56: Квемо Картли | C56: Болниси | D56: (1.1.2) დაბა კაზრეთის კორპუსების ქსელის რეაბ. და მრიცხველების გამოტანა (P.2.401)კორპ. №12/6 | E56: კორპუსი №12/6 | F56: (Пр)-Интерсервис 2011 | H56: 197.75 | I56: 197.75 | K56: 197.75 | L56: =H56-K56 -> 0 | M56: =I56-K56 -> 0 | O56: =IF(OR(AJ56="принят",AJ56="Завершено",AJ56="ПриПро"),I56-K56,H56-K56) -> 0 | P56: 0 | S56: 0 | T56: 0 | U56: 0 | AB56: =IF(AJ56="Принят",(J56/1.18-W56-Z56)*0.1,J56/1.18*0.8*0.1)-AA56 -> 0 | AF56: =IF(OR(I56="",I56=0,N56="",N56=0),"Нет инфо",I56/N56) -> Нет инфо | AG56: =IF(OR(I56="",I56=0,R56="",R56=0),"Нет инфо",I56/R56) -> Нет инфо | AH56: Проектирование | AI56: 45363 | AJ56: ПриПро | AK56: Сакорггаз | AL56: 44677 | AM56: BCP-220426-1/2(1.1.2) | AO56: P.2.401 | AP56: P.2.401
A57: 2086 | B57: Квемо Картли | C57: Болниси | D57: (1.1.2) დაბა კაზრეთის კორპუსების ქსელის რეაბ. და მრიცხველების გამოტანა (P.2.401)კორპ. №12/7 | E57: კორპუსი №12/7 | F57: (Пр)-Интерсервис 2011 | H57: 192.5 | I57: 192.5 | K57: 192.5 | L57: =H57-K57 -> 0 | M57: =I57-K57 -> 0 | O57: =IF(OR(AJ57="принят",AJ57="Завершено",AJ57="ПриПро"),I57-K57,H57-K57) -> 0 | P57: 0 | S57: 0 | T57: 0 | U57: 0 | AB57: =IF(AJ57="Принят",(J57/1.18-W57-Z57)*0.1,J57/1.18*0.8*0.1)-AA57 -> 0 | AF57: =IF(OR(I57="",I57=0,N57="",N57=0),"Нет инфо",I57/N57) -> Нет инфо | AG57: =IF(OR(I57="",I57=0,R57="",R57=0),"Нет инфо",I57/R57) -> Нет инфо | AH57: Проектирование | AI57: 45363 | AJ57: ПриПро | AK57: Сакорггаз | AL57: 44677 | AM57: BCP-220426-1/2(1.1.2) | AO57: P.2.401 | AP57: P.2.401
A58: 2087 | B58: Квемо Картли | C58: Болниси | D58: (1.1.2) დაბა კაზრეთის კორპუსების ქსელის რეაბ. და მრიცხველების გამოტანა (P.2.401)კორპ. №12/8 | E58: კორპუსი №12/8 | F58: (Пр)-Интерсервис 2011 | H58: 136.5 | I58: 136.5 | K58: 136.5 | L58: =H58-K58 -> 0 | M58: =I58-K58 -> 0 | O58: =IF(OR(AJ58="принят",AJ58="Завершено",AJ58="ПриПро"),I58-K58,H58-K58) -> 0 | P58: 0 | S58: 0 | T58: 0 | U58: 0 | AB58: =IF(AJ58="Принят",(J58/1.18-W58-Z58)*0.1,J58/1.18*0.8*0.1)-AA58 -> 0 | AF58: =IF(OR(I58="",I58=0,N58="",N58=0),"Нет инфо",I58/N58) -> Нет инфо | AG58: =IF(OR(I58="",I58=0,R58="",R58=0),"Нет инфо",I58/R58) -> Нет инфо | AH58: Проектирование | AI58: 45363 | AJ58: ПриПро | AK58: Сакорггаз | AL58: 44677 | AM58: BCP-220426-1/2(1.1.2) | AO58: P.2.401 | AP58: P.2.401
A59: 2088 | B59: Квемо Картли | C59: Болниси | D59: (1.1.2) დაბა კაზრეთის კორპუსების ქსელის რეაბ. და მრიცხველების გამოტანა (P.2.401)კორპ. №12/9 | E59: კორპუსი №12/9 | F59: (Пр)-Интерсервис 2011 | H59: 211.75 | I59: 211.75 | K59: 211.75 | L59: =H59-K59 -> 0 | M59: =I59-K59 -> 0 | O59: =IF(OR(AJ59="принят",AJ59="Завершено",AJ59="ПриПро"),I59-K59,H59-K59) -> 0 | P59: 0 | S59: 0 | T59: 0 | U59: 0 | AB59: =IF(AJ59="Принят",(J59/1.18-W59-Z59)*0.1,J59/1.18*0.8*0.1)-AA59 -> 0 | AF59: =IF(OR(I59="",I59=0,N59="",N59=0),"Нет инфо",I59/N59) -> Нет инфо | AG59: =IF(OR(I59="",I59=0,R59="",R59=0),"Нет инфо",I59/R59) -> Нет инфо | AH59: Проектирование | AI59: 45363 | AJ59: ПриПро | AK59: Сакорггаз | AL59: 44677 | AM59: BCP-220426-1/2(1.1.2) | AO59: P.2.401 | AP59: P.2.401
A60: 2089 | B60: Квемо Картли | C60: Болниси | D60: (1.1.2) დაბა კაზრეთის კორპუსების ქსელის რეაბ. და მრიცხველების გამოტანა (P.2.401)კორპ. №12/10 | E60: კორპუსი №12/10 | F60: (Пр)-Интерсервис 2011 | H60: 203 | I60: 203 | K60: 203 | L60: =H60-K60 -> 0 | M60: =I60-K60 -> 0 | O60: =IF(OR(AJ60="принят",AJ60="Завершено",AJ60="ПриПро"),I60-K60,H60-K60) -> 0 | P60: 0 | S60: 0 | T60: 0 | U60: 0 | AB60: =IF(AJ60="Принят",(J60/1.18-W60-Z60)*0.1,J60/1.18*0.8*0.1)-AA60 -> 0 | AF60: =IF(OR(I60="",I60=0,N60="",N60=0),"Нет инфо",I60/N60) -> Нет инфо | AG60: =IF(OR(I60="",I60=0,R60="",R60=0),"Нет инфо",I60/R60) -> Нет инфо | AH60: Проектирование | AI60: 45363 | AJ60: ПриПро | AK60: Сакорггаз | AL60: 44677 | AM60: BCP-220426-1/2(1.1.2) | AO60: P.2.401 | AP60: P.2.401
A61: 2090 | B61: Квемо Картли | C61: Болниси | D61: (1.1.2) დაბა კაზრეთის კორპუსების ქსელის რეაბ. და მრიცხველების გამოტანა (P.2.401)კორპ. №12/11 | E61: კორპუსი №12/11 | F61: (Пр)-Интерсервис 2011 | H61: 112 | I61: 112 | K61: 112 | L61: =H61-K61 -> 0 | M61: =I61-K61 -> 0 | O61: =IF(OR(AJ61="принят",AJ61="Завершено",AJ61="ПриПро"),I61-K61,H61-K61) -> 0 | P61: 0 | S61: 0 | T61: 0 | U61: 0 | AB61: =IF(AJ61="Принят",(J61/1.18-W61-Z61)*0.1,J61/1.18*0.8*0.1)-AA61 -> 0 | AF61: =IF(OR(I61="",I61=0,N61="",N61=0),"Нет инфо",I61/N61) -> Нет инфо | AG61: =IF(OR(I61="",I61=0,R61="",R61=0),"Нет инфо",I61/R61) -> Нет инфо | AH61: Проектирование | AI61: 45363 | AJ61: ПриПро | AK61: Сакорггаз | AL61: 44677 | AM61: BCP-220426-1/2(1.1.2) | AO61: P.2.401 | AP61: P.2.401
A62: 2091 | B62: Квемо Картли | C62: Болниси | D62: (1.1.2) დაბა კაზრეთის კორპუსების ქსელის რეაბ. და მრიცხველების გამოტანა (P.2.401)კორპ. №12/12 | E62: კორპუსი №12/12 | F62: (Пр)-Интерсервис 2011 | H62: 232.75 | I62: 232.75 | K62: 232.75 | L62: =H62-K62 -> 0 | M62: =I62-K62 -> 0 | O62: =IF(OR(AJ62="принят",AJ62="Завершено",AJ62="ПриПро"),I62-K62,H62-K62) -> 0 | P62: 0 | S62: 0 | T62: 0 | U62: 0 | AB62: =IF(AJ62="Принят",(J62/1.18-W62-Z62)*0.1,J62/1.18*0.8*0.1)-AA62 -> 0 | AF62: =IF(OR(I62="",I62=0,N62="",N62=0),"Нет инфо",I62/N62) -> Нет инфо | AG62: =IF(OR(I62="",I62=0,R62="",R62=0),"Нет инфо",I62/R62) -> Нет инфо | AH62: Проектирование | AI62: 45363 | AJ62: ПриПро | AK62: Сакорггаз | AL62: 44677 | AM62: BCP-220426-1/2(1.1.2) | AO62: P.2.401 | AP62: P.2.401
... A67: 2096 | B67: Квемо Картли | C67: Болниси | D67: (1.1.2) დაბა კაზრეთის კორპუსების ქსელის რეაბ. და მრიცხველების გამოტანა (P.2.401)კორპ. №60/4 | E67: კორპუსი №60/4 | F67: (Пр)-Интерсервис 2011 | H67: 925.75 | I67: 925.75 | K67: 925.75 | L67: =H67-K67 -> 0 | M67: =I67-K67 -> 0 | O67: =IF(OR(AJ67="принят",AJ67="Завершено",AJ67="ПриПро"),I67-K67,H67-K67) -> 0 | P67: 0 | S67: 0 | T67: 0 | U67: 0 | AB67: =IF(AJ67="Принят",(J67/1.18-W67-Z67)*0.1,J67/1.18*0.8*0.1)-AA67 -> 0 | AF67: =IF(OR(I67="",I67=0,N67="",N67=0),"Нет инфо",I67/N67) -> Нет инфо | AG67: =IF(OR(I67="",I67=0,R67="",R67=0),"Нет инфо",I67/R67) -> Нет инфо | AH67: Проектирование | AI67: 45363 | AJ67: ПриПро | AK67: Сакорггаз | AL67: 44677 | AM67: BCP-220426-1/2(1.1.2) | AO67: P.2.401 | AP67: P.2.401
A68: 2097 | B68: Квемо Картли | C68: Болниси | D68: (1.1.2) დაბა კაზრეთის კორპუსების ქსელის რეაბ. და მრიცხველების გამოტანა (P.2.401)კორპ. №63/66 | E68: კორპუსი №63/66 | F68: (Пр)-Интерсервис 2011 | H68: 1310.75 | I68: 1310.75 | K68: =199.945+1110.805 -> 1310.75 | L68: =H68-K68 -> 0 | M68: =I68-K68 -> 0 | O68: =IF(OR(AJ68="принят",AJ68="Завершено",AJ68="ПриПро"),I68-K68,H68-K68) -> 0 | P68: 0 | S68: 0 | T68: 0 | U68: 0 | AB68: =IF(AJ68="Принят",(J68/1.18-W68-Z68)*0.1,J68/1.18*0.8*0.1)-AA68 -> 0 | AF68: =IF(OR(I68="",I68=0,N68="",N68=0),"Нет инфо",I68/N68) -> Нет инфо | AG68: =IF(OR(I68="",I68=0,R68="",R68=0),"Нет инфо",I68/R68) -> Нет инфо | AH68: Проектирование | AI68: 45363 | AJ68: ПриПро | AK68: Сакорггаз | AL68: 44677 | AM68: BCP-220426-1/2(1.1.2) | AO68: P.2.401 | AP68: P.2.401
A69: 2098 | B69: Квемо Картли | C69: Болниси | D69: (1.1.2) დაბა კაზრეთის კორპუსების ქსელის რეაბ. და მრიცხველების გამოტანა (P.2.401)კორპ. №67/69 | E69: კორპუსი №67/69 | F69: (Пр)-Интерсервис 2011 | H69: 1555.75 | I69: 1555.75 | K69: =237.32+1318.43 -> 1555.75 | L69: =H69-K69 -> 0 | M69: =I69-K69 -> 0 | O69: =IF(OR(AJ69="принят",AJ69="Завершено",AJ69="ПриПро"),I69-K69,H69-K69) -> 0 | P69: 0 | S69: 0 | T69: 0 | U69: 0 | AB69: =IF(AJ69="Принят",(J69/1.18-W69-Z69)*0.1,J69/1.18*0.8*0.1)-AA69 -> 0 | AF69: =IF(OR(I69="",I69=0,N69="",N69=0),"Нет инфо",I69/N69) -> Нет инфо | AG69: =IF(OR(I69="",I69=0,R69="",R69=0),"Нет инфо",I69/R69) -> Нет инфо | AH69: Проектирование | AI69: 45363 | AJ69: ПриПро | AK69: Сакорггаз | AL69: 44677 | AM69: BCP-220426-1/2(1.1.2) | AO69: P.2.401 | AP69: P.2.401
A70: 2099 | B70: Квемо Картли | C70: Болниси | D70: (1.1.2) დაბა კაზრეთის კორპუსების ქსელის რეაბ. და მრიცხველების გამოტანა (P.2.401)კორპ. №70/73 | E70: კორპუსი №70/73 | F70: (Пр)-Интерсервис 2011 | H70: 1324.75 | I70: 1324.75 | K70: =202.08+1122.67 -> 1324.75 | L70: =H70-K70 -> 0 | M70: =I70-K70 -> 0 | O70: =IF(OR(AJ70="принят",AJ70="Завершено",AJ70="ПриПро"),I70-K70,H70-K70) -> 0 | P70: 0 | S70: 0 | T70: 0 | U70: 0 | AB70: =IF(AJ70="Принят",(J70/1.18-W70-Z70)*0.1,J70/1.18*0.8*0.1)-AA70 -> 0 | AF70: =IF(OR(I70="",I70=0,N70="",N70=0),"Нет инфо",I70/N70) -> Нет инфо | AG70: =IF(OR(I70="",I70=0,R70="",R70=0),"Нет инфо",I70/R70) -> Нет инфо | AH70: Проектирование | AI70: 45363 | AJ70: ПриПро | AK70: Сакорггаз | AL70: 44677 | AM70: BCP-220426-1/2(1.1.2) | AO70: P.2.401 | AP70: P.2.401
A71: 2100 | B71: Квемо Картли | C71: Болниси | D71: (1.1.2) დაბა კაზრეთის კორპუსების ქსელის რეაბ. და მრიცხველების გამოტანა (P.2.401)კორპ. №83/85 | E71: კორპუსი №83/85 | F71: (Пр)-Интерсервис 2011 | H71: 1512 | I71: 1512 | K71: =230.64+1281.36 -> 1512 | L71: =H71-K71 -> 0 | M71: =I71-K71 -> 0 | O71: =IF(OR(AJ71="принят",AJ71="Завершено",AJ71="ПриПро"),I71-K71,H71-K71) -> 0 | P71: 0 | S71: 0 | T71: 0 | U71: 0 | AB71: =IF(AJ71="Принят",(J71/1.18-W71-Z71)*0.1,J71/1.18*0.8*0.1)-AA71 -> 0 | AF71: =IF(OR(I71="",I71=0,N71="",N71=0),"Нет инфо",I71/N71) -> Нет инфо | AG71: =IF(OR(I71="",I71=0,R71="",R71=0),"Нет инфо",I71/R71) -> Нет инфо | AH71: Проектирование | AI71: 45363 | AJ71: ПриПро | AK71: Сакорггаз | AL71: 44677 | AM71: BCP-220426-1/2(1.1.2) | AO71: P.2.401 | AP71: P.2.401
A72: 2101 | B72: Квемо Картли | C72: Болниси | D72: (1.1.2) დაბა კაზრეთის კორპუსების ქსელის რეაბ. და მრიცხველების გამოტანა (P.2.401)კორპ. №88/90 | E72: კორპუსი №88/90 | F72: (Пр)-Интерсервис 2011 | H72: 1482.25 | I72: 1482.25 | K72: =226.11+1256.14 -> 1482.25 | L72: =H72-K72 -> 0 | M72: =I72-K72 -> 0 | O72: =IF(OR(AJ72="принят",AJ72="Завершено",AJ72="ПриПро"),I72-K72,H72-K72) -> 0 | P72: 0 | S72: 0 | T72: 0 | U72: 0 | AB72: =IF(AJ72="Принят",(J72/1.18-W72-Z72)*0.1,J72/1.18*0.8*0.1)-AA72 -> 0 | AF72: =IF(OR(I72="",I72=0,N72="",N72=0),"Нет инфо",I72/N72) -> Нет инфо | AG72: =IF(OR(I72="",I72=0,R72="",R72=0),"Нет инфо",I72/R72) -> Нет инфо | AH72: Проектирование | AI72: 45363 | AJ72: ПриПро | AK72: Сакорггаз | AL72: 44677 | AM72: BCP-220426-1/2(1.1.2) | AO72: P.2.401 | AP72: P.2.401
A73: 2102 | B73: Квемо Картли | C73: Болниси | D73: (1.1.2) დაბა კაზრეთის კორპუსების ქსელის რეაბ. და მრიცხველების გამოტანა (P.2.401)კორპ. №95/102 | E73: კორპუსი №95/102 | F73: (Пр)-Интерсервис 2011 | H73: 2394 | I73: 2394 | K73: =365.19+2028.81 -> 2394 | L73: =H73-K73 -> 0 | M73: =I73-K73 -> 0 | O73: =IF(OR(AJ73="принят",AJ73="Завершено",AJ73="ПриПро"),I73-K73,H73-K73) -> 0 | P73: 0 | S73: 0 | T73: 0 | U73: 0 | AB73: =IF(AJ73="Принят",(J73/1.18-W73-Z73)*0.1,J73/1.18*0.8*0.1)-AA73 -> 0 | AF73: =IF(OR(I73="",I73=0,N73="",N73=0),"Нет инфо",I73/N73) -> Нет инфо | AG73: =IF(OR(I73="",I73=0,R73="",R73=0),"Нет инфо",I73/R73) -> Нет инфо | AH73: Проектирование | AI73: 45363 | AJ73: ПриПро | AK73: Сакорггаз | AL73: 44677 | AM73: BCP-220426-1/2(1.1.2) | AO73: P.2.401 | AP73: P.2.401
A74: 2103 | B74: Квемо Картли | C74: Болниси | D74: (1.1.2) დაბა კაზრეთის კორპუსების ქსელის რეაბ. და მრიცხველების გამოტანა (P.2.401)კორპ. №97/1 | E74: კორპუსი №97/1 | F74: (Пр)-Интерсервис 2011 | H74: 2553.25 | I74: 2553.25 | K74: =389.48+2163.77 -> 2553.25 | L74: =H74-K74 -> 0 | M74: =I74-K74 -> 0 | O74: =IF(OR(AJ74="принят",AJ74="Завершено",AJ74="ПриПро"),I74-K74,H74-K74) -> 0 | P74: 0 | S74: 0 | T74: 0 | U74: 0 | AB74: =IF(AJ74="Принят",(J74/1.18-W74-Z74)*0.1,J74/1.18*0.8*0.1)-AA74 -> 0 | AF74: =IF(OR(I74="",I74=0,N74="",N74=0),"Нет инфо",I74/N74) -> Нет инфо | AG74: =IF(OR(I74="",I74=0,R74="",R74=0),"Нет инфо",I74/R74) -> Нет инфо | AH74: Проектирование | AI74: 45363 | AJ74: ПриПро | AK74: Сакорггаз | AL74: 44677 | AM74: BCP-220426-1/2(1.1.2) | AO74: P.2.401 | AP74: P.2.401
A75: 2104 | B75: Квемо Картли | C75: Болниси | D75: (1.1.2) დაბა კაზრეთის კორპუსების ქსელის რეაბ. და მრიცხველების გამოტანა (P.2.401)კორპ. №97/2 | E75: კორპუსი №97/2 | F75: (Пр)-Интерсервис 2011 | H75: 2541 | I75: 2541 | K75: =387.61+2153.39 -> 2541 | L75: =H75-K75 -> 0 | M75: =I75-K75 -> 0 | O75: =IF(OR(AJ75="принят",AJ75="Завершено",AJ75="ПриПро"),I75-K75,H75-K75) -> 0 | P75: 0 | S75: 0 | T75: 0 | U75: 0 | AB75: =IF(AJ75="Принят",(J75/1.18-W75-Z75)*0.1,J75/1.18*0.8*0.1)-AA75 -> 0 | AF75: =IF(OR(I75="",I75=0,N75="",N75=0),"Нет инфо",I75/N75) -> Нет инфо | AG75: =IF(OR(I75="",I75=0,R75="",R75=0),"Нет инфо",I75/R75) -> Нет инфо | AH75: Проектирование | AI75: 45363 | AJ75: ПриПро | AK75: Сакорггаз | AL75: 44677 | AM75: BCP-220426-1/2(1.1.2) | AO75: P.2.401 | AP75: P.2.401
A76: 2105 | B76: Квемо Картли | C76: Болниси | D76: (1.1.2) დაბა კაზრეთის კორპუსების ქსელის რეაბ. და მრიცხველების გამოტანა (P.2.401)კორპ. №97/3 | E76: კორპუსი №97/3 | F76: (Пр)-Интерсервис 2011 | H76: 2506 | I76: 2506 | K76: =382.27+2123.73 -> 2506 | L76: =H76-K76 -> 0 | M76: =I76-K76 -> 0 | O76: =IF(OR(AJ76="принят",AJ76="Завершено",AJ76="ПриПро"),I76-K76,H76-K76) -> 0 | P76: 0 | S76: 0 | T76: 0 | U76: 0 | AB76: =IF(AJ76="Принят",(J76/1.18-W76-Z76)*0.1,J76/1.18*0.8*0.1)-AA76 -> 0 | AF76: =IF(OR(I76="",I76=0,N76="",N76=0),"Нет инфо",I76/N76) -> Нет инфо | AG76: =IF(OR(I76="",I76=0,R76="",R76=0),"Нет инфо",I76/R76) -> Нет инфо | AH76: Проектирование | AI76: 45363 | AJ76: ПриПро | AK76: Сакорггаз | AL76: 44677 | AM76: BCP-220426-1/2(1.1.2) | AO76: P.2.401 | AP76: P.2.401
A77: 2106 | B77: Квемо Картли | C77: Болниси | D77: (1.1.2) დაბა კაზრეთის კორპუსების ქსელის რეაბ. და მრიცხველების გამოტანა (P.2.401)კორპ. №97/4 | E77: კორპუსი №97/4 | F77: (Пр)-Интерсервис 2011 | H77: 2523.5 | I77: 2523.5 | K77: =384.94+2138.56 -> 2523.5 | L77: =H77-K77 -> 0 | M77: =I77-K77 -> 0 | O77: =IF(OR(AJ77="принят",AJ77="Завершено",AJ77="ПриПро"),I77-K77,H77-K77) -> 0 | P77: 0 | S77: 0 | T77: 0 | U77: 0 | AB77: =IF(AJ77="Принят",(J77/1.18-W77-Z77)*0.1,J77/1.18*0.8*0.1)-AA77 -> 0 | AF77: =IF(OR(I77="",I77=0,N77="",N77=0),"Нет инфо",I77/N77) -> Нет инфо | AG77: =IF(OR(I77="",I77=0,R77="",R77=0),"Нет инфо",I77/R77) -> Нет инфо | AH77: Проектирование | AI77: 45363 | AJ77: ПриПро | AK77: Сакорггаз | AL77: 44677 | AM77: BCP-220426-1/2(1.1.2) | AO77: P.2.401 | AP77: P.2.401
A78: 2107 | B78: Квемо Картли | C78: Болниси | D78: (1.1.2) დაბა კაზრეთის კორპუსების ქსელის რეაბ. და მრიცხველების გამოტანა (P.2.401)კორპ. №103/106 | E78: კორპუსი №103/106 | F78: (Пр)-Интерсервис 2011 | H78: 1604.75 | I78: 1604.75 | K78: =244.79+1359.96 -> 1604.75 | L78: =H78-K78 -> 0 | M78: =I78-K78 -> 0 | O78: =IF(OR(AJ78="принят",AJ78="Завершено",AJ78="ПриПро"),I78-K78,H78-K78) -> 0 | P78: 0 | S78: 0 | T78: 0 | U78: 0 | AB78: =IF(AJ78="Принят",(J78/1.18-W78-Z78)*0.1,J78/1.18*0.8*0.1)-AA78 -> 0 | AF78: =IF(OR(I78="",I78=0,N78="",N78=0),"Нет инфо",I78/N78) -> Нет инфо | AG78: =IF(OR(I78="",I78=0,R78="",R78=0),"Нет инфо",I78/R78) -> Нет инфо | AH78: Проектирование | AI78: 45363 | AJ78: ПриПро | AK78: Сакорггаз | AL78: 44677 | AM78: BCP-220426-1/2(1.1.2) | AO78: P.2.401 | AP78: P.2.401
A79: 2108 | B79: Квемо Картли | C79: Болниси | D79: (1.1.2) დაბა კაზრეთის კორპუსების ქსელის რეაბ. და მრიცხველების გამოტანა (P.2.401)კორპ. №107 | E79: კორპუსი №107 | F79: (Пр)-Интерсервис 2011 | H79: 1046.5 | I79: 1046.5 | K79: =159.63+886.87 -> 1046.5 | L79: =H79-K79 -> 0 | M79: =I79-K79 -> 0 | O79: =IF(OR(AJ79="принят",AJ79="Завершено",AJ79="ПриПро"),I79-K79,H79-K79) -> 0 | P79: 0 | S79: 0 | T79: 0 | U79: 0 | AB79: =IF(AJ79="Принят",(J79/1.18-W79-Z79)*0.1,J79/1.18*0.8*0.1)-AA79 -> 0 | AF79: =IF(OR(I79="",I79=0,N79="",N79=0),"Нет инфо",I79/N79) -> Нет инфо | AG79: =IF(OR(I79="",I79=0,R79="",R79=0),"Нет инфо",I79/R79) -> Нет инфо | AH79: Проектирование | AI79: 45363 | AJ79: ПриПро | AK79: Сакорггаз | AL79: 44677 | AM79: BCP-220426-1/2(1.1.2) | AO79: P.2.401 | AP79: P.2.401
A80: 2109 | B80: Квемо Картли | C80: Болниси | D80: (1.1.2) დაბა კაზრეთის კორპუსების ქსელის რეაბ. და მრიცხველების გამოტანა (P.2.401)კორპ. №108 | E80: კორპუსი №108 | F80: (Пр)-Интерсервис 2011 | H80: 1032.5 | I80: 1032.5 | K80: =157.5+875 -> 1032.5 | L80: =H80-K80 -> 0 | M80: =I80-K80 -> 0 | O80: =IF(OR(AJ80="принят",AJ80="Завершено",AJ80="ПриПро"),I80-K80,H80-K80) -> 0 | P80: 0 | S80: 0 | T80: 0 | U80: 0 | AB80: =IF(AJ80="Принят",(J80/1.18-W80-Z80)*0.1,J80/1.18*0.8*0.1)-AA80 -> 0 | AF80: =IF(OR(I80="",I80=0,N80="",N80=0),"Нет инфо",I80/N80) -> Нет инфо | AG80: =IF(OR(I80="",I80=0,R80="",R80=0),"Нет инфо",I80/R80) -> Нет инфо | AH80: Проектирование | AI80: 45363 | AJ80: ПриПро | AK80: Сакорггаз | AL80: 44677 | AM80: BCP-220426-1/2(1.1.2) | AO80: P.2.401 | AP80: P.2.401
A81: 2110 | B81: Квемо Картли | C81: Болниси | D81: (1.1.2) დაბა კაზრეთის კორპუსების ქსელის რეაბ. და მრიცხველების გამოტანა (P.2.401)კორპ. №109 | E81: კორპუსი №109 | F81: (Пр)-Интерсервис 2011 | H81: 1027.25 | I81: 1027.25 | K81: =156.7+870.55 -> 1027.25 | L81: =H81-K81 -> 0 | M81: =I81-K81 -> 0 | O81: =IF(OR(AJ81="принят",AJ81="Завершено",AJ81="ПриПро"),I81-K81,H81-K81) -> 0 | P81: 0 | S81: 0 | T81: 0 | U81: 0 | AB81: =IF(AJ81="Принят",(J81/1.18-W81-Z81)*0.1,J81/1.18*0.8*0.1)-AA81 -> 0 | AF81: =IF(OR(I81="",I81=0,N81="",N81=0),"Нет инфо",I81/N81) -> Нет инфо | AG81: =IF(OR(I81="",I81=0,R81="",R81=0),"Нет инфо",I81/R81) -> Нет инфо | AH81: Проектирование | AI81: 45363 | AJ81: ПриПро | AK81: Сакорггаз | AL81: 44677 | AM81: BCP-220426-1/2(1.1.2) | AO81: P.2.401 | AP81: P.2.401
A82: 2111 | B82: Квемо Картли | C82: Болниси | D82: (1.1.2) დაბა კაზრეთის კორპუსების ქსელის რეაბ. და მრიცხველების გამოტანა (P.2.401)კორპ. №114/115 | E82: კორპუსი №114/115 | F82: (Пр)-Интерсервис 2011 | H82: 1510.25 | I82: 1510.25 | K82: =230.38+1279.87 -> 1510.25 | L82: =H82-K82 -> 0 | M82: =I82-K82 -> 0 | O82: =IF(OR(AJ82="принят",AJ82="Завершено",AJ82="ПриПро"),I82-K82,H82-K82) -> 0 | P82: 0 | S82: 0 | T82: 0 | U82: 0 | AB82: =IF(AJ82="Принят",(J82/1.18-W82-Z82)*0.1,J82/1.18*0.8*0.1)-AA82 -> 0 | AF82: =IF(OR(I82="",I82=0,N82="",N82=0),"Нет инфо",I82/N82) -> Нет инфо | AG82: =IF(OR(I82="",I82=0,R82="",R82=0),"Нет инфо",I82/R82) -> Нет инфо | AH82: Проектирование | AI82: 45363 | AJ82: ПриПро | AK82: Сакорггаз | AL82: 44677 | AM82: BCP-220426-1/2(1.1.2) | AO82: P.2.401 | AP82: P.2.401
A83: 2112 | B83: Квемо Картли | C83: Болниси | D83: (1.1.2) დაბა კაზრეთის კორპუსების ქსელის რეაბ. და მრიცხველების გამოტანა (P.2.401)კორპ. №118/119 | E83: კორპუსი №118/119 | F83: (Пр)-Интерсервис 2011 | H83: 1463 | I83: 1463 | K83: =223.17+1239.83 -> 1463 | L83: =H83-K83 -> 0 | M83: =I83-K83 -> 0 | O83: =IF(OR(AJ83="принят",AJ83="Завершено",AJ83="ПриПро"),I83-K83,H83-K83) -> 0 | P83: 0 | S83: 0 | T83: 0 | U83: 0 | AB83: =IF(AJ83="Принят",(J83/1.18-W83-Z83)*0.1,J83/1.18*0.8*0.1)-AA83 -> 0 | AF83: =IF(OR(I83="",I83=0,N83="",N83=0),"Нет инфо",I83/N83) -> Нет инфо | AG83: =IF(OR(I83="",I83=0,R83="",R83=0),"Нет инфо",I83/R83) -> Нет инфо | AH83: Проектирование | AI83: 45363 | AJ83: ПриПро | AK83: Сакорггаз | AL83: 44677 | AM83: BCP-220426-1/2(1.1.2) | AO83: P.2.401 | AP83: P.2.401
A84: 2113 | B84: Квемо Картли | C84: Болниси | D84: (1.1.2) დაბა კაზრეთის კორპუსების ქსელის რეაბ. და მრიცხველების გამოტანა (P.2.401)კორპ. №126/1 | E84: კორპუსი №126/1 | F84: (Пр)-Интерсервис 2011 | H84: 3197.25 | I84: 3197.25 | K84: =487.72+2709.53 -> 3197.25 | L84: =H84-K84 -> 0 | M84: =I84-K84 -> 0 | O84: =IF(OR(AJ84="принят",AJ84="Завершено",AJ84="ПриПро"),I84-K84,H84-K84) -> 0 | P84: 0 | S84: 0 | T84: 0 | U84: 0 | AB84: =IF(AJ84="Принят",(J84/1.18-W84-Z84)*0.1,J84/1.18*0.8*0.1)-AA84 -> 0 | AF84: =IF(OR(I84="",I84=0,N84="",N84=0),"Нет инфо",I84/N84) -> Нет инфо | AG84: =IF(OR(I84="",I84=0,R84="",R84=0),"Нет инфо",I84/R84) -> Нет инфо | AH84: Проектирование | AI84: 45363 | AJ84: ПриПро | AK84: Сакорггаз | AL84: 44677 | AM84: BCP-220426-1/2(1.1.2) | AO84: P.2.401 | AP84: P.2.401
A85: 2114 | B85: Квемо Картли | C85: Болниси | D85: (1.1.2) დაბა კაზრეთის კორპუსების ქსელის რეაბ. და მრიცხველების გამოტანა (P.2.401)კორპ. №126/2 | E85: კორპუსი №126/2 | F85: (Пр)-Интерсервис 2011 | H85: 3704.75 | I85: 3704.75 | K85: =565.13+3139.62 -> 3704.75 | L85: =H85-K85 -> 0 | M85: =I85-K85 -> 0 | O85: =IF(OR(AJ85="принят",AJ85="Завершено",AJ85="ПриПро"),I85-K85,H85-K85) -> 0 | P85: 0 | S85: 0 | T85: 0 | U85: 0 | AB85: =IF(AJ85="Принят",(J85/1.18-W85-Z85)*0.1,J85/1.18*0.8*0.1)-AA85 -> 0 | AF85: =IF(OR(I85="",I85=0,N85="",N85=0),"Нет инфо",I85/N85) -> Нет инфо | AG85: =IF(OR(I85="",I85=0,R85="",R85=0),"Нет инфо",I85/R85) -> Нет инфо | AH85: Проектирование | AI85: 45363 | AJ85: ПриПро | AK85: Сакорггаз | AL85: 44677 | AM85: BCP-220426-1/2(1.1.2) | AO85: P.2.401 | AP85: P.2.401
A86: 2115 | B86: Квемо Картли | C86: Болниси | D86: (1.1.2) დაბა კაზრეთის კორპუსების ქსელის რეაბ. და მრიცხველების გამოტანა (P.2.401)კორპ. №154 | E86: კორპუსი №154 | F86: (Пр)-Интерсервис 2011 | H86: 1064 | I86: 1064 | K86: =162.3+901.7 -> 1064 | L86: =H86-K86 -> 0 | M86: =I86-K86 -> 0 | O86: =IF(OR(AJ86="принят",AJ86="Завершено",AJ86="ПриПро"),I86-K86,H86-K86) -> 0 | P86: 0 | S86: 0 | T86: 0 | U86: 0 | AB86: =IF(AJ86="Принят",(J86/1.18-W86-Z86)*0.1,J86/1.18*0.8*0.1)-AA86 -> 0 | AF86: =IF(OR(I86="",I86=0,N86="",N86=0),"Нет инфо",I86/N86) -> Нет инфо | AG86: =IF(OR(I86="",I86=0,R86="",R86=0),"Нет инфо",I86/R86) -> Нет инфо | AH86: Проектирование | AI86: 45363 | AJ86: ПриПро | AK86: Сакорггаз | AL86: 44677 | AM86: BCP-220426-1/2(1.1.2) | AO86: P.2.401 | AP86: P.2.401
A87: 2116 | B87: Квемо Картли | C87: Болниси | D87: (1.1.2) დაბა კაზრეთის კორპუსების ქსელის რეაბ. და მრიცხველების გამოტანა (P.2.401)კორპ. №155 | E87: კორპუსი №155 | F87: (Пр)-Интерсервис 2011 | H87: 1016.75 | I87: 1016.75 | K87: =155.1+861.65 -> 1016.75 | L87: =H87-K87 -> 0 | M87: =I87-K87 -> 0 | O87: =IF(OR(AJ87="принят",AJ87="Завершено",AJ87="ПриПро"),I87-K87,H87-K87) -> 0 | P87: 0 | S87: 0 | T87: 0 | U87: 0 | AB87: =IF(AJ87="Принят",(J87/1.18-W87-Z87)*0.1,J87/1.18*0.8*0.1)-AA87 -> 0 | AF87: =IF(OR(I87="",I87=0,N87="",N87=0),"Нет инфо",I87/N87) -> Нет инфо | AG87: =IF(OR(I87="",I87=0,R87="",R87=0),"Нет инфо",I87/R87) -> Нет инфо | AH87: Проектирование | AI87: 45363 | AJ87: ПриПро | AK87: Сакорггаз | AL87: 44677 | AM87: BCP-220426-1/2(1.1.2) | AO87: P.2.401 | AP87: P.2.401
A88: 2117 | B88: Квемо Картли | C88: Болниси | D88: (1.1.2) დაბა კაზრეთის კორპუსების ქსელის რეაბ. და მრიცხველების გამოტანა (P.2.401)კორპ. №156 | E88: კორპუსი №156 | F88: (Пр)-Интерсервис 2011 | H88: 1043 | I88: 1043 | K88: =159.1+883.9 -> 1043 | L88: =H88-K88 -> 0 | M88: =I88-K88 -> 0 | O88: =IF(OR(AJ88="принят",AJ88="Завершено",AJ88="ПриПро"),I88-K88,H88-K88) -> 0 | P88: 0 | S88: 0 | T88: 0 | U88: 0 | AB88: =IF(AJ88="Принят",(J88/1.18-W88-Z88)*0.1,J88/1.18*0.8*0.1)-AA88 -> 0 | AF88: =IF(OR(I88="",I88=0,N88="",N88=0),"Нет инфо",I88/N88) -> Нет инфо | AG88: =IF(OR(I88="",I88=0,R88="",R88=0),"Нет инфо",I88/R88) -> Нет инфо | AH88: Проектирование | AI88: 45363 | AJ88: ПриПро | AK88: Сакорггаз | AL88: 44677 | AM88: BCP-220426-1/2(1.1.2) | AO88: P.2.401 | AP88: P.2.401
A89: 2118 | B89: Квемо Картли | C89: Болниси | D89: (1.1.2) დაბა კაზრეთის კორპუსების ქსელის რეაბ. და მრიცხველების გამოტანა (P.2.401)კორპ. №157 | E89: კორპუსი №157 | F89: (Пр)-Интерсервис 2011 | H89: 1055.25 | I89: 1055.25 | K89: =160.97+894.28 -> 1055.25 | L89: =H89-K89 -> 0 | M89: =I89-K89 -> 0 | O89: =IF(OR(AJ89="принят",AJ89="Завершено",AJ89="ПриПро"),I89-K89,H89-K89) -> 0 | P89: 0 | S89: 0 | T89: 0 | U89: 0 | AB89: =IF(AJ89="Принят",(J89/1.18-W89-Z89)*0.1,J89/1.18*0.8*0.1)-AA89 -> 0 | AF89: =IF(OR(I89="",I89=0,N89="",N89=0),"Нет инфо",I89/N89) -> Нет инфо | AG89: =IF(OR(I89="",I89=0,R89="",R89=0),"Нет инфо",I89/R89) -> Нет инфо | AH89: Проектирование | AI89: 45363 | AJ89: ПриПро | AK89: Сакорггаз | AL89: 44677 | AM89: BCP-220426-1/2(1.1.2) | AO89: P.2.401 | AP89: P.2.401
A90: 2119 | B90: Квемо Картли | C90: Рустави | D90: (10) გამოტანილი მრიცხველების პოლიეთილენის მილების შეცვლა რკინის მილებით P.2.721 (მე-7-ე მკრ. №10 კორპ) | E90: მე-7-ე მკრ. №10 კორპ | F90: Интерсервис 2011 | G90: 721 | H90: =1365+50000+2000+17200 -> 70565 | I90: =1365+50000+2000+17200 -> 70565 | J90: =I90-1365 -> 69200 | K90: =208.22+7627.12+V90+305.08+2623.73+15733.05 -> 70565 | L90: =H90-K90 -> 0 | M90: =I90-K90 -> 0 | N90: 818 | O90: =IF(OR(AJ90="принят",AJ90="Завершено",AJ90="ПриПро"),I90-K90,H90-K90) -> 0 | P90: 0 | S90: 0 | T90: 0 | U90: 0 | V90: =42372.88+1694.92 -> 44067.8 | W90: =2699.09+84.84 -> 2783.93 | AA90: =IF(AJ90="Принят",(J90/1.18-W90-Z90)*0.1,J90/1.18*0.8*0.1) -> 5586.0138 | AB90: =IF(AJ90="Принят",(J90/1.18-W90-Z90)*0.1,J90/1.18*0.8*0.1)-AA90 -> 0 | AF90: =IF(OR(I90="",I90=0,N90="",N90=0),"Нет инфо",I90/N90) -> 86.265281 | AG90: =IF(OR(I90="",I90=0,R90="",R90=0),"Нет инфо",I90/R90) -> Нет инфо | AH90: Реаб. | AI90: 45380 | AJ90: Принят | AK90: Сакорггаз | AL90: 44570 | AM90: BCG-230109-1/0(10) | AO90: P.2.721 | AP90: P.2.721
A91: 2120 | B91: Квемо Картли | C91: Рустави | D91: (2) გამოტანილი მრიცხველების პოლიეთილენის მილების შეცვლა რკინის მილებით P.2.744 (ჯავახიშვილის ქ. №1 კორპ) | E91: ჯავახიშვილის ქ. №1 კორპ | F91: Интерсервис 2011 | G91: 744 | H91: =1274+30000+2731 -> 34005 | I91: =1274+30000+2731 -> 34005 | J91: =I91-1274 -> 32731 | K91: =194.34+V91+4576.27+416.59+3394.07 -> 34005 | L91: =H91-K91 -> 0 | M91: =I91-K91 -> 0 | N91: 388 | O91: =IF(OR(AJ91="принят",AJ91="Завершено",AJ91="ПриПро"),I91-K91,H91-K91) -> 0 | P91: 0 | S91: 0 | T91: 0 | U91: 0 | V91: 25423.73 | W91: 1272.58 | AA91: =IF(AJ91="Принят",(J91/1.18-W91-Z91)*0.1,J91/1.18*0.8*0.1) -> 2646.5556 | AB91: =IF(AJ91="Принят",(J91/1.18-W91-Z91)*0.1,J91/1.18*0.8*0.1)-AA91 -> 0 | AF91: =IF(OR(I91="",I91=0,N91="",N91=0),"Нет инфо",I91/N91) -> 87.641753 | AG91: =IF(OR(I91="",I91=0,R91="",R91=0),"Нет инфо",I91/R91) -> Нет инфо | AH91: Реаб. | AI91: 45380 | AJ91: Принят | AK91: Сакорггаз | AL91: 44935 | AM91: BCG-230109-1/0(2) | AO91: P.2.744 | AP91: P.2.744
A92: 2121 | B92: Квемо Картли | C92: Рустави | D92: (1) გამოსატანი მრიცხველების გამოტანა (P.2.647) (მე-12-ე მკრ. № 2 კორპ) | E92: მე-12-ე მკრ. № 2 კორპ | F92: (Пр)-Интерсервис 2011 | G92: 647 | H92: 952 | I92: 952 | K92: =145.22+806.78 -> 952 | L92: =H92-K92 -> 0 | M92: =I92-K92 -> 0 | O92: =IF(OR(AJ92="принят",AJ92="Завершено",AJ92="ПриПро"),I92-K92,H92-K92) -> 0 | P92: 0 | S92: 0 | T92: 0 | U92: 0 | AB92: =IF(AJ92="Принят",(J92/1.18-W92-Z92)*0.1,J92/1.18*0.8*0.1)-AA92 -> 0 | AF92: =IF(OR(I92="",I92=0,N92="",N92=0),"Нет инфо",I92/N92) -> Нет инфо | AG92: =IF(OR(I92="",I92=0,R92="",R92=0),"Нет инфо",I92/R92) -> Нет инфо | AH92: Проектирование | AI92: 45405 | AJ92: ПриПро | AK92: Сакорггаз | AL92: 45309 | AM92: CC-240118-1/0 (1) | AO92: P.2.647 | AP92: P.2.647
A93: 2122 | B93: Квемо Картли | C93: Рустави | D93: (1) გამოსატანი მრიცხველების გამოტანა (P.2.647) (მე-12-ე მკრ. № 3 კორპ) | E93: მე-12-ე მკრ. № 3 კორპ | F93: (Пр)-Интерсервис 2011 | G93: 647 | H93: 1879.5 | I93: 1879.5 | K93: =286.7+1592.8 -> 1879.5 | L93: =H93-K93 -> 0 | M93: =I93-K93 -> 0 | O93: =IF(OR(AJ93="принят",AJ93="Завершено",AJ93="ПриПро"),I93-K93,H93-K93) -> 0 | P93: 0 | S93: 0 | T93: 0 | U93: 0 | AB93: =IF(AJ93="Принят",(J93/1.18-W93-Z93)*0.1,J93/1.18*0.8*0.1)-AA93 -> 0 | AF93: =IF(OR(I93="",I93=0,N93="",N93=0),"Нет инфо",I93/N93) -> Нет инфо | AG93: =IF(OR(I93="",I93=0,R93="",R93=0),"Нет инфо",I93/R93) -> Нет инфо | AH93: Проектирование | AI93: 45405 | AJ93: ПриПро | AK93: Сакорггаз | AL93: 45309 | AM93: CC-240118-1/0 (1) | AO93: P.2.647 | AP93: P.2.647
A94: 2123 | B94: Квемо Картли | C94: Рустави | D94: (1) გამოსატანი მრიცხველების გამოტანა (P.2.647) (მე-12-ე მკრ. № 4 კორპ) | E94: მე-12-ე მკრ. № 4 კორპ | F94: (Пр)-Интерсервис 2011 | G94: 647 | H94: 1874.25 | I94: 1874.25 | K94: =285.9+1588.35 -> 1874.25 | L94: =H94-K94 -> 0 | M94: =I94-K94 -> 0 | O94: =IF(OR(AJ94="принят",AJ94="Завершено",AJ94="ПриПро"),I94-K94,H94-K94) -> 0 | P94: 0 | S94: 0 | T94: 0 | U94: 0 | AB94: =IF(AJ94="Принят",(J94/1.18-W94-Z94)*0.1,J94/1.18*0.8*0.1)-AA94 -> 0 | AF94: =IF(OR(I94="",I94=0,N94="",N94=0),"Нет инфо",I94/N94) -> Нет инфо | AG94: =IF(OR(I94="",I94=0,R94="",R94=0),"Нет инфо",I94/R94) -> Нет инфо | AH94: Проектирование | AI94: 45405 | AJ94: ПриПро | AK94: Сакорггаз | AL94: 45309 | AM94: CC-240118-1/0 (1) | AO94: P.2.647 | AP94: P.2.647
A95: 2124 | B95: Квемо Картли | C95: Рустави | D95: (1) გამოსატანი მრიცხველების გამოტანა (P.2.647) (მე-12-ე მკრ. № 6 კორპ) | E95: მე-12-ე მკრ. № 6 კორპ | F95: (Пр)-Интерсервис 2011 | G95: 647 | H95: 2264.5 | I95: 2264.5 | K95: =345.43+1919.07 -> 2264.5 | L95: =H95-K95 -> 0 | M95: =I95-K95 -> 0 | O95: =IF(OR(AJ95="принят",AJ95="Завершено",AJ95="ПриПро"),I95-K95,H95-K95) -> 0 | P95: 0 | S95: 0 | T95: 0 | U95: 0 | AB95: =IF(AJ95="Принят",(J95/1.18-W95-Z95)*0.1,J95/1.18*0.8*0.1)-AA95 -> 0 | AF95: =IF(OR(I95="",I95=0,N95="",N95=0),"Нет инфо",I95/N95) -> Нет инфо | AG95: =IF(OR(I95="",I95=0,R95="",R95=0),"Нет инфо",I95/R95) -> Нет инфо | AH95: Проектирование | AI95: 45405 | AJ95: ПриПро | AK95: Сакорггаз | AL95: 45309 | AM95: CC-240118-1/0 (1) | AO95: P.2.647 | AP95: P.2.647
A96: 2125 | B96: Квемо Картли | C96: Рустави | D96: (1) გამოსატანი მრიცხველების გამოტანა (P.2.647) (მე-7-ე მკრ. № 18 კორპ) | E96: მე-7-ე მკრ. № 18 კორპ | F96: (Пр)-Интерсервис 2011 | G96: 647 | H96: 999.25 | I96: 999.25 | K96: =152.43+846.82 -> 999.25 | L96: =H96-K96 -> 0 | M96: =I96-K96 -> 0 | O96: =IF(OR(AJ96="принят",AJ96="Завершено",AJ96="ПриПро"),I96-K96,H96-K96) -> 0 | P96: 0 | S96: 0 | T96: 0 | U96: 0 | AB96: =IF(AJ96="Принят",(J96/1.18-W96-Z96)*0.1,J96/1.18*0.8*0.1)-AA96 -> 0 | AF96: =IF(OR(I96="",I96=0,N96="",N96=0),"Нет инфо",I96/N96) -> Нет инфо | AG96: =IF(OR(I96="",I96=0,R96="",R96=0),"Нет инфо",I96/R96) -> Нет инфо | AH96: Проектирование | AI96: 45405 | AJ96: ПриПро | AK96: Сакорггаз | AL96: 45309 | AM96: CC-240118-1/0 (1) | AO96: P.2.647 | AP96: P.2.647
A97: 2126 | B97: Квемо Картли | C97: Рустави | D97: (1) გამოსატანი მრიცხველების გამოტანა (P.2.647) (მე-7-ე მკრ. № 19 კორპ) | E97: მე-7-ე მკრ. № 19 კორპ | F97: (Пр)-Интерсервис 2011 | G97: 647 | H97: 892.5 | I97: 892.5 | K97: =136.14+756.36 -> 892.5 | L97: =H97-K97 -> 0 | M97: =I97-K97 -> 0 | O97: =IF(OR(AJ97="принят",AJ97="Завершено",AJ97="ПриПро"),I97-K97,H97-K97) -> 0 | P97: 0 | S97: 0 | T97: 0 | U97: 0 | AB97: =IF(AJ97="Принят",(J97/1.18-W97-Z97)*0.1,J97/1.18*0.8*0.1)-AA97 -> 0 | AF97: =IF(OR(I97="",I97=0,N97="",N97=0),"Нет инфо",I97/N97) -> Нет инфо | AG97: =IF(OR(I97="",I97=0,R97="",R97=0),"Нет инфо",I97/R97) -> Нет инфо | AH97: Проектирование | AI97: 45405 | AJ97: ПриПро | AK97: Сакорггаз | AL97: 45309 | AM97: CC-240118-1/0 (1) | AO97: P.2.647 | AP97: P.2.647
A98: 2127 | B98: Квемо Картли | C98: Рустави | D98: (1) გამოსატანი მრიცხველების გამოტანა (P.2.647) (მე-7-ე მკრ. № 27 კორპ) | E98: მე-7-ე მკრ. № 27 კორპ | F98: (Пр)-Интерсервис 2011 | G98: 647 | H98: 2695 | I98: 2695 | K98: =411.1+2283.9 -> 2695 | L98: =H98-K98 -> 0 | M98: =I98-K98 -> 0 | O98: =IF(OR(AJ98="принят",AJ98="Завершено",AJ98="ПриПро"),I98-K98,H98-K98) -> 0 | P98: 0 | S98: 0 | T98: 0 | U98: 0 | AB98: =IF(AJ98="Принят",(J98/1.18-W98-Z98)*0.1,J98/1.18*0.8*0.1)-AA98 -> 0 | AF98: =IF(OR(I98="",I98=0,N98="",N98=0),"Нет инфо",I98/N98) -> Нет инфо | AG98: =IF(OR(I98="",I98=0,R98="",R98=0),"Нет инфо",I98/R98) -> Нет инфо | AH98: Проектирование | AI98: 45405 | AJ98: ПриПро | AK98: Сакорггаз | AL98: 45309 | AM98: CC-240118-1/0 (1) | AO98: P.2.647 | AP98: P.2.647
A99: 2128 | B99: Квемо Картли | C99: Рустави | D99: (1) გამოსატანი მრიცხველების გამოტანა (P.2.647) (მე-21-ე მკრ. № 6 კორპ) | E99: მე-21-ე მკრ. № 6 კორპ | F99: (Пр)-Интерсервис 2011 | G99: 647 | H99: 5166 | I99: 5166 | K99: =788.034+4377.966 -> 5166 | L99: =H99-K99 -> 0 | M99: =I99-K99 -> 0 | O99: =IF(OR(AJ99="принят",AJ99="Завершено",AJ99="ПриПро"),I99-K99,H99-K99) -> 0 | P99: 0 | S99: 0 | T99: 0 | U99: 0 | AB99: =IF(AJ99="Принят",(J99/1.18-W99-Z99)*0.1,J99/1.18*0.8*0.1)-AA99 -> 0 | AF99: =IF(OR(I99="",I99=0,N99="",N99=0),"Нет инфо",I99/N99) -> Нет инфо | AG99: =IF(OR(I99="",I99=0,R99="",R99=0),"Нет инфо",I99/R99) -> Нет инфо | AH99: Проектирование | AI99: 45405 | AJ99: ПриПро | AK99: Сакорггаз | AL99: 45309 | AM99: CC-240118-1/0 (1) | AO99: P.2.647 | AP99: P.2.647
A100: 2129 | B100: Квемо Картли | C100: Рустави | D100: (1) გამოსატანი მრიცხველების გამოტანა (P.2.647) (მე-21-ე მკრ. № 9 კორპ) | E100: მე-21-ე მკრ. № 9 კორპ | F100: (Пр)-Интерсервис 2011 | G100: 647 | H100: 2681 | I100: 2681 | K100: =408.97+2272.03 -> 2681 | L100: =H100-K100 -> 0 | M100: =I100-K100 -> 0 | O100: =IF(OR(AJ100="принят",AJ100="Завершено",AJ100="ПриПро"),I100-K100,H100-K100) -> 0 | P100: 0 | S100: 0 | T100: 0 | U100: 0 | AB100: =IF(AJ100="Принят",(J100/1.18-W100-Z100)*0.1,J100/1.18*0.8*0.1)-AA100 -> 0 | AF100: =IF(OR(I100="",I100=0,N100="",N100=0),"Нет инфо",I100/N100) -> Нет инфо | AG100: =IF(OR(I100="",I100=0,R100="",R100=0),"Нет инфо",I100/R100) -> Нет инфо | AH100: Проектирование | AI100: 45405 | AJ100: ПриПро | AK100: Сакорггаз | AL100: 45309 | AM100: CC-240118-1/0 (1) | AO100: P.2.647 | AP100: P.2.647
A101: 2130 | B101: Квемо Картли | C101: Рустави | D101: (1) გამოსატანი მრიცხველების გამოტანა (P.2.647) (რუსთაველის ქუჩა №50 კორპ) | E101: რუსთაველის ქუჩა №50 კორპ | F101: (Пр)-Интерсервис 2011 | G101: 647 | H101: 444.5 | I101: 444.5 | K101: =67.81+376.69 -> 444.5 | L101: =H101-K101 -> 0 | M101: =I101-K101 -> 0 | O101: =IF(OR(AJ101="принят",AJ101="Завершено",AJ101="ПриПро"),I101-K101,H101-K101) -> 0 | P101: 0 | S101: 0 | T101: 0 | U101: 0 | AB101: =IF(AJ101="Принят",(J101/1.18-W101-Z101)*0.1,J101/1.18*0.8*0.1)-AA101 -> 0 | AF101: =IF(OR(I101="",I101=0,N101="",N101=0),"Нет инфо",I101/N101) -> Нет инфо | AG101: =IF(OR(I101="",I101=0,R101="",R101=0),"Нет инфо",I101/R101) -> Нет инфо | AH101: Проектирование | AI101: 45405 | AJ101: ПриПро | AK101: Сакорггаз | AL101: 45309 | AM101: CC-240118-1/0 (1) | AO101: P.2.647 | AP101: P.2.647
A102: 2131 | B102: Квемо Картли | C102: Рустави | D102: (1) გამოსატანი მრიცხველების გამოტანა (P.2.647) (რუსთაველის ქუჩა №52 კორპ) | E102: რუსთაველის ქუჩა №52 კორპ | F102: (Пр)-Интерсервис 2011 | G102: 647 | H102: 598.5 | I102: 598.5 | K102: =91.3+507.2 -> 598.5 | L102: =H102-K102 -> 0 | M102: =I102-K102 -> 0 | O102: =IF(OR(AJ102="принят",AJ102="Завершено",AJ102="ПриПро"),I102-K102,H102-K102) -> 0 | P102: 0 | S102: 0 | T102: 0 | U102: 0 | AB102: =IF(AJ102="Принят",(J102/1.18-W102-Z102)*0.1,J102/1.18*0.8*0.1)-AA102 -> 0 | AF102: =IF(OR(I102="",I102=0,N102="",N102=0),"Нет инфо",I102/N102) -> Нет инфо | AG102: =IF(OR(I102="",I102=0,R102="",R102=0),"Нет инфо",I102/R102) -> Нет инфо | AH102: Проектирование | AI102: 45405 | AJ102: ПриПро | AK102: Сакорггаз | AL102: 45309 | AM102: CC-240118-1/0 (1) | AO102: P.2.647 | AP102: P.2.647
A103: 2132 | B103: Квемо Картли | C103: Рустави | D103: (1) გამოსატანი მრიცხველების გამოტანა (P.2.647) (მესხიშვილის ქუჩა №5 კორპ) | E103: მესხიშვილის ქუჩა №5 კორპ | F103: (Пр)-Интерсервис 2011 | G103: 647 | H103: 1606.5 | I103: 1606.5 | K103: =245.06+1361.44 -> 1606.5 | L103: =H103-K103 -> 0 | M103: =I103-K103 -> 0 | O103: =IF(OR(AJ103="принят",AJ103="Завершено",AJ103="ПриПро"),I103-K103,H103-K103) -> 0 | P103: 0 | S103: 0 | T103: 0 | U103: 0 | AB103: =IF(AJ103="Принят",(J103/1.18-W103-Z103)*0.1,J103/1.18*0.8*0.1)-AA103 -> 0 | AF103: =IF(OR(I103="",I103=0,N103="",N103=0),"Нет инфо",I103/N103) -> Нет инфо | AG103: =IF(OR(I103="",I103=0,R103="",R103=0),"Нет инфо",I103/R103) -> Нет инфо | AH103: Проектирование | AI103: 45405 | AJ103: ПриПро | AK103: Сакорггаз | AL103: 45309 | AM103: CC-240118-1/0 (1) | AO103: P.2.647 | AP103: P.2.647
A104: 2133 | B104: Квемо Картли | C104: Рустави | D104: (1) გამოსატანი მრიცხველების გამოტანა (P.2.647) (მესხიშვილის ქუჩა №9 კორპ) | E104: მესხიშვილის ქუჩა №9 კორპ | F104: (Пр)-Интерсервис 2011 | G104: 647 | H104: 2541 | I104: 2541 | K104: =387.61+2153.39 -> 2541 | L104: =H104-K104 -> 0 | M104: =I104-K104 -> 0 | O104: =IF(OR(AJ104="принят",AJ104="Завершено",AJ104="ПриПро"),I104-K104,H104-K104) -> 0 | P104: 0 | S104: 0 | T104: 0 | U104: 0 | AB104: =IF(AJ104="Принят",(J104/1.18-W104-Z104)*0.1,J104/1.18*0.8*0.1)-AA104 -> 0 | AF104: =IF(OR(I104="",I104=0,N104="",N104=0),"Нет инфо",I104/N104) -> Нет инфо | AG104: =IF(OR(I104="",I104=0,R104="",R104=0),"Нет инфо",I104/R104) -> Нет инфо | AH104: Проектирование | AI104: 45405 | AJ104: ПриПро | AK104: Сакорггаз | AL104: 45309 | AM104: CC-240118-1/0 (1) | AO104: P.2.647 | AP104: P.2.647
A105: 2134 | B105: Квемо Картли | C105: Рустави | D105: (1) გამოსატანი მრიცხველების გამოტანა (P.2.647) (მესხიშვილის ქუჩა №11 კორპ) | E105: მესხიშვილის ქუჩა №11 კორპ | F105: (Пр)-Интерсервис 2011 | G105: 647 | H105: 1701 | I105: 1701 | K105: =259.47+1441.53 -> 1701 | L105: =H105-K105 -> 0 | M105: =I105-K105 -> 0 | O105: =IF(OR(AJ105="принят",AJ105="Завершено",AJ105="ПриПро"),I105-K105,H105-K105) -> 0 | P105: 0 | S105: 0 | T105: 0 | U105: 0 | AB105: =IF(AJ105="Принят",(J105/1.18-W105-Z105)*0.1,J105/1.18*0.8*0.1)-AA105 -> 0 | AF105: =IF(OR(I105="",I105=0,N105="",N105=0),"Нет инфо",I105/N105) -> Нет инфо | AG105: =IF(OR(I105="",I105=0,R105="",R105=0),"Нет инфо",I105/R105) -> Нет инфо | AH105: Проектирование | AI105: 45405 | AJ105: ПриПро | AK105: Сакорггаз | AL105: 45309 | AM105: CC-240118-1/0 (1) | AO105: P.2.647 | AP105: P.2.647
A106: 2135 | B106: Квемо Картли | C106: Рустави | D106: (1) გამოსატანი მრიცხველების გამოტანა (P.2.647) (მესხიშვილის ქუჩა №13 კორპ) | E106: მესხიშვილის ქუჩა №13 კორპ | F106: (Пр)-Интерсервис 2011 | G106: 647 | H106: 1743 | I106: 1743 | K106: =265.88+1477.12 -> 1743 | L106: =H106-K106 -> 0 | M106: =I106-K106 -> 0 | O106: =IF(OR(AJ106="принят",AJ106="Завершено",AJ106="ПриПро"),I106-K106,H106-K106) -> 0 | P106: 0 | S106: 0 | T106: 0 | U106: 0 | AB106: =IF(AJ106="Принят",(J106/1.18-W106-Z106)*0.1,J106/1.18*0.8*0.1)-AA106 -> 0 | AF106: =IF(OR(I106="",I106=0,N106="",N106=0),"Нет инфо",I106/N106) -> Нет инфо | AG106: =IF(OR(I106="",I106=0,R106="",R106=0),"Нет инфо",I106/R106) -> Нет инфо | AH106: Проектирование | AI106: 45405 | AJ106: ПриПро | AK106: Сакорггаз | AL106: 45309 | AM106: CC-240118-1/0 (1) | AO106: P.2.647 | AP106: P.2.647
A107: 2136 | B107: Квемо Картли | C107: Рустави | D107: (1) გამოსატანი მრიცხველების გამოტანა (P.2.647) (თოდრიას ქუჩა №9 კორპ) | E107: თოდრიას ქუჩა №9 კორპ | F107: (Пр)-Интерсервис 2011 | G107: 647 | H107: 1764 | I107: 1764 | K107: =269.09+1494.91 -> 1764 | L107: =H107-K107 -> 0 | M107: =I107-K107 -> 0 | O107: =IF(OR(AJ107="принят",AJ107="Завершено",AJ107="ПриПро"),I107-K107,H107-K107) -> 0 | P107: 0 | S107: 0 | T107: 0 | U107: 0 | AB107: =IF(AJ107="Принят",(J107/1.18-W107-Z107)*0.1,J107/1.18*0.8*0.1)-AA107 -> 0 | AF107: =IF(OR(I107="",I107=0,N107="",N107=0),"Нет инфо",I107/N107) -> Нет инфо | AG107: =IF(OR(I107="",I107=0,R107="",R107=0),"Нет инфо",I107/R107) -> Нет инфо | AH107: Проектирование | AI107: 45405 | AJ107: ПриПро | AK107: Сакорггаз | AL107: 45309 | AM107: CC-240118-1/0 (1) | AO107: P.2.647 | AP107: P.2.647
...

Sheet ндс 2022
B1: НДС 2022 год | J1: 48646 | N1: 527 | O1: =N1-N2 -> -61605.6 | P1: 66
F2: =SUBTOTAL(3,F5:F446) -> 341 | G2: =SUBTOTAL(9,G5:G446) -> 46018209 | H2: =SUBTOTAL(9,H5:H446) -> 7019726.8 | I2: =SUBTOTAL(9,I5:I446) -> 457936.52 | J2: =J1-G2 -> -45969563 | K2: =SUBTOTAL(3,K5:K446) -> 148 | L2: =SUBTOTAL(9,L5:L446) -> 540365.09 | M2: =SUBTOTAL(9,M5:M446) -> 29626.655 | N2: =SUBTOTAL(9,N5:N446) -> 62132.6 | O2: =SUBTOTAL(9,O5:O446) -> 3711 | P2: =P1-O2 -> -3645
B3: № договора | C3: Район | D3: Наименование обьекта | E3: Организация | F3: Месяц сдачи | G3: Сумма под ндс | H3: НДС | J3: Компания | L3: სრული თანხა | M3: ფაქტორინგი | N3: სიგრძე | O3: გადაცემული მრიცხ. რაო-ბა | P3: 1 მეტრის ღირებ. | Q3: 1 მრიცხ. ღირებ. | R3: მშენებლობა 1C-ში | S3: პროექტი 1C-ში
B5: BCP-220426-1/0(1.1.7) | C5: Рустави | D5: 1.1.7. В г. Рустави замена полиэтиленовых труб на фасадах корпусов (I и II этап). (P.2.72 (1 и 2)) (проектирование и строительство) | E5: Интерсервис 2011 | F5: Август | G5: 42500 | H5: =G5-G5/1.18 -> 6483.0508 | I5: =G5-H5 -> 36016.949 | J5: Сакорггаз | K5: VI მ/რ V კორპუსში მრიცხველების გამოტანა | N5: 1250 | O5: 86 | P5: =G5/N5 -> 34 | Q5: დასრულდა
B6: BCP-220426-1/0(1.1.7) | C6: Рустави | D6: 1.1.7. В г. Рустави замена полиэтиленовых труб на фасадах корпусов (I и II этап). (P.2.72 (1 и 2)) (проектирование и строительство) | E6: Интерсервис 2011 | F6: Август | G6: 41000 | H6: =G6-G6/1.18 -> 6254.2373 | J6: Сакорггаз | K6: თოდრიას ქუჩა №15 კორპუსი | N6: 610 | O6: 26 | P6: =G6/N6 -> 67.213115 | Q6: დასრულდა
B7: BCP-220426-1/0(1.1.7) | C7: Рустави | D7: 1.1.7. В г. Рустави замена полиэтиленовых труб на фасадах корпусов (I и II этап). (P.2.72 (1 и 2)) (проектирование и строительство) | E7: Интерсервис 2011 | F7: Август | G7: 37500 | H7: =G7-G7/1.18 -> 5720.339 | J7: Сакорггаз | K7: თოდრიას ქუჩა №19 კორპუსი | N7: 500 | O7: 20 | P7: =G7/N7 -> 75 | Q7: დასრულდა
B8: BS-220513-2/0 | C8: Дманиси | D8: Село Далари, строиетльство газораспределительной сети (газификация). (P.2.406) | E8: Бриджи | F8: Август | G8: 150622 | H8: =G8-G8/1.18 -> 22976.237 | J8: SGG
B9: BCP-220328-2/0(1.2.1) | C9: Терджола | D9: 1.2.1 Участок Муджирети-Мухура (проектирование и строительство) | E9: Интер Газ | F9: Август | G9: 1800000 | H9: =G9-G9/1.18 -> 274576.27 | J9: Сакорггаз
B10: BCP-220328-1/0(1.2.3) | C10: Вани | D10: 1.2.3 С. Шуагора (проектирование и строительство) | E10: Интер Газ | F10: Август | G10: 600000 | H10: =G10-G10/1.18 -> 91525.424 | J10: Сакорггаз
B11: BCP-220328-1/0(1.2.6) | C11: Вани | D11: 1.2.6 С. Перета (проектирование и строительство) | E11: Интер Газ | F11: Август | G11: 400000 | H11: =G11-G11/1.18 -> 61016.949 | J11: Сакорггаз
B12: BCP-220328-1/0(1.2.1) | C12: Багдати | D12: 1.2.1. С. Рохи (проектирование и строительство) | E12: Интер Газ | F12: Август | G12: 500000 | H12: =G12-G12/1.18 -> 76271.186 | J12: Сакорггаз
B13: BCP-220328-1/0(1.2.2) | C13: Вани | D13: 1.2.2 С. Зеиндари (проектирование и строительство) | E13: Интер Газ | F13: Август | G13: 500000 | H13: =G13-G13/1.18 -> 76271.186 | J13: Сакорггаз
B14: BCP-220328-1/0(1.2.4) | C14: Вани | D14: 1.2.4 С. Гора (проектирование и строительство) | E14: Интер Газ | F14: Август | G14: 600000 | H14: =G14-G14/1.18 -> 91525.424 | J14: Сакорггаз
B15: BCP-220321-1/0(1.1.18) | C15: Кутаиси | D15: 1.1.18. В г. Кутаиси, реаибилитация газопровода по алее Агмашенебели. (P.6.799) | E15: Газсервис | F15: Август | G15: 111332.28 | H15: =G15-G15/1.18 -> 16982.89 | J15: Сакорггаз
B16: BCP-220321-1/0(1.1.10) | C16: Самтредия | D16: 1.1.10. Строительство питающего газопровода Самтредиа - Хони. (P.6.115) | E16: Газсервис | F16: Август | G16: 875000 | H16: =G16-G16/1.18 -> 133474.58 | J16: Сакорггаз
B17: BCP-220425-1/0(1.1.25) | C17: Борджоми | D17: 1.1.25. Замена старых счетчиков G 4 в Сервис/центре Боржоми (I этап). (P.3.42 (1)) | E17: Газ Констракт | F17: Август | G17: 4050 | H17: =G17-G17/1.18 -> 617.79661 | J17: Сакорггаз
B18: BS-220513-2/0 | C18: Дманиси | D18: Село Далари, строиетльство газораспределительной сети (газификация). (P.2.406) | E18: Бриджи | F18: Август | G18: 127276.75 | H18: =G18-G18/1.18 -> 19415.097 | J18: SGG
B19: BSP-211108-1/0 | C19: Адигени | D19: в Абасстумани, строит. сети вместе с Фондом Муниц. Развития (I этап 1.6 км.) | E19: Интер Газ | F19: Апрель | G19: =63700.88+2991.16 -> 66692.04 | H19: =G19-G19/1.18 -> 10173.362 | J19: SGG
B20: BS-211115-1/0 | C20: Тианети | D20: с. Тетрахева | E20: Интерсервис 2011 | F20: Апрель | G20: 110078 | H20: =G20-G20/1.18 -> 16791.559 | J20: SGG
B21: BS-220301-1/0 | C21: Чохатаури | D21: Реаб. Гаопр. На ул. Думбадзе | E21: Унимшени | F21: Апрель | G21: 42187 | H21: =G21-G21/1.18 -> 6435.3051 | J21: SGG
B22: BC-220330-1/0 | C22: Кутаиси | D22: ул. Джибладзе реаб. Газопр. | E22: Газсервис | F22: Апрель | G22: 29579 | H22: =G22-G22/1.18 -> 4512.0508 | J22: Сакорггаз
B23: СC-210203-1/0 | D23: 1.2 Реабилитация газопровода в пос. Абастумани Адигенского Муниципалитета. 1.3 Вынос счётчиков на участках №50-51-52-56 в пос. Бакуриани. 1.4 Реабилитация газопровода Д-200мм. на улице Агмашенебели в пос. Бакуриани. 1.5 Реабилитация газопровода Д-150мм. на улице Триалети в пос. Бакуриани. 1.6 Замена наружных полиэтилиновых газопроводов в корпусах на ул. Руставели и ул. Месхети в Борджоми. 1.7 Вынос счётчиков в. Селе Папа пос. Бакуриани. 1.8 Реабилитация газопровода среднего давления проходящего от сёл Свенети и Бербуки Гориского муниципалитета по ул. Сухишвили г. Гори. 1.9 Реабилитация питающего газопровода от узла учёта до центра с. Меджврисхеви. 1.10 Реабилитация газопровода от с.Тквиави по направлению сёл тирдзниси-Дици. 1.11 Вынос и реабилитация питающнго газопровода в селе Бербуки. 1.12 Вынос-Замена счётчиков в г.Гори, реабилитация сети газопроводов на ул Пушкина, трассе Цхинвали, с. Свенети и с. Тинисхиди. 1.13 Реабилитация газопровода среднего Давления на пересечениях канала мелиорации в г. Гори-17км. По трассе Цхинвали. 1.14 Замена сушествующего стального газопровода на масту центральной железной дороги в г. Гори от 11 участкового узла до поселения Садгури (1 этап) (409.5 лари). 1.15 В г. Гори вынос счётчиков на улицах Тамар Мепе, Беруашвили, Чантурия, Багратиони, Кутаиси и Чочишвили. 1.16 Реабилитация газопровода на ул. Пушкина в г. Гори (1601.25 лари). 1.17 Реабилитация газопровода на ул. Размадзе г. Гори (1513.75 лари). 1.18 Реабилитация газопровода от ооо “ Гори“ до входа села Меджврисхеви (7962.5 лари). 1.19 Реабилитация газопровода в с. Оками Каспского муниципалитета. 1.20 Реабилитация газопровода в с. Перма Каспского муниципалитета. 1.21 Реабилитация газопровода проходящего через ветрозащитной полосы в с. Перма Каспского муниципалитета. 1.22 Реабилитация питающего газопровода от с Перма по направлению Чангилари. 1.23 Реабилитация газопровода на ул. Агмашенебели в г. Каспи. 1.24 Реабилитация газопровода на ул. Тависуплеба в г. Каспи. 1.25 Реабилитация сетей на улицах Мириан Мепе, Леселидзе, Костава, Руставели и Чавчавадзе в г. Каспи. 1.26 Реабилитация газопровода на перекрёстке улиц Агмашенебели и Габашвили в г. Каспи. 1.27 Вынос-замена счётчиков на улицах Церетели, 26 Мая, Шарикашвили, Гурамишвили и Агмашенебели в г. Каспи. | E23: (Пр)-Газ Констракт | F23: Апрель | G23: 1354.5 | H23: =G23-G23/1.18 -> 206.61864 | J23: Сакорггаз
B24: BS-210815-1/0 | C24: Гардабани | D24: Реаб. в селе Вахтангиси, Гардабанского муниципалитета включая замену и вынос счетчиков; | E24: Интерсервис 2011 | F24: Апрель | G24: 64429 | H24: =G24-G24/1.18 -> 9828.1525 | J24: SGG
B25: СC-210203-1/0 | D25: 1.2 Реабилитация газопровода в пос. Абастумани Адигенского Муниципалитета. 1.3 Вынос счётчиков на участках №50-51-52-56 в пос. Бакуриани. 1.4 Реабилитация газопровода Д-200мм. на улице Агмашенебели в пос. Бакуриани. 1.5 Реабилитация газопровода Д-150мм. на улице Триалети в пос. Бакуриани. 1.6 Замена наружных полиэтилиновых газопроводов в корпусах на ул. Руставели и ул. Месхети в Борджоми. 1.7 Вынос счётчиков в. Селе Папа пос. Бакуриани. 1.8 Реабилитация газопровода среднего давления проходящего от сёл Свенети и Бербуки Гориского муниципалитета по ул. Сухишвили г. Гори. 1.9 Реабилитация питающего газопровода от узла учёта до центра с. Меджврисхеви. 1.10 Реабилитация газопровода от с.Тквиави по направлению сёл тирдзниси-Дици. 1.11 Вынос и реабилитация питающнго газопровода в селе Бербуки. 1.12 Вынос-Замена счётчиков в г.Гори, реабилитация сети газопроводов на ул Пушкина, трассе Цхинвали, с. Свенети и с. Тинисхиди. 1.13 Реабилитация газопровода среднего Давления на пересечениях канала мелиорации в г. Гори-17км. По трассе Цхинвали. 1.14 Замена сушествующего стального газопровода на масту центральной железной дороги в г. Гори от 11 участкового узла до поселения Садгури (1 этап) (409.5 лари). 1.15 В г. Гори вынос счётчиков на улицах Тамар Мепе, Беруашвили, Чантурия, Багратиони, Кутаиси и Чочишвили. 1.16 Реабилитация газопровода на ул. Пушкина в г. Гори (1601.25 лари). 1.17 Реабилитация газопровода на ул. Размадзе г. Гори (1513.75 лари). 1.18 Реабилитация газопровода от ооо “ Гори“ до входа села Меджврисхеви (7962.5 лари). 1.19 Реабилитация газопровода в с. Оками Каспского муниципалитета. 1.20 Реабилитация газопровода в с. Перма Каспского муниципалитета. 1.21 Реабилитация газопровода проходящего через ветрозащитной полосы в с. Перма Каспского муниципалитета. 1.22 Реабилитация питающего газопровода от с Перма по направлению Чангилари. 1.23 Реабилитация газопровода на ул. Агмашенебели в г. Каспи. 1.24 Реабилитация газопровода на ул. Тависуплеба в г. Каспи. 1.25 Реабилитация сетей на улицах Мириан Мепе, Леселидзе, Костава, Руставели и Чавчавадзе в г. Каспи. 1.26 Реабилитация газопровода на перекрёстке улиц Агмашенебели и Габашвили в г. Каспи. 1.27 Вынос-замена счётчиков на улицах Церетели, 26 Мая, Шарикашвили, Гурамишвили и Агмашенебели в г. Каспи. | E25: (Пр)-Газ Констракт | F25: Декабрь | G25: 9817.5 | H25: =G25-G25/1.18 -> 1497.5847 | J25: Сакорггаз
B26: BCP-220426-1/0(1.1.7) | C26: Рустави | D26: 1.1.7. В г. Рустави замена полиэтиленовых труб на фасадах корпусов (I и II этап). (P.2.72 (1 и 2)) (проектирование и строительство) | E26: Интерсервис 2011 | F26: Июль | G26: 33500 | H26: =G26-G26/1.18 -> 5110.1695 | I26: =G26-H26 -> 28389.831 | J26: Сакорггаз | K26: VI მ/რ VI კორპუსში მრიცხველების გამოტანა | N26: 1100 | O26: 79 | P26: =G26/N26 -> 30.454545 | Q26: დასრულდა
B27: BCP-220426-1/0(1.1.7) | C27: Рустави | D27: 1.1.7. В г. Рустави замена полиэтиленовых труб на фасадах корпусов (I и II этап). (P.2.72 (1 и 2)) (проектирование и строительство) | E27: Интерсервис 2011 | F27: Июль | G27: 42000 | H27: =G27-G27/1.18 -> 6406.7797 | J27: Сакорггаз | K27: მეგობრობის ქუჩა №30-ში მდებარე კორპუსი | N27: 750 | O27: 110 | P27: =G27/N27 -> 56 | Q27: დასრულდა
B28: BCP-220426-1/0(1.1.7) | C28: Рустави | D28: 1.1.7. В г. Рустави замена полиэтиленовых труб на фасадах корпусов (I и II этап). (P.2.72 (1 и 2)) (проектирование и строительство) | E28: Интерсервис 2011 | F28: Июль | G28: 44500 | H28: =G28-G28/1.18 -> 6788.1356 | J28: Сакорггаз | K28: ფალიაშვილის ქუჩა №1-ში მდებარე კორპუსი | N28: 700 | O28: 115 | P28: =G28/N28 -> 63.571429 | Q28: დასრულდა
B29: BSP-220502-1/0 | C29: Адигени | D29: в Абастумани, строит. сети вместе с Фондом Муниц. Развития (II этап 1.8 км.) (проектирование и строительство) | E29: Интер Газ | F29: Июль | G29: 132163.32 | H29: =G29-G29/1.18 -> 20160.506 | J29: SGG
B30: BS-220513-2/0 | C30: Дманиси | D30: Село Далари, строиетльство газораспределительной сети (газификация). (P.2.406) | E30: Бриджи | F30: Июль | G30: 142645 | H30: =G30-G30/1.18 -> 21759.407 | J30: SGG
B31: BCP-220321-1/0(1.1.10) | C31: Самтредия | D31: 1.1.10. Строительство питающего газопровода Самтредиа - Хони. (P.6.115) | E31: Газсервис | F31: Июль | G31: 950000 | H31: =G31-G31/1.18 -> 144915.25 | J31: Сакорггаз
B32: BSP-220502-2/0(1.1.5) | C32: Чиатура | D32: 1.1.5. Работы по реабилитации газопровода в г. Чиатура на улице Иашвили проведение. (P.6.53) | E32: Газсервис | F32: Июль | G32: 85000 | H32: =G32-G32/1.18 -> 12966.102 | J32: SGG
B33: BCP-220426-1/0(1.1.7) | C33: Рустави | D33: 1.1.7. В г. Рустави замена полиэтиленовых труб на фасадах корпусов (I и II этап). (P.2.72 (1 и 2)) (проектирование и строительство) | E33: Интерсервис 2011 | F33: Июль | G33: 27172.25 | H33: =G33-G33/1.18 -> 4144.9195 | J33: Сакорггаз
B34: BCP-220426-1/0(1.1.7) | C34: Рустави | D34: 1.1.7. В г. Рустави замена полиэтиленовых труб на фасадах корпусов (I и II этап). (P.2.72 (1 и 2)) (проектирование и строительство) | E34: Интерсервис 2011 | F34: Июнь | G34: 70450 | H34: =G34-G34/1.18 -> 10746.61 | J34: Сакорггаз | K34: მე-12-ე მიკრო რაიონი, №1 კორპუსი | N34: 1460 | O34: 0 | Q34: დასრულდა
B35: BC-220322-1/0 | C35: Рустави | D35: Вынос счетч. с корпусов ул. Костава №25, ул. Мегоброба №26. | E35: Интерсервис 2011 | F35: Июнь | G35: 34224 | H35: =G35-G35/1.18 -> 5220.6102 | J35: Сакорггаз | K35: კოსტავას №25-სა და მეგობრობის №26-ში | N35: 479 | O35: 80 | P35: =G35/N35 -> 71.448852 | Q35: =G35/O35 -> 427.8
B36: BCP-220321-1/0(1.1.1) | C36: Вани | D36: 1.1.1. В г. Вани, строительство газопровода от улицы Соломона II до центра с . Сулори. (P.6.121) | E36: Газсервис | F36: Июнь | G36: 910000 | H36: =G36-G36/1.18 -> 138813.56 | J36: Сакорггаз
B37: BCP-220321-1/0(1.1.10) | C37: Самтредия | D37: 1.1.10. Строительство питающего газопровода Самтредиа - Хони. (P.6.115) | E37: Газсервис | F37: Июнь | G37: 975000 | H37: =G37-G37/1.18 -> 148728.81 | J37: Сакорггаз
B38: BCP-220321-1/0(1.1.7) | C38: Терджола | D38: 1.1.7. В г. Тержола, поселке Метлахис Кархана, реабилитация питающего газопровода. (проектирование и строительство). (P.6.135) | E38: Газсервис | F38: Июнь | G38: 420000 | H38: =G38-G38/1.18 -> 64067.797 | J38: Сакорггаз
B39: BCP-220321-1/0(1.1.18) | C39: Кутаиси | D39: 1.1.18. В г. Кутаиси, реаибилитация газопровода по алее Агмашенебели. (P.6.799) | E39: Газсервис | F39: Июнь | G39: 270000 | H39: =G39-G39/1.18 -> 41186.441 | J39: Сакорггаз
B40: BSP-220429-1/0(1.1.4) | C40: Гурджаани | D40: 1.1.4. Окольцование газопровода для обеспечения стандартного газоснабжения г. Гурджаани и г. Лагодехи. (P.2.403) (проектирование и строительство) | E40: Интерсервис 2011 | F40: Июнь | G40: 305700 | H40: =G40-G40/1.18 -> 46632.203 | J40: SGG
B41: BCP-220328-1/0(1.2.4) | C41: Вани | D41: 1.2.4 С. Гора (проектирование и строительство) | E41: Интер Газ | F41: Июнь | G41: 747000 | H41: =G41-G41/1.18 -> 113949.15 | J41: Сакорггаз
B42: BCP-220328-1/0(1.2.1) | C42: Багдати | D42: 1.2.1. С. Рохи (проектирование и строительство) | E42: Интер Газ | F42: Июнь | G42: 1560000 | H42: =G42-G42/1.18 -> 237966.1 | J42: Сакорггаз
B43: BCP-220328-1/0(1.2.2) | C43: Вани | D43: 1.2.2 С. Зеиндари (проектирование и строительство) | E43: Интер Газ | F43: Июнь | G43: 1130000 | H43: =G43-G43/1.18 -> 172372.88 | J43: Сакорггаз
B44: BCP-220328-1/0(1.2.6) | C44: Вани | D44: 1.2.6 С. Перета (проектирование и строительство) | E44: Интер Газ | F44: Июнь | G44: 300000 | H44: =G44-G44/1.18 -> 45762.712 | J44: Сакорггаз
B45: BCP-220328-1/0(1.2.3) | C45: Вани | D45: 1.2.3 С. Шуагора (проектирование и строительство) | E45: Интер Газ | F45: Июнь | G45: 260000 | H45: =G45-G45/1.18 -> 39661.017 | J45: Сакорггаз
B46: BCP-220321-1/0(1.1.8) | C46: Терджола | D46: 1.1.8. В г. Терджола, реабилитация газопровода по ул. Леселидзе. (P.6.138) | E46: Газсервис | F46: Июнь | G46: 120000 | H46: =G46-G46/1.18 -> 18305.085 | J46: Сакорггаз
B47: BCP-220321-1/0(1.1.16) | C47: Кутаиси | D47: 1.1.16. В г. Кутаиси, реабилитация газопровода на ул. Гелати. (P.6.68) | E47: Газсервис | F47: Июнь | G47: 200000 | H47: =G47-G47/1.18 -> 30508.475 | J47: Сакорггаз
... B49: BS-220513-1/0 | C49: Дманиси | D49: Село Мтисдзири, строиетльство газораспределительной сети (газификация). (P.2.407) | E49: Бриджи | F49: Июнь | G49: 104630.23 | H49: =G49-G49/1.18 -> 15960.544 | J49: SGG
B50: BC-220322-1/0 | C50: Рустави | D50: Вынос счетч. С корпусов ул. Костава №25, ул. Мегоброба №26. | E50: Интерсервис 2011 | F50: Май | G50: 18624 | H50: =G50-G50/1.18 -> 2840.9492 | J50: Сакорггаз | K50: კოსტავას №25-სა და მეგობრობის №26-ში | N50: 548 | O50: 28 | P50: =G50/N50 -> 33.985401 | Q50: =G50/O50 -> 665.14286
B51: BC-220407-1/0 | C51: Гори | D51: 1.11 Реабилитация газопровода в селе Бербуки. (P 3.109) | E51: Газ Констракт | F51: Май | G51: 29442 | H51: =G51-G51/1.18 -> 4491.1525 | J51: Сакорггаз
B52: BS-210815-1/0 | C52: Гардабани | D52: Реаб. в селе Вахтангиси, Гардабанского муниципалитета включая замену и вынос счетчиков; | E52: Интерсервис 2011 | F52: Май | G52: 38553 | H52: =G52-G52/1.18 -> 5880.9661 | J52: SGG
B53: СC-210203-1/0 | D53: 1.2 Реабилитация газопровода в пос. Абастумани Адигенского Муниципалитета. 1.3 Вынос счётчиков на участках №50-51-52-56 в пос. Бакуриани. 1.4 Реабилитация газопровода Д-200мм. на улице Агмашенебели в пос. Бакуриани. 1.5 Реабилитация газопровода Д-150мм. на улице Триалети в пос. Бакуриани. 1.6 Замена наружных полиэтилиновых газопроводов в корпусах на ул. Руставели и ул. Месхети в Борджоми. 1.7 Вынос счётчиков в. Селе Папа пос. Бакуриани. 1.8 Реабилитация газопровода среднего давления проходящего от сёл Свенети и Бербуки Гориского муниципалитета по ул. Сухишвили г. Гори. 1.9 Реабилитация питающего газопровода от узла учёта до центра с. Меджврисхеви. 1.10 Реабилитация газопровода от с.Тквиави по направлению сёл тирдзниси-Дици. 1.11 Вынос и реабилитация питающнго газопровода в селе Бербуки. 1.12 Вынос-Замена счётчиков в г.Гори, реабилитация сети газопроводов на ул Пушкина, трассе Цхинвали, с. Свенети и с. Тинисхиди. 1.13 Реабилитация газопровода среднего Давления на пересечениях канала мелиорации в г. Гори-17км. По трассе Цхинвали. 1.14 Замена сушествующего стального газопровода на масту центральной железной дороги в г. Гори от 11 участкового узла до поселения Садгури (1 этап) (409.5 лари). 1.15 В г. Гори вынос счётчиков на улицах Тамар Мепе, Беруашвили, Чантурия, Багратиони, Кутаиси и Чочишвили. 1.16 Реабилитация газопровода на ул. Пушкина в г. Гори (1601.25 лари). 1.17 Реабилитация газопровода на ул. Размадзе г. Гори (1513.75 лари). 1.18 Реабилитация газопровода от ооо “ Гори“ до входа села Меджврисхеви (7962.5 лари). 1.19 Реабилитация газопровода в с. Оками Каспского муниципалитета. 1.20 Реабилитация газопровода в с. Перма Каспского муниципалитета. 1.21 Реабилитация газопровода проходящего через ветрозащитной полосы в с. Перма Каспского муниципалитета. 1.22 Реабилитация питающего газопровода от с Перма по направлению Чангилари. 1.23 Реабилитация газопровода на ул. Агмашенебели в г. Каспи. 1.24 Реабилитация газопровода на ул. Тависуплеба в г. Каспи. 1.25 Реабилитация сетей на улицах Мириан Мепе, Леселидзе, Костава, Руставели и Чавчавадзе в г. Каспи. 1.26 Реабилитация газопровода на перекрёстке улиц Агмашенебели и Габашвили в г. Каспи. 1.27 Вынос-замена счётчиков на улицах Церетели, 26 Мая, Шарикашвили, Гурамишвили и Агмашенебели в г. Каспи. | E53: (Пр)-Газ Констракт | F53: Март | G53: 5022.5 | H53: =G53-G53/1.18 -> 766.14407 | J53: Сакорггаз
B54: CS-220215-1/0 | C54: Чохатаури | D54: Реаб. Гаопр. На ул. Думбадзе | E54: (Пр)-Унимшени | F54: Март | G54: 1426.25 | H54: =G54-G54/1.18 -> 217.56356 | J54: SGG
B55: CC-220228-2/0 | C55: Рустави | D55: Вынос счетч. С корпусов ул. Костава №25, ул. Мегоброба №26. | E55: (Пр)-Интерсервис 2011 | F55: Март | G55: 2593.5 | H55: =G55-G55/1.18 -> 395.61864 | J55: Сакорггаз
B56: CC-220325-1/0 | C56: Кутаиси | D56: ул. Джибладзе реаб. Газопр. | E56: (Пр)-Газсервис | F56: Март | G56: 633.5 | H56: =G56-G56/1.18 -> 96.635593 | J56: Сакорггаз
B57: CC-220228-1/0 | C57: Кутаиси | D57: Участ. ул. Давида Агмашенебели (от ул. Гамсахурдиа до ул. Ниношвили) | E57: (Пр)-Газсервис | F57: Март | G57: 3024 | H57: =G57-G57/1.18 -> 461.28814 | J57: Сакорггаз
B58: BS-211019-1/0 | C58: Адигени | D58: В с. Вархани реабилитация подз. Газопровода. | E58: Газ Констракт | F58: Март | G58: 2939 | H58: =G58-G58/1.18 -> 448.32203 | J58: SGG
B59: BS-220304-1/0 | C59: Чиатура | D59: Реаб. Газопр. в с. Дарквети. d-40 mm (из за оползни) | E59: Газсервис | F59: Март | G59: 12801 | H59: =G59-G59/1.18 -> 1952.6949 | J59: SGG
B60: BS-211111-1/0 | C60: Ахмета | D60: Часть (30м) ул. Руставели | E60: Интерсервис 2011 | F60: Март | G60: 3751 | H60: =G60-G60/1.18 -> 572.18644 | J60: SGG
B61: BS-211124-2/0 | C61: Гардабани | D61: 1.11 Вынос счетчиков в с. Кесало Гардабанского муниципалитета | E61: Интерсервис 2011 | F61: Март | G61: 71076 | H61: =G61-G61/1.18 -> 10842.102 | J61: SGG
B62: BC-220310-1/0 | C62: Каспи | D62: 1.19 Реаб. Газоп. в с. Оками. | E62: Газ Констракт | F62: Март | G62: 135842 | H62: =G62-G62/1.18 -> 20721.661 | J62: Сакорггаз
B63: BC-220110-2/0 | C63: Каспи | D63: 1.20; 1.21; 1.22 Реаб. газоп. в с. Перма+от Перма в сторонй Чангилари+в Перма через ветрянную полосу. | E63: Газ Констракт | F63: Март | G63: 110443 | H63: =G63-G63/1.18 -> 16847.237 | J63: Сакорггаз
B64: BC-220110-1/0 | C64: Каспи | D64: ул. Костава, А. Церетели и Ширикашвили (пересечения Важа Пшавела и Цулукидзе) (I этап) | E64: Газ Констракт | F64: Март | G64: 47622 | H64: =G64-G64/1.18 -> 7264.3729 | J64: Сакорггаз
B65: BC-211203-1/0 | C65: Рустави | D65: Вынос счетчиков на ул. Тбилиси №22, №3 I-го прохода Мегоброба, ул. Руставели №16 и ул. Батуми №17 | E65: Интерсервис 2011 | F65: Март | G65: 22751 | H65: =G65-G65/1.18 -> 3470.4915 | J65: Сакорггаз
B66: BS-210815-1/0 | C66: Гардабани | D66: Реаб. в селе Вахтангиси, Гардабанского муниципалитета включая замену и вынос счетчиков; | E66: Интерсервис 2011 | F66: Март | G66: 65204 | H66: =G66-G66/1.18 -> 9946.3729 | J66: SGG
B67: BCP-220426-1/0(1.1.7) | C67: Рустави | D67: 1.1.7. В г. Рустави замена полиэтиленовых труб на фасадах корпусов (I и II этап). (P.2.72 (1 и 2)) (проектирование и строительство) | E67: Интерсервис 2011 | F67: Ноябрь | G67: 18000 | H67: =G67-G67/1.18 -> 2745.7627 | I67: =G67-H67 -> 15254.237 | J67: Сакорггаз | K67: VI მ/რ I კორპუსში მრიცხველების გამოტანა | N67: 0 | O67: 26 | P67: =G67/N67 -> #DIV/0! | Q67: დასრულდა
B68: BCP-220426-1/0(1.1.7) | C68: Рустави | D68: 1.1.7. В г. Рустави замена полиэтиленовых труб на фасадах корпусов (I и II этап). (P.2.72 (1 и 2)) (проектирование и строительство) | E68: Интерсервис 2011 | F68: Ноябрь | G68: 15000 | H68: =G68-G68/1.18 -> 2288.1356 | I68: =G68-H68 -> 12711.864 | J68: Сакорггаз | K68: VI მ/რ II კორპუსში მრიცხველების გამოტანა | N68: 0 | O68: 20 | P68: =G68/N68 -> #DIV/0! | Q68: დასრულდა
B69: BCP-220426-1/0(1.1.7) | C69: Рустави | D69: 1.1.7. В г. Рустави замена полиэтиленовых труб на фасадах корпусов (I и II этап). (P.2.72 (1 и 2)) (проектирование и строительство) | E69: Интерсервис 2011 | F69: Ноябрь | G69: 15000 | H69: =G69-G69/1.18 -> 2288.1356 | J69: Сакорггаз | K69: XVII მ/რ XI კორპუსში მრიცხველების გამოტანა | N69: 350 | O69: 34 | P69: =G69/N69 -> 42.857143 | Q69: დასრულდა
B70: BCP-220426-1/0(1.1.7) | C70: Рустави | D70: 1.1.7. В г. Рустави замена полиэтиленовых труб на фасадах корпусов (I и II этап). (P.2.72 (1 и 2)) (проектирование и строительство) | E70: Интерсервис 2011 | F70: Ноябрь | G70: 30000 | H70: =G70-G70/1.18 -> 4576.2712 | I70: =G70-H70 -> 25423.729 | J70: Сакорггаз | K70: დავით გარეჯის ქუჩა №21ა კორპუსი | N70: 450 | O70: 0 | P70: =G70/N70 -> 66.666667 | Q70: დასრულდა
B71: BCP-220426-1/0(1.1.7) | C71: Рустави | D71: 1.1.7. В г. Рустави замена полиэтиленовых труб на фасадах корпусов (I и II этап). (P.2.72 (1 и 2)) (проектирование и строительство) | E71: Интерсервис 2011 | F71: Ноябрь | G71: 35000 | H71: =G71-G71/1.18 -> 5338.9831 | I71: =G71-H71 -> 29661.017 | J71: Сакорггаз | K71: დავით გარეჯის ქუჩა №21ბ კორპუსი | N71: 500 | O71: 0 | P71: =G71/N71 -> 70 | Q71: დასრულდა
B72: BCP-220426-1/0(1.1.7) | C72: Рустави | D72: 1.1.7. В г. Рустави замена полиэтиленовых труб на фасадах корпусов (I и II этап). (P.2.72 (1 и 2)) (проектирование и строительство) | E72: Интерсервис 2011 | F72: Ноябрь | G72: 30000 | H72: =G72-G72/1.18 -> 4576.2712 | J72: Сакорггаз | K72: თოდრიას ქუჩა №17 კორპუსი | N72: 100 | O72: 0 | P72: =G72/N72 -> 300 | Q72: დასრულდა
B73: BCP-220426-1/0(1.1.7) | C73: Рустави | D73: 1.1.7. В г. Рустави замена полиэтиленовых труб на фасадах корпусов (I и II этап). (P.2.72 (1 и 2)) (проектирование и строительство) | E73: Интерсервис 2011 | F73: Ноябрь | G73: 30000 | H73: =G73-G73/1.18 -> 4576.2712 | J73: Сакорггаз | K73: თოდრიას ქუჩა №19 კორპუსი | N73: 450 | O73: 0 | P73: =G73/N73 -> 66.666667 | Q73: დასრულდა
B74: BCP-220426-1/0(1.1.7) | C74: Рустави | D74: 1.1.7. В г. Рустави замена полиэтиленовых труб на фасадах корпусов (I и II этап). (P.2.72 (1 и 2)) (проектирование и строительство) | E74: Интерсервис 2011 | F74: Ноябрь | G74: 25000 | H74: =G74-G74/1.18 -> 3813.5593 | J74: Сакорггаз | K74: თოდრიას ქუჩა №21 კორპუსი | N74: 700 | O74: 13 | P74: =G74/N74 -> 35.714286 | Q74: დასრულდა
B75: BCP-220426-1/0(1.1.7) | C75: Рустави | D75: 1.1.7. В г. Рустави замена полиэтиленовых труб на фасадах корпусов (I и II этап). (P.2.72 (1 и 2)) (проектирование и строительство) | E75: Интерсервис 2011 | F75: Ноябрь | G75: 25000 | H75: =G75-G75/1.18 -> 3813.5593 | J75: Сакорггаз | K75: მე-11-ე მიკრო რაიონი, №1 კორპუსი | N75: 650 | O75: 0 | P75: =G75/N75 -> 38.461538 | Q75: დასრულდა
B76: BCP-220426-1/0(1.1.7) | C76: Рустави | D76: 1.1.7. В г. Рустави замена полиэтиленовых труб на фасадах корпусов (I и II этап). (P.2.72 (1 и 2)) (проектирование и строительство) | E76: Интерсервис 2011 | F76: Ноябрь | G76: 90000 | H76: =G76-G76/1.18 -> 13728.814 | J76: Сакорггаз | K76: მე-12-ე მიკრო რაიონი, №1 კორპუსი | N76: 1150 | O76: 126 | P76: =G76/N76 -> 78.26087 | Q76: დასრულდა
B77: BCP-220426-1/0(1.1.7) | C77: Рустави | D77: 1.1.7. В г. Рустави замена полиэтиленовых труб на фасадах корпусов (I и II этап). (P.2.72 (1 и 2)) (проектирование и строительство) | E77: Интерсервис 2011 | F77: Ноябрь | G77: 32000 | H77: =G77-G77/1.18 -> 4881.3559 | J77: Сакорггаз | K77: მე-17-ე მიკრო რაიონი, №1 კორპუსი | N77: 750 | O77: 0 | P77: =G77/N77 -> 42.666667 | Q77: დასრულდა
B78: BCP-220426-1/0(1.1.7) | C78: Рустави | D78: 1.1.7. В г. Рустави замена полиэтиленовых труб на фасадах корпусов (I и II этап). (P.2.72 (1 и 2)) (проектирование и строительство) | E78: Интерсервис 2011 | F78: Ноябрь | G78: 60000 | H78: =G78-G78/1.18 -> 9152.5424 | J78: Сакорггаз | K78: მე-17-ე მიკრო რაიონი, №15 კორპუსი | N78: 700 | O78: 108 | P78: =G78/N78 -> 85.714286 | Q78: დასრულდა
B79: BCP-220426-1/0(1.1.7) | C79: Рустави | D79: 1.1.7. В г. Рустави замена полиэтиленовых труб на фасадах корпусов (I и II этап). (P.2.72 (1 и 2)) (проектирование и строительство) | E79: Интерсервис 2011 | F79: Ноябрь | G79: 18000 | H79: =G79-G79/1.18 -> 2745.7627 | J79: Сакорггаз | K79: მე-17-ე მიკრო რაიონი, №25 კორპუსი | N79: 190 | O79: 22 | P79: =G79/N79 -> 94.736842 | Q79: დასრულდა
B80: BCP-220426-1/0(1.1.7) | C80: Рустави | D80: 1.1.7. В г. Рустави замена полиэтиленовых труб на фасадах корпусов (I и II этап). (P.2.72 (1 и 2)) (проектирование и строительство) | E80: Интерсервис 2011 | F80: Ноябрь | G80: 12000 | H80: =G80-G80/1.18 -> 1830.5085 | J80: Сакорггаз | K80: მე-17-ე მიკრო რაიონი, №26 კორპუსი | N80: 210 | O80: 8 | P80: =G80/N80 -> 57.142857 | Q80: დასრულდა
B81: BCP-220426-1/0(1.1.7) | C81: Рустави | D81: 1.1.7. В г. Рустави замена полиэтиленовых труб на фасадах корпусов (I и II этап). (P.2.72 (1 и 2)) (проектирование и строительство) | E81: Интерсервис 2011 | F81: Ноябрь | G81: 20000 | H81: =G81-G81/1.18 -> 3050.8475 | J81: Сакорггаз | K81: მე-19-ე მიკრო რაიონი, №12 კორპუსი | N81: 60 | O81: 66 | P81: =G81/N81 -> 333.33333 | Q81: დასრულდა
B82: BCP-220426-1/0(1.1.7) | C82: Рустави | D82: 1.1.7. В г. Рустави замена полиэтиленовых труб на фасадах корпусов (I и II этап). (P.2.72 (1 и 2)) (проектирование и строительство) | E82: Интерсервис 2011 | F82: Ноябрь | G82: 10000 | H82: =G82-G82/1.18 -> 1525.4237 | J82: Сакорггаз | K82: მე-19-ე მიკრო რაიონი, №16 კორპუსი | N82: 0 | O82: 35 | P82: =G82/N82 -> #DIV/0! | Q82: დასრულდა
B83: BCP-220426-1/0(1.1.7) | C83: Рустави | D83: 1.1.7. В г. Рустави замена полиэтиленовых труб на фасадах корпусов (I и II этап). (P.2.72 (1 и 2)) (проектирование и строительство) | E83: Интерсервис 2011 | F83: Ноябрь | G83: 20000 | H83: =G83-G83/1.18 -> 3050.8475 | J83: Сакорггаз | K83: მე-19-ე მიკრო რაიონი, №24 კორპუსი | N83: 350 | O83: 0 | P83: =G83/N83 -> 57.142857 | Q83: დასრულდა
... B91: BCP-220426-1/0(1.1.7) | C91: Рустави | D91: 1.1.7. В г. Рустави замена полиэтиленовых труб на фасадах корпусов (I и II этап). (P.2.72 (1 и 2)) (проектирование и строительство) | E91: Интерсервис 2011 | F91: Ноябрь | G91: 10000 | H91: =G91-G91/1.18 -> 1525.4237 | J91: Сакорггаз | K91: წმინდა ნინოს ქუჩა №2 კორპუსი | N91: 30 | O91: 0 | P91: =G91/N91 -> 333.33333 | Q91: დასრულდა
B92: BCP-220328-1/0(1.2.1) | C92: Багдати | D92: 1.2.1. С. Рохи (проектирование и строительство) P.6.127 (5) | E92: Интер Газ | F92: Ноябрь | G92: 1000000 | H92: =G92-G92/1.18 -> 152542.37 | J92: Сакорггаз
B93: BCP-220328-1/0(1.2.2) | C93: Вани | D93: 1.2.2 С. Зеиндари (проектирование и строительство) P.6.127 (5) | E93: Интер Газ | F93: Ноябрь | G93: 550000 | H93: =G93-G93/1.18 -> 83898.305 | J93: Сакорггаз
B94: BCP-220328-1/0(1.2.3) | C94: Вани | D94: 1.2.3 С. Шуагора (проектирование и строительство) P.6.127 (5) | E94: Интер Газ | F94: Ноябрь | G94: 550000 | H94: =G94-G94/1.18 -> 83898.305 | J94: Сакорггаз
B95: BCP-220328-1/0(1.2.4) | C95: Вани | D95: 1.2.4 С. Гора (проектирование и строительство) P.6.127 (5) | E95: Интер Газ | F95: Ноябрь | G95: 400000 | H95: =G95-G95/1.18 -> 61016.949 | J95: Сакорггаз
B96: BCP-220328-1/0(1.2.6) | C96: Вани | D96: 1.2.6 С. Перета (проектирование и строительство) P.6.127 (5) | E96: Интер Газ | F96: Ноябрь | G96: 330000 | H96: =G96-G96/1.18 -> 50338.983 | J96: Сакорггаз
B97: BCP-220328-1/0(1.2.5) | C97: Вани | D97: 1.2.5 С. Зедагора (проектирование и строительство) P.6.127 (5) | E97: Интер Газ | F97: Ноябрь | G97: 120000 | H97: =G97-G97/1.18 -> 18305.085 | J97: Сакорггаз
B98: BCP-220328-2/0(1.2.1) | C98: Терджола | D98: 1.2.1 Участок Муджирети-Мухура (проектирование и строительство) (P.6.144) | E98: Интер Газ | F98: Ноябрь | G98: 1500000 | H98: =G98-G98/1.18 -> 228813.56 | J98: Сакорггаз
